Workbook

Sheet Legend
A1: GST Scrutiny Tool – Rule Matrix
A3: Sheet | B3: Purpose
A4: Rule Matrix | B4: One row per check: legal ref, data sources, logic, threshold, severity, exposure basis, action. Yellow columns (Status, Exposure ₹, Remarks) are for the user/system to fill.
A5: Data Sources | B5: Inputs the tool must ingest, with key fields.
A6: Summary | B6: Auto counts by module/severity/status and total exposure (formulas).
A7: Sec 73-74 Classifier | B7: Per flagged issue: enter Rule ID, FY, tax, fraud indicators, payment stage, interest dates → auto section (73/74/74A), SCN & order deadlines, limitation status, penalty, interest, s.128A flag.
A8: Client Master | B8: Client list: name, GSTIN, industry (drop-down) and Y/N flags (Exports, Imports, SEZ, E-invoice, Multi-GSTIN). Auto-counts applicable rules.
A9: Client Checklist | B9: Select client → auto-filtered list of applicable checks (industry + flags).
A10: Applicability | B10: Rule × industry matrix (Y/N, editable) + client flag required per rule. Change a Y/N here and every client's checklist updates.
A11: Validation Log | B11: What was verified/corrected on 21-Sep-2026, with sources. Read before using the matrix.
A12: Limitation Inputs | B12: Annual return due dates, COVID-extended s.73 deadlines, interest rate, as-of date (editable, blue).
A14: Status values | B14: Pending / Pass / Fail / N.A. (drop-down)
A15: Severity | B15: High = direct tax exposure likely; Med = exposure possible/conditional; Low = procedural
... A18: Example row | B18: Rule Matrix row 2 (B-01) filled with sample Status 'Fail', Exposure ₹1,25,000 to show format.

Sheet Validation Log
A1: # | B1: Area | C1: Provision checked | D1: Result | E1: Finding / correction applied | F1: Primary source
A2: 1 | B2: Demand | C2: s.73/74 vs s.74A | D2: Verified | E2: FY ≤ 2023-24 → s.73/74; FY 2024-25 onwards → s.74A (in force 01.11.2024). SCN 42 months from AR due date; order 12 months (+6). | F2: Finance (No.2) Act 2024
A3: 2 | B3: Demand | C3: s.74A de minimis | D3: Corrected (added) | E3: No SCN where tax < ₹1,000 per FY – new rule K + classifier flag. | F3: s.74A(1) proviso
A4: 3 | B4: Demand | C4: Reduced-penalty windows | D4: Verified | E4: 30 days (s.73/74) vs 60 days (s.74A). | F4: s.74A(5),(8)
A5: 4 | B5: Demand | C5: 168A COVID extensions | D5: Flag – sub judice | E5: Madras HC (Tata Play, 12.06.2025) struck down 9/2023 & 56/2023; Telangana HC (Brunda Infra) upheld; SC SLP (HCC-SEW-MEIL-AAG JV) – check final outcome before relying. | F5: Notfn 9/2023, 56/2023
A6: 5 | B6: Demand | C6: Suppression standard | D6: Added | E6: SC: Uniworth Textiles, Pushpam Pharmaceuticals, Continental Foundation – intent must be pleaded and proved. | F6: SC judgments
A7: 6 | B7: ITC | C7: s.17(5)(d) plant & machinery | D7: Corrected | E7: Earlier matrix tagged FA 2025 amendment to cl.(c); correct clause is (d) with Explanation 2, retro 01.07.2017, overriding Safari Retreats. | F7: Finance Act 2025, s.119 of Bill
A8: 7 | B8: CN | C8: s.34(2) proviso | D8: Verified + dated | E8: Recipient-reversal condition effective 01.10.2025 (Notfn 16/2025-CT), enforced via IMS. | F8: Finance Act 2025
A9: 8 | B9: CN | C9: s.15(3)(b) post-sale discount | D9: Updated | E9: FA 2026 substitution (no pre-agreement) enacted but awaiting notification – old conditions apply until notified. Circ 251/08/2025: no recipient reversal on financial CNs. | F9: FA 2026; Circ 251/08/2025
A10: 9 | B10: CN | C10: s.16(4) debit note date | D10: Corrected | E10: Amendment is FA 2020 w.e.f. 01.01.2021 (not FA 2022). | F10: Finance Act 2020
A11: 10 | B11: POS | C11: Intermediary s.13(8)(b) | D11: Updated | E11: Omitted by FA 2026 s.157 w.e.f. 30.03.2026 (prospective). Legacy periods remain exposed; inbound foreign intermediary now RCM. | F11: Finance Act 2026
A12: 11 | B12: Rates | C12: Hotel & restaurant | D12: Updated | E12: Rooms ≤ ₹7,500: 5% w/o ITC; > ₹7,500: 18% (22.09.2025). Restaurant at specified premises 18% with ITC (Notfn 05/2025 w.e.f. 01.04.2025). | F12: Notfn 05/2025, 15/2025-CT(R)
A13: 12 | B13: Rates | C13: GTA | D13: Updated | E13: 12% FCM replaced by 18% with ITC from 22.09.2025; Annexure V by 31 March (not 15 March). | F13: Notfn 15/2025-CT(R)
... A23: 22 | B23: ITC | C23: Rule 37A / s.16(2)(c) | D23: Added defence | E23: Suncraft Energy line – bona fide recipient; verify post-2022 s.16(2)(aa) position. | F23: Cal HC; SC SLP dismissed
A25: Checked on 21-Sep-2026 against CBIC notifications/circulars and reported judgments via web sources. Re-verify before filing any reply; law and SC outcomes may have moved.

Sheet Client Master
A1: Client Name | B1: GSTIN | C1: Industry | D1: Exports | E1: Imports | F1: SEZ Supplies | G1: E-invoice | H1: Multi-GSTIN | I1: Applicable Rules (auto)
A2: Sample Developers LLP | B2: 27AAAAA0000A1Z5 | C2: Real Estate Developer | D2: N | E2: N | F2: N | G2: Y | H2: N | I2: =IF(C2="","",IFERROR(SUMPRODUCT((INDEX(Applicability!$E$2:$O$142,0,MATCH(C2,Applicability!$E$1:$O$1,0))="Y")*((Applicability!$D$2:$D$142="")+(Applicability!$D$2:$D$142="Exports")*(D2="Y")+(Applicability!$D$2:$D$142="Imports")*(E2="Y")+(Applicability!$D$2:$D$142="SEZ Supplies")*(F2="Y")+(Applicability!$D$2:$D$142="E-invoice")*(G2="Y")+(Applicability!$D$2:$D$142="Multi-GSTIN")*(H2="Y"))),"Check industry")) -> 96
A3: Sample Traders | B3: 27BBBBB0000B1Z5 | C3: Trader / Retailer | D3: N | E3: Y | F3: N | G3: N | H3: N | I3: =IF(C3="","",IFERROR(SUMPRODUCT((INDEX(Applicability!$E$2:$O$142,0,MATCH(C3,Applicability!$E$1:$O$1,0))="Y")*((Applicability!$D$2:$D$142="")+(Applicability!$D$2:$D$142="Exports")*(D3="Y")+(Applicability!$D$2:$D$142="Imports")*(E3="Y")+(Applicability!$D$2:$D$142="SEZ Supplies")*(F3="Y")+(Applicability!$D$2:$D$142="E-invoice")*(G3="Y")+(Applicability!$D$2:$D$142="Multi-GSTIN")*(H3="Y"))),"Check industry")) -> 96
A4: Sample Co-op Bank Ltd | B4: 27CCCCC0000C1Z5 | C4: Bank / NBFC / Co-op Bank | D4: N | E4: N | F4: N | G4: Y | H4: Y | I4: =IF(C4="","",IFERROR(SUMPRODUCT((INDEX(Applicability!$E$2:$O$142,0,MATCH(C4,Applicability!$E$1:$O$1,0))="Y")*((Applicability!$D$2:$D$142="")+(Applicability!$D$2:$D$142="Exports")*(D4="Y")+(Applicability!$D$2:$D$142="Imports")*(E4="Y")+(Applicability!$D$2:$D$142="SEZ Supplies")*(F4="Y")+(Applicability!$D$2:$D$142="E-invoice")*(G4="Y")+(Applicability!$D$2:$D$142="Multi-GSTIN")*(H4="Y"))),"Check industry")) -> 93
A5: Sample Restaurant | B5: 27DDDDD0000D1Z5 | C5: Hotel / Restaurant | D5: N | E5: N | F5: N | G5: N | H5: N | I5: =IF(C5="","",IFERROR(SUMPRODUCT((INDEX(Applicability!$E$2:$O$142,0,MATCH(C5,Applicability!$E$1:$O$1,0))="Y")*((Applicability!$D$2:$D$142="")+(Applicability!$D$2:$D$142="Exports")*(D5="Y")+(Applicability!$D$2:$D$142="Imports")*(E5="Y")+(Applicability!$D$2:$D$142="SEZ Supplies")*(F5="Y")+(Applicability!$D$2:$D$142="E-invoice")*(G5="Y")+(Applicability!$D$2:$D$142="Multi-GSTIN")*(H5="Y"))),"Check industry")) -> 91
A6: Sample IT Services Pvt Ltd | B6: 27EEEEE0000E1Z5 | C6: Service Provider | D6: Y | E6: Y | F6: Y | G6: Y | H6: N | I6: =IF(C6="","",IFERROR(SUMPRODUCT((INDEX(Applicability!$E$2:$O$142,0,MATCH(C6,Applicability!$E$1:$O$1,0))="Y")*((Applicability!$D$2:$D$142="")+(Applicability!$D$2:$D$142="Exports")*(D6="Y")+(Applicability!$D$2:$D$142="Imports")*(E6="Y")+(Applicability!$D$2:$D$142="SEZ Supplies")*(F6="Y")+(Applicability!$D$2:$D$142="E-invoice")*(G6="Y")+(Applicability!$D$2:$D$142="Multi-GSTIN")*(H6="Y"))),"Check industry")) -> 97
I7: =IF(C7="","",IFERROR(SUMPRODUCT((INDEX(Applicability!$E$2:$O$142,0,MATCH(C7,Applicability!$E$1:$O$1,0))="Y")*((Applicability!$D$2:$D$142="")+(Applicability!$D$2:$D$142="Exports")*(D7="Y")+(Applicability!$D$2:$D$142="Imports")*(E7="Y")+(Applicability!$D$2:$D$142="SEZ Supplies")*(F7="Y")+(Applicability!$D$2:$D$142="E-invoice")*(G7="Y")+(Applicability!$D$2:$D$142="Multi-GSTIN")*(H7="Y"))),"Check industry"))
I8: =IF(C8="","",IFERROR(SUMPRODUCT((INDEX(Applicability!$E$2:$O$142,0,MATCH(C8,Applicability!$E$1:$O$1,0))="Y")*((Applicability!$D$2:$D$142="")+(Applicability!$D$2:$D$142="Exports")*(D8="Y")+(Applicability!$D$2:$D$142="Imports")*(E8="Y")+(Applicability!$D$2:$D$142="SEZ Supplies")*(F8="Y")+(Applicability!$D$2:$D$142="E-invoice")*(G8="Y")+(Applicability!$D$2:$D$142="Multi-GSTIN")*(H8="Y"))),"Check industry"))
I9: =IF(C9="","",IFERROR(SUMPRODUCT((INDEX(Applicability!$E$2:$O$142,0,MATCH(C9,Applicability!$E$1:$O$1,0))="Y")*((Applicability!$D$2:$D$142="")+(Applicability!$D$2:$D$142="Exports")*(D9="Y")+(Applicability!$D$2:$D$142="Imports")*(E9="Y")+(Applicability!$D$2:$D$142="SEZ Supplies")*(F9="Y")+(Applicability!$D$2:$D$142="E-invoice")*(G9="Y")+(Applicability!$D$2:$D$142="Multi-GSTIN")*(H9="Y"))),"Check industry"))
I10: =IF(C10="","",IFERROR(SUMPRODUCT((INDEX(Applicability!$E$2:$O$142,0,MATCH(C10,Applicability!$E$1:$O$1,0))="Y")*((Applicability!$D$2:$D$142="")+(Applicability!$D$2:$D$142="Exports")*(D10="Y")+(Applicability!$D$2:$D$142="Imports")*(E10="Y")+(Applicability!$D$2:$D$142="SEZ Supplies")*(F10="Y")+(Applicability!$D$2:$D$142="E-invoice")*(G10="Y")+(Applicability!$D$2:$D$142="Multi-GSTIN")*(H10="Y"))),"Check industry"))
I11: =IF(C11="","",IFERROR(SUMPRODUCT((INDEX(Applicability!$E$2:$O$142,0,MATCH(C11,Applicability!$E$1:$O$1,0))="Y")*((Applicability!$D$2:$D$142="")+(Applicability!$D$2:$D$142="Exports")*(D11="Y")+(Applicability!$D$2:$D$142="Imports")*(E11="Y")+(Applicability!$D$2:$D$142="SEZ Supplies")*(F11="Y")+(Applicability!$D$2:$D$142="E-invoice")*(G11="Y")+(Applicability!$D$2:$D$142="Multi-GSTIN")*(H11="Y"))),"Check industry"))
I12: =IF(C12="","",IFERROR(SUMPRODUCT((INDEX(Applicability!$E$2:$O$142,0,MATCH(C12,Applicability!$E$1:$O$1,0))="Y")*((Applicability!$D$2:$D$142="")+(Applicability!$D$2:$D$142="Exports")*(D12="Y")+(Applicability!$D$2:$D$142="Imports")*(E12="Y")+(Applicability!$D$2:$D$142="SEZ Supplies")*(F12="Y")+(Applicability!$D$2:$D$142="E-invoice")*(G12="Y")+(Applicability!$D$2:$D$142="Multi-GSTIN")*(H12="Y"))),"Check industry"))
I13: =IF(C13="","",IFERROR(SUMPRODUCT((INDEX(Applicability!$E$2:$O$142,0,MATCH(C13,Applicability!$E$1:$O$1,0))="Y")*((Applicability!$D$2:$D$142="")+(Applicability!$D$2:$D$142="Exports")*(D13="Y")+(Applicability!$D$2:$D$142="Imports")*(E13="Y")+(Applicability!$D$2:$D$142="SEZ Supplies")*(F13="Y")+(Applicability!$D$2:$D$142="E-invoice")*(G13="Y")+(Applicability!$D$2:$D$142="Multi-GSTIN")*(H13="Y"))),"Check industry"))
I14: =IF(C14="","",IFERROR(SUMPRODUCT((INDEX(Applicability!$E$2:$O$142,0,MATCH(C14,Applicability!$E$1:$O$1,0))="Y")*((Applicability!$D$2:$D$142="")+(Applicability!$D$2:$D$142="Exports")*(D14="Y")+(Applicability!$D$2:$D$142="Imports")*(E14="Y")+(Applicability!$D$2:$D$142="SEZ Supplies")*(F14="Y")+(Applicability!$D$2:$D$142="E-invoice")*(G14="Y")+(Applicability!$D$2:$D$142="Multi-GSTIN")*(H14="Y"))),"Check industry"))
I15: =IF(C15="","",IFERROR(SUMPRODUCT((INDEX(Applicability!$E$2:$O$142,0,MATCH(C15,Applicability!$E$1:$O$1,0))="Y")*((Applicability!$D$2:$D$142="")+(Applicability!$D$2:$D$142="Exports")*(D15="Y")+(Applicability!$D$2:$D$142="Imports")*(E15="Y")+(Applicability!$D$2:$D$142="SEZ Supplies")*(F15="Y")+(Applicability!$D$2:$D$142="E-invoice")*(G15="Y")+(Applicability!$D$2:$D$142="Multi-GSTIN")*(H15="Y"))),"Check industry"))
I16: =IF(C16="","",IFERROR(SUMPRODUCT((INDEX(Applicability!$E$2:$O$142,0,MATCH(C16,Applicability!$E$1:$O$1,0))="Y")*((Applicability!$D$2:$D$142="")+(Applicability!$D$2:$D$142="Exports")*(D16="Y")+(Applicability!$D$2:$D$142="Imports")*(E16="Y")+(Applicability!$D$2:$D$142="SEZ Supplies")*(F16="Y")+(Applicability!$D$2:$D$142="E-invoice")*(G16="Y")+(Applicability!$D$2:$D$142="Multi-GSTIN")*(H16="Y"))),"Check industry"))
I17: =IF(C17="","",IFERROR(SUMPRODUCT((INDEX(Applicability!$E$2:$O$142,0,MATCH(C17,Applicability!$E$1:$O$1,0))="Y")*((Applicability!$D$2:$D$142="")+(Applicability!$D$2:$D$142="Exports")*(D17="Y")+(Applicability!$D$2:$D$142="Imports")*(E17="Y")+(Applicability!$D$2:$D$142="SEZ Supplies")*(F17="Y")+(Applicability!$D$2:$D$142="E-invoice")*(G17="Y")+(Applicability!$D$2:$D$142="Multi-GSTIN")*(H17="Y"))),"Check industry"))
I18: =IF(C18="","",IFERROR(SUMPRODUCT((INDEX(Applicability!$E$2:$O$142,0,MATCH(C18,Applicability!$E$1:$O$1,0))="Y")*((Applicability!$D$2:$D$142="")+(Applicability!$D$2:$D$142="Exports")*(D18="Y")+(Applicability!$D$2:$D$142="Imports")*(E18="Y")+(Applicability!$D$2:$D$142="SEZ Supplies")*(F18="Y")+(Applicability!$D$2:$D$142="E-invoice")*(G18="Y")+(Applicability!$D$2:$D$142="Multi-GSTIN")*(H18="Y"))),"Check industry"))
... I61: =IF(C61="","",IFERROR(SUMPRODUCT((INDEX(Applicability!$E$2:$O$142,0,MATCH(C61,Applicability!$E$1:$O$1,0))="Y")*((Applicability!$D$2:$D$142="")+(Applicability!$D$2:$D$142="Exports")*(D61="Y")+(Applicability!$D$2:$D$142="Imports")*(E61="Y")+(Applicability!$D$2:$D$142="SEZ Supplies")*(F61="Y")+(Applicability!$D$2:$D$142="E-invoice")*(G61="Y")+(Applicability!$D$2:$D$142="Multi-GSTIN")*(H61="Y"))),"Check industry"))

Sheet Client Checklist
A1: Select Client | B1: Sample Developers LLP | D1: Pick a client in B1 – list below refreshes. For working papers, copy-paste values into a client tab (statuses here don't move with the list).
A2: Industry | B2: =IFERROR(INDEX('Client Master'!$C$2:$C$61,MATCH($B$1,'Client Master'!$A$2:$A$61,0)),"") -> Real Estate Developer
A3: Client flags | B3: Exports | C3: Imports | D3: SEZ Supplies | E3: E-invoice | F3: Multi-GSTIN
B4: =IFERROR(INDEX('Client Master'!$D$2:$D$61,MATCH($B$1,'Client Master'!$A$2:$A$61,0)),"N") -> N | C4: =IFERROR(INDEX('Client Master'!$E$2:$E$61,MATCH($B$1,'Client Master'!$A$2:$A$61,0)),"N") -> N | D4: =IFERROR(INDEX('Client Master'!$F$2:$F$61,MATCH($B$1,'Client Master'!$A$2:$A$61,0)),"N") -> N | E4: =IFERROR(INDEX('Client Master'!$G$2:$G$61,MATCH($B$1,'Client Master'!$A$2:$A$61,0)),"N") -> Y | F4: =IFERROR(INDEX('Client Master'!$H$2:$H$61,MATCH($B$1,'Client Master'!$A$2:$A$61,0)),"N") -> N
A5: Applicable rules | B5: =SUM(AA8:AA148) -> 96 | Z5: =IFERROR(MATCH($B$2,Applicability!$E$1:$O$1,0),0) -> 1
A7: Sr | B7: Rule ID | C7: Module | D7: Check | E7: Legal Reference | F7: Logic / Test | G7: Threshold | H7: Severity | I7: Action | Z7: Helper: Rule | AA7: Applies | AB7: Seq
A8: =IF(1>$B$5,"",1) -> 1 | B8: =IF(A8="","",INDEX($Z$8:$Z$148,MATCH(A8,$AB$8:$AB$148,0))) -> A-01 | C8: =IF(B8="","",INDEX('Rule Matrix'!$B$2:$B$142,MATCH(B8,'Rule Matrix'!$A$2:$A$142,0))) -> A. Data Integrity | D8: =IF(B8="","",INDEX('Rule Matrix'!$C$2:$C$142,MATCH(B8,'Rule Matrix'!$A$2:$A$142,0))) -> GSTIN master validation | E8: =IF(B8="","",INDEX('Rule Matrix'!$D$2:$D$142,MATCH(B8,'Rule Matrix'!$A$2:$A$142,0))) -> Rule 10A/21A | F8: =IF(B8="","",INDEX('Rule Matrix'!$F$2:$F$142,MATCH(B8,'Rule Matrix'!$A$2:$A$142,0))) -> Check each vendor/customer GSTIN active on invoice date; flag cancelled (incl. retrospective), suspended, composition | G8: =IF(B8="","",INDEX('Rule Matrix'!$G$2:$G$142,MATCH(B8,'Rule Matrix'!$A$2:$A$142,0))) -> Any mismatch | H8: =IF(B8="","",INDEX('Rule Matrix'!$H$2:$H$142,MATCH(B8,'Rule Matrix'!$A$2:$A$142,0))) -> High | I8: =IF(B8="","",INDEX('Rule Matrix'!$J$2:$J$142,MATCH(B8,'Rule Matrix'!$A$2:$A$142,0))) -> Reverse ITC; obtain vendor clarification | Z8: =Applicability!A2 -> A-01 | AA8: =IF($Z$5=0,0,IF(AND(INDEX(Applicability!$E$2:$O$2,1,$Z$5)="Y",OR(Applicability!$D$2="",IFERROR(INDEX($B$4:$F$4,MATCH(Applicability!$D$2,$B$3:$F$3,0)),"N")="Y")),1,0)) -> 1 | AB8: =IF(AA8=1,SUM(AA$8:AA8),"") -> 1
A9: =IF(2>$B$5,"",2) -> 2 | B9: =IF(A9="","",INDEX($Z$8:$Z$148,MATCH(A9,$AB$8:$AB$148,0))) -> A-02 | C9: =IF(B9="","",INDEX('Rule Matrix'!$B$2:$B$142,MATCH(B9,'Rule Matrix'!$A$2:$A$142,0))) -> A. Data Integrity | D9: =IF(B9="","",INDEX('Rule Matrix'!$C$2:$C$142,MATCH(B9,'Rule Matrix'!$A$2:$A$142,0))) -> Period & return filing completeness | E9: =IF(B9="","",INDEX('Rule Matrix'!$D$2:$D$142,MATCH(B9,'Rule Matrix'!$A$2:$A$142,0))) -> s.37/39/44 | F9: =IF(B9="","",INDEX('Rule Matrix'!$F$2:$F$142,MATCH(B9,'Rule Matrix'!$A$2:$A$142,0))) -> All GSTR-1/3B/9/9C filed for all periods; compute delay days | G9: =IF(B9="","",INDEX('Rule Matrix'!$G$2:$G$142,MATCH(B9,'Rule Matrix'!$A$2:$A$142,0))) -> Any non-filing | H9: =IF(B9="","",INDEX('Rule Matrix'!$H$2:$H$142,MATCH(B9,'Rule Matrix'!$A$2:$A$142,0))) -> Med | I9: =IF(B9="","",INDEX('Rule Matrix'!$J$2:$J$142,MATCH(B9,'Rule Matrix'!$A$2:$A$142,0))) -> File pending; pay late fee | Z9: =Applicability!A3 -> A-02 | AA9: =IF($Z$5=0,0,IF(AND(INDEX(Applicability!$E$3:$O$3,1,$Z$5)="Y",OR(Applicability!$D$3="",IFERROR(INDEX($B$4:$F$4,MATCH(Applicability!$D$3,$B$3:$F$3,0)),"N")="Y")),1,0)) -> 1 | AB9: =IF(AA9=1,SUM(AA$8:AA9),"") -> 2
A10: =IF(3>$B$5,"",3) -> 3 | B10: =IF(A10="","",INDEX($Z$8:$Z$148,MATCH(A10,$AB$8:$AB$148,0))) -> A-03 | C10: =IF(B10="","",INDEX('Rule Matrix'!$B$2:$B$142,MATCH(B10,'Rule Matrix'!$A$2:$A$142,0))) -> A. Data Integrity | D10: =IF(B10="","",INDEX('Rule Matrix'!$C$2:$C$142,MATCH(B10,'Rule Matrix'!$A$2:$A$142,0))) -> Books vs return data completeness | E10: =IF(B10="","",INDEX('Rule Matrix'!$D$2:$D$142,MATCH(B10,'Rule Matrix'!$A$2:$A$142,0))) -> — | F10: =IF(B10="","",INDEX('Rule Matrix'!$F$2:$F$142,MATCH(B10,'Rule Matrix'!$A$2:$A$142,0))) -> Sum of registers = GL control accounts; all GSTINs of PAN covered | G10: =IF(B10="","",INDEX('Rule Matrix'!$G$2:$G$142,MATCH(B10,'Rule Matrix'!$A$2:$A$142,0))) -> Diff > ₹1,000 | H10: =IF(B10="","",INDEX('Rule Matrix'!$H$2:$H$142,MATCH(B10,'Rule Matrix'!$A$2:$A$142,0))) -> Med | I10: =IF(B10="","",INDEX('Rule Matrix'!$J$2:$J$142,MATCH(B10,'Rule Matrix'!$A$2:$A$142,0))) -> Reconcile registers to GL | Z10: =Applicability!A4 -> A-03 | AA10: =IF($Z$5=0,0,IF(AND(INDEX(Applicability!$E$4:$O$4,1,$Z$5)="Y",OR(Applicability!$D$4="",IFERROR(INDEX($B$4:$F$4,MATCH(Applicability!$D$4,$B$3:$F$3,0)),"N")="Y")),1,0)) -> 1 | AB10: =IF(AA10=1,SUM(AA$8:AA10),"") -> 3
A11: =IF(4>$B$5,"",4) -> 4 | B11: =IF(A11="","",INDEX($Z$8:$Z$148,MATCH(A11,$AB$8:$AB$148,0))) -> B-01 | C11: =IF(B11="","",INDEX('Rule Matrix'!$B$2:$B$142,MATCH(B11,'Rule Matrix'!$A$2:$A$142,0))) -> B. ITC Eligibility (s.16) | D11: =IF(B11="","",INDEX('Rule Matrix'!$C$2:$C$142,MATCH(B11,'Rule Matrix'!$A$2:$A$142,0))) -> ITC claimed vs GSTR-2B | E11: =IF(B11="","",INDEX('Rule Matrix'!$D$2:$D$142,MATCH(B11,'Rule Matrix'!$A$2:$A$142,0))) -> s.16(2)(aa), Rule 36(4) | F11: =IF(B11="","",INDEX('Rule Matrix'!$F$2:$F$142,MATCH(B11,'Rule Matrix'!$A$2:$A$142,0))) -> Line-level match: GSTIN+Inv No+Date+Taxable+Tax; ITC in 3B > 2B → excess | G11: =IF(B11="","",INDEX('Rule Matrix'!$G$2:$G$142,MATCH(B11,'Rule Matrix'!$A$2:$A$142,0))) -> Diff > ₹1,000/month or > 1% | H11: =IF(B11="","",INDEX('Rule Matrix'!$H$2:$H$142,MATCH(B11,'Rule Matrix'!$A$2:$A$142,0))) -> High | I11: =IF(B11="","",INDEX('Rule Matrix'!$J$2:$J$142,MATCH(B11,'Rule Matrix'!$A$2:$A$142,0))) -> Reverse via DRC-03; respond to DRC-01C (Rule 88D) | Z11: =Applicability!A5 -> B-01 | AA11: =IF($Z$5=0,0,IF(AND(INDEX(Applicability!$E$5:$O$5,1,$Z$5)="Y",OR(Applicability!$D$5="",IFERROR(INDEX($B$4:$F$4,MATCH(Applicability!$D$5,$B$3:$F$3,0)),"N")="Y")),1,0)) -> 1 | AB11: =IF(AA11=1,SUM(AA$8:AA11),"") -> 4
A12: =IF(5>$B$5,"",5) -> 5 | B12: =IF(A12="","",INDEX($Z$8:$Z$148,MATCH(A12,$AB$8:$AB$148,0))) -> B-02 | C12: =IF(B12="","",INDEX('Rule Matrix'!$B$2:$B$142,MATCH(B12,'Rule Matrix'!$A$2:$A$142,0))) -> B. ITC Eligibility (s.16) | D12: =IF(B12="","",INDEX('Rule Matrix'!$C$2:$C$142,MATCH(B12,'Rule Matrix'!$A$2:$A$142,0))) -> ITC in books but not in 2B | E12: =IF(B12="","",INDEX('Rule Matrix'!$D$2:$D$142,MATCH(B12,'Rule Matrix'!$A$2:$A$142,0))) -> s.16(2)(aa) | F12: =IF(B12="","",INDEX('Rule Matrix'!$F$2:$F$142,MATCH(B12,'Rule Matrix'!$A$2:$A$142,0))) -> Invoices in books absent in 2B/IMS | G12: =IF(B12="","",INDEX('Rule Matrix'!$G$2:$G$142,MATCH(B12,'Rule Matrix'!$A$2:$A$142,0))) -> Any | H12: =IF(B12="","",INDEX('Rule Matrix'!$H$2:$H$142,MATCH(B12,'Rule Matrix'!$A$2:$A$142,0))) -> Med | I12: =IF(B12="","",INDEX('Rule Matrix'!$J$2:$J$142,MATCH(B12,'Rule Matrix'!$A$2:$A$142,0))) -> Vendor follow-up; defer claim | Z12: =Applicability!A6 -> B-02 | AA12: =IF($Z$5=0,0,IF(AND(INDEX(Applicability!$E$6:$O$6,1,$Z$5)="Y",OR(Applicability!$D$6="",IFERROR(INDEX($B$4:$F$4,MATCH(Applicability!$D$6,$B$3:$F$3,0)),"N")="Y")),1,0)) -> 1 | AB12: =IF(AA12=1,SUM(AA$8:AA12),"") -> 5
A13: =IF(6>$B$5,"",6) -> 6 | B13: =IF(A13="","",INDEX($Z$8:$Z$148,MATCH(A13,$AB$8:$AB$148,0))) -> B-03 | C13: =IF(B13="","",INDEX('Rule Matrix'!$B$2:$B$142,MATCH(B13,'Rule Matrix'!$A$2:$A$142,0))) -> B. ITC Eligibility (s.16) | D13: =IF(B13="","",INDEX('Rule Matrix'!$C$2:$C$142,MATCH(B13,'Rule Matrix'!$A$2:$A$142,0))) -> Receipt of goods/services | E13: =IF(B13="","",INDEX('Rule Matrix'!$D$2:$D$142,MATCH(B13,'Rule Matrix'!$A$2:$A$142,0))) -> s.16(2)(b) | F13: =IF(B13="","",INDEX('Rule Matrix'!$F$2:$F$142,MATCH(B13,'Rule Matrix'!$A$2:$A$142,0))) -> Invoice without GRN/EWB for goods; bill-to-ship-to documentation | G13: =IF(B13="","",INDEX('Rule Matrix'!$G$2:$G$142,MATCH(B13,'Rule Matrix'!$A$2:$A$142,0))) -> Any | H13: =IF(B13="","",INDEX('Rule Matrix'!$H$2:$H$142,MATCH(B13,'Rule Matrix'!$A$2:$A$142,0))) -> High | I13: =IF(B13="","",INDEX('Rule Matrix'!$J$2:$J$142,MATCH(B13,'Rule Matrix'!$A$2:$A$142,0))) -> Obtain proof of receipt | Z13: =Applicability!A7 -> B-03 | AA13: =IF($Z$5=0,0,IF(AND(INDEX(Applicability!$E$7:$O$7,1,$Z$5)="Y",OR(Applicability!$D$7="",IFERROR(INDEX($B$4:$F$4,MATCH(Applicability!$D$7,$B$3:$F$3,0)),"N")="Y")),1,0)) -> 1 | AB13: =IF(AA13=1,SUM(AA$8:AA13),"") -> 6
A14: =IF(7>$B$5,"",7) -> 7 | B14: =IF(A14="","",INDEX($Z$8:$Z$148,MATCH(A14,$AB$8:$AB$148,0))) -> B-04 | C14: =IF(B14="","",INDEX('Rule Matrix'!$B$2:$B$142,MATCH(B14,'Rule Matrix'!$A$2:$A$142,0))) -> B. ITC Eligibility (s.16) | D14: =IF(B14="","",INDEX('Rule Matrix'!$C$2:$C$142,MATCH(B14,'Rule Matrix'!$A$2:$A$142,0))) -> Supplier tax payment (Rule 37A) | E14: =IF(B14="","",INDEX('Rule Matrix'!$D$2:$D$142,MATCH(B14,'Rule Matrix'!$A$2:$A$142,0))) -> s.16(2)(c), Rule 37A; Suncraft Energy (Cal HC; SC dismissed SLP, Dec 2023) | F14: =IF(B14="","",INDEX('Rule Matrix'!$F$2:$F$142,MATCH(B14,'Rule Matrix'!$A$2:$A$142,0))) -> Vendor 3B not filed by 30 Sept of next FY → reverse by 30 Nov. Defence: ITC cannot be denied to bona fide buyer solely for supplier default without first proceeding against supplier | G14: =IF(B14="","",INDEX('Rule Matrix'!$G$2:$G$142,MATCH(B14,'Rule Matrix'!$A$2:$A$142,0))) -> Any | H14: =IF(B14="","",INDEX('Rule Matrix'!$H$2:$H$142,MATCH(B14,'Rule Matrix'!$A$2:$A$142,0))) -> High | I14: =IF(B14="","",INDEX('Rule Matrix'!$J$2:$J$142,MATCH(B14,'Rule Matrix'!$A$2:$A$142,0))) -> Reverse by 30 Nov; reclaim once vendor files | Z14: =Applicability!A8 -> B-04 | AA14: =IF($Z$5=0,0,IF(AND(INDEX(Applicability!$E$8:$O$8,1,$Z$5)="Y",OR(Applicability!$D$8="",IFERROR(INDEX($B$4:$F$4,MATCH(Applicability!$D$8,$B$3:$F$3,0)),"N")="Y")),1,0)) -> 1 | AB14: =IF(AA14=1,SUM(AA$8:AA14),"") -> 7
A15: =IF(8>$B$5,"",8) -> 8 | B15: =IF(A15="","",INDEX($Z$8:$Z$148,MATCH(A15,$AB$8:$AB$148,0))) -> B-05 | C15: =IF(B15="","",INDEX('Rule Matrix'!$B$2:$B$142,MATCH(B15,'Rule Matrix'!$A$2:$A$142,0))) -> B. ITC Eligibility (s.16) | D15: =IF(B15="","",INDEX('Rule Matrix'!$C$2:$C$142,MATCH(B15,'Rule Matrix'!$A$2:$A$142,0))) -> Payment within 180 days | E15: =IF(B15="","",INDEX('Rule Matrix'!$D$2:$D$142,MATCH(B15,'Rule Matrix'!$A$2:$A$142,0))) -> Rule 37, s.16(2) 2nd proviso | F15: =IF(B15="","",INDEX('Rule Matrix'!$F$2:$F$142,MATCH(B15,'Rule Matrix'!$A$2:$A$142,0))) -> Unpaid value > 180 days from invoice date (excl. RCM, deemed supply) | G15: =IF(B15="","",INDEX('Rule Matrix'!$G$2:$G$142,MATCH(B15,'Rule Matrix'!$A$2:$A$142,0))) -> Any | H15: =IF(B15="","",INDEX('Rule Matrix'!$H$2:$H$142,MATCH(B15,'Rule Matrix'!$A$2:$A$142,0))) -> High | I15: =IF(B15="","",INDEX('Rule Matrix'!$J$2:$J$142,MATCH(B15,'Rule Matrix'!$A$2:$A$142,0))) -> Reverse in 3B; reclaim on payment | Z15: =Applicability!A9 -> B-05 | AA15: =IF($Z$5=0,0,IF(AND(INDEX(Applicability!$E$9:$O$9,1,$Z$5)="Y",OR(Applicability!$D$9="",IFERROR(INDEX($B$4:$F$4,MATCH(Applicability!$D$9,$B$3:$F$3,0)),"N")="Y")),1,0)) -> 1 | AB15: =IF(AA15=1,SUM(AA$8:AA15),"") -> 8
A16: =IF(9>$B$5,"",9) -> 9 | B16: =IF(A16="","",INDEX($Z$8:$Z$148,MATCH(A16,$AB$8:$AB$148,0))) -> B-06 | C16: =IF(B16="","",INDEX('Rule Matrix'!$B$2:$B$142,MATCH(B16,'Rule Matrix'!$A$2:$A$142,0))) -> B. ITC Eligibility (s.16) | D16: =IF(B16="","",INDEX('Rule Matrix'!$C$2:$C$142,MATCH(B16,'Rule Matrix'!$A$2:$A$142,0))) -> Depreciation on tax component | E16: =IF(B16="","",INDEX('Rule Matrix'!$D$2:$D$142,MATCH(B16,'Rule Matrix'!$A$2:$A$142,0))) -> s.16(3) | F16: =IF(B16="","",INDEX('Rule Matrix'!$F$2:$F$142,MATCH(B16,'Rule Matrix'!$A$2:$A$142,0))) -> Capital goods where ITC claimed AND GST capitalised in cost | G16: =IF(B16="","",INDEX('Rule Matrix'!$G$2:$G$142,MATCH(B16,'Rule Matrix'!$A$2:$A$142,0))) -> Any | H16: =IF(B16="","",INDEX('Rule Matrix'!$H$2:$H$142,MATCH(B16,'Rule Matrix'!$A$2:$A$142,0))) -> High | I16: =IF(B16="","",INDEX('Rule Matrix'!$J$2:$J$142,MATCH(B16,'Rule Matrix'!$A$2:$A$142,0))) -> Reverse ITC or de-capitalise | Z16: =Applicability!A10 -> B-06 | AA16: =IF($Z$5=0,0,IF(AND(INDEX(Applicability!$E$10:$O$10,1,$Z$5)="Y",OR(Applicability!$D$10="",IFERROR(INDEX($B$4:$F$4,MATCH(Applicability!$D$10,$B$3:$F$3,0)),"N")="Y")),1,0)) -> 1 | AB16: =IF(AA16=1,SUM(AA$8:AA16),"") -> 9
A17: =IF(10>$B$5,"",10) -> 10 | B17: =IF(A17="","",INDEX($Z$8:$Z$148,MATCH(A17,$AB$8:$AB$148,0))) -> B-07 | C17: =IF(B17="","",INDEX('Rule Matrix'!$B$2:$B$142,MATCH(B17,'Rule Matrix'!$A$2:$A$142,0))) -> B. ITC Eligibility (s.16) | D17: =IF(B17="","",INDEX('Rule Matrix'!$C$2:$C$142,MATCH(B17,'Rule Matrix'!$A$2:$A$142,0))) -> Time limit for ITC | E17: =IF(B17="","",INDEX('Rule Matrix'!$D$2:$D$142,MATCH(B17,'Rule Matrix'!$A$2:$A$142,0))) -> s.16(4), 16(5), 16(6) | F17: =IF(B17="","",INDEX('Rule Matrix'!$F$2:$F$142,MATCH(B17,'Rule Matrix'!$A$2:$A$142,0))) -> Claimed after earlier of 30 Nov next FY / annual return date; DN date used for DN | G17: =IF(B17="","",INDEX('Rule Matrix'!$G$2:$G$142,MATCH(B17,'Rule Matrix'!$A$2:$A$142,0))) -> Any | H17: =IF(B17="","",INDEX('Rule Matrix'!$H$2:$H$142,MATCH(B17,'Rule Matrix'!$A$2:$A$142,0))) -> High | I17: =IF(B17="","",INDEX('Rule Matrix'!$J$2:$J$142,MATCH(B17,'Rule Matrix'!$A$2:$A$142,0))) -> Reverse; check 16(5)/(6) relaxation | Z17: =Applicability!A11 -> B-07 | AA17: =IF($Z$5=0,0,IF(AND(INDEX(Applicability!$E$11:$O$11,1,$Z$5)="Y",OR(Applicability!$D$11="",IFERROR(INDEX($B$4:$F$4,MATCH(Applicability!$D$11,$B$3:$F$3,0)),"N")="Y")),1,0)) -> 1 | AB17: =IF(AA17=1,SUM(AA$8:AA17),"") -> 10
A18: =IF(11>$B$5,"",11) -> 11 | B18: =IF(A18="","",INDEX($Z$8:$Z$148,MATCH(A18,$AB$8:$AB$148,0))) -> B-08 | C18: =IF(B18="","",INDEX('Rule Matrix'!$B$2:$B$142,MATCH(B18,'Rule Matrix'!$A$2:$A$142,0))) -> B. ITC Eligibility (s.16) | D18: =IF(B18="","",INDEX('Rule Matrix'!$C$2:$C$142,MATCH(B18,'Rule Matrix'!$A$2:$A$142,0))) -> Duplicate ITC | E18: =IF(B18="","",INDEX('Rule Matrix'!$D$2:$D$142,MATCH(B18,'Rule Matrix'!$A$2:$A$142,0))) -> s.16 | F18: =IF(B18="","",INDEX('Rule Matrix'!$F$2:$F$142,MATCH(B18,'Rule Matrix'!$A$2:$A$142,0))) -> Same GSTIN+Inv No claimed twice / across GSTINs / periods | G18: =IF(B18="","",INDEX('Rule Matrix'!$G$2:$G$142,MATCH(B18,'Rule Matrix'!$A$2:$A$142,0))) -> Any | H18: =IF(B18="","",INDEX('Rule Matrix'!$H$2:$H$142,MATCH(B18,'Rule Matrix'!$A$2:$A$142,0))) -> High | I18: =IF(B18="","",INDEX('Rule Matrix'!$J$2:$J$142,MATCH(B18,'Rule Matrix'!$A$2:$A$142,0))) -> Reverse | Z18: =Applicability!A12 -> B-08 | AA18: =IF($Z$5=0,0,IF(AND(INDEX(Applicability!$E$12:$O$12,1,$Z$5)="Y",OR(Applicability!$D$12="",IFERROR(INDEX($B$4:$F$4,MATCH(Applicability!$D$12,$B$3:$F$3,0)),"N")="Y")),1,0)) -> 1 | AB18: =IF(AA18=1,SUM(AA$8:AA18),"") -> 11
A19: =IF(12>$B$5,"",12) -> 12 | B19: =IF(A19="","",INDEX($Z$8:$Z$148,MATCH(A19,$AB$8:$AB$148,0))) -> B-10 | C19: =IF(B19="","",INDEX('Rule Matrix'!$B$2:$B$142,MATCH(B19,'Rule Matrix'!$A$2:$A$142,0))) -> B. ITC Eligibility (s.16) | D19: =IF(B19="","",INDEX('Rule Matrix'!$C$2:$C$142,MATCH(B19,'Rule Matrix'!$A$2:$A$142,0))) -> ITC on invoices from cancelled/composition vendors | E19: =IF(B19="","",INDEX('Rule Matrix'!$D$2:$D$142,MATCH(B19,'Rule Matrix'!$A$2:$A$142,0))) -> s.16, s.10(4) | F19: =IF(B19="","",INDEX('Rule Matrix'!$F$2:$F$142,MATCH(B19,'Rule Matrix'!$A$2:$A$142,0))) -> Tax charged by composition dealer or post-cancellation invoice | G19: =IF(B19="","",INDEX('Rule Matrix'!$G$2:$G$142,MATCH(B19,'Rule Matrix'!$A$2:$A$142,0))) -> Any | H19: =IF(B19="","",INDEX('Rule Matrix'!$H$2:$H$142,MATCH(B19,'Rule Matrix'!$A$2:$A$142,0))) -> High | I19: =IF(B19="","",INDEX('Rule Matrix'!$J$2:$J$142,MATCH(B19,'Rule Matrix'!$A$2:$A$142,0))) -> Reverse | Z19: =Applicability!A13 -> B-09 | AA19: =IF($Z$5=0,0,IF(AND(INDEX(Applicability!$E$13:$O$13,1,$Z$5)="Y",OR(Applicability!$D$13="",IFERROR(INDEX($B$4:$F$4,MATCH(Applicability!$D$13,$B$3:$F$3,0)),"N")="Y")),1,0)) -> 0 | AB19: =IF(AA19=1,SUM(AA$8:AA19),"")
A20: =IF(13>$B$5,"",13) -> 13 | B20: =IF(A20="","",INDEX($Z$8:$Z$148,MATCH(A20,$AB$8:$AB$148,0))) -> B-11 | C20: =IF(B20="","",INDEX('Rule Matrix'!$B$2:$B$142,MATCH(B20,'Rule Matrix'!$A$2:$A$142,0))) -> B. ITC Eligibility (s.16) | D20: =IF(B20="","",INDEX('Rule Matrix'!$C$2:$C$142,MATCH(B20,'Rule Matrix'!$A$2:$A$142,0))) -> Document validity | E20: =IF(B20="","",INDEX('Rule Matrix'!$D$2:$D$142,MATCH(B20,'Rule Matrix'!$A$2:$A$142,0))) -> s.16(2)(a), Rule 36 | F20: =IF(B20="","",INDEX('Rule Matrix'!$F$2:$F$142,MATCH(B20,'Rule Matrix'!$A$2:$A$142,0))) -> Mandatory particulars present (Rule 46): GSTIN, HSN, POS, tax break-up; e-invoice IRN where supplier mandated | G20: =IF(B20="","",INDEX('Rule Matrix'!$G$2:$G$142,MATCH(B20,'Rule Matrix'!$A$2:$A$142,0))) -> Any | H20: =IF(B20="","",INDEX('Rule Matrix'!$H$2:$H$142,MATCH(B20,'Rule Matrix'!$A$2:$A$142,0))) -> Med | I20: =IF(B20="","",INDEX('Rule Matrix'!$J$2:$J$142,MATCH(B20,'Rule Matrix'!$A$2:$A$142,0))) -> Obtain corrected invoice | Z20: =Applicability!A14 -> B-10 | AA20: =IF($Z$5=0,0,IF(AND(INDEX(Applicability!$E$14:$O$14,1,$Z$5)="Y",OR(Applicability!$D$14="",IFERROR(INDEX($B$4:$F$4,MATCH(Applicability!$D$14,$B$3:$F$3,0)),"N")="Y")),1,0)) -> 1 | AB20: =IF(AA20=1,SUM(AA$8:AA20),"") -> 12
A21: =IF(14>$B$5,"",14) -> 14 | B21: =IF(A21="","",INDEX($Z$8:$Z$148,MATCH(A21,$AB$8:$AB$148,0))) -> C-01 | C21: =IF(B21="","",INDEX('Rule Matrix'!$B$2:$B$142,MATCH(B21,'Rule Matrix'!$A$2:$A$142,0))) -> C. RCM | D21: =IF(B21="","",INDEX('Rule Matrix'!$C$2:$C$142,MATCH(B21,'Rule Matrix'!$A$2:$A$142,0))) -> RCM liability identification | E21: =IF(B21="","",INDEX('Rule Matrix'!$D$2:$D$142,MATCH(B21,'Rule Matrix'!$A$2:$A$142,0))) -> s.9(3), 9(4); Notfn 13/2017-CT(R) | F21: =IF(B21="","",INDEX('Rule Matrix'!$F$2:$F$142,MATCH(B21,'Rule Matrix'!$A$2:$A$142,0))) -> Map GTA, legal, security, director sitting fees, sponsorship, renting by URP, import of services; compute liability | G21: =IF(B21="","",INDEX('Rule Matrix'!$G$2:$G$142,MATCH(B21,'Rule Matrix'!$A$2:$A$142,0))) -> Any unpaid | H21: =IF(B21="","",INDEX('Rule Matrix'!$H$2:$H$142,MATCH(B21,'Rule Matrix'!$A$2:$A$142,0))) -> High | I21: =IF(B21="","",INDEX('Rule Matrix'!$J$2:$J$142,MATCH(B21,'Rule Matrix'!$A$2:$A$142,0))) -> Pay via cash ledger; claim ITC | Z21: =Applicability!A15 -> B-11 | AA21: =IF($Z$5=0,0,IF(AND(INDEX(Applicability!$E$15:$O$15,1,$Z$5)="Y",OR(Applicability!$D$15="",IFERROR(INDEX($B$4:$F$4,MATCH(Applicability!$D$15,$B$3:$F$3,0)),"N")="Y")),1,0)) -> 1 | AB21: =IF(AA21=1,SUM(AA$8:AA21),"") -> 13
A22: =IF(15>$B$5,"",15) -> 15 | B22: =IF(A22="","",INDEX($Z$8:$Z$148,MATCH(A22,$AB$8:$AB$148,0))) -> C-02 | C22: =IF(B22="","",INDEX('Rule Matrix'!$B$2:$B$142,MATCH(B22,'Rule Matrix'!$A$2:$A$142,0))) -> C. RCM | D22: =IF(B22="","",INDEX('Rule Matrix'!$C$2:$C$142,MATCH(B22,'Rule Matrix'!$A$2:$A$142,0))) -> RCM ITC after payment | E22: =IF(B22="","",INDEX('Rule Matrix'!$D$2:$D$142,MATCH(B22,'Rule Matrix'!$A$2:$A$142,0))) -> s.16, Rule 36(1)(b) | F22: =IF(B22="","",INDEX('Rule Matrix'!$F$2:$F$142,MATCH(B22,'Rule Matrix'!$A$2:$A$142,0))) -> ITC on RCM ≤ RCM tax paid in cash in same/earlier period | G22: =IF(B22="","",INDEX('Rule Matrix'!$G$2:$G$142,MATCH(B22,'Rule Matrix'!$A$2:$A$142,0))) -> ITC > paid | H22: =IF(B22="","",INDEX('Rule Matrix'!$H$2:$H$142,MATCH(B22,'Rule Matrix'!$A$2:$A$142,0))) -> High | I22: =IF(B22="","",INDEX('Rule Matrix'!$J$2:$J$142,MATCH(B22,'Rule Matrix'!$A$2:$A$142,0))) -> Reverse | Z22: =Applicability!A16 -> C-01 | AA22: =IF($Z$5=0,0,IF(AND(INDEX(Applicability!$E$16:$O$16,1,$Z$5)="Y",OR(Applicability!$D$16="",IFERROR(INDEX($B$4:$F$4,MATCH(Applicability!$D$16,$B$3:$F$3,0)),"N")="Y")),1,0)) -> 1 | AB22: =IF(AA22=1,SUM(AA$8:AA22),"") -> 14
A23: =IF(16>$B$5,"",16) -> 16 | B23: =IF(A23="","",INDEX($Z$8:$Z$148,MATCH(A23,$AB$8:$AB$148,0))) -> C-03 | C23: =IF(B23="","",INDEX('Rule Matrix'!$B$2:$B$142,MATCH(B23,'Rule Matrix'!$A$2:$A$142,0))) -> C. RCM | D23: =IF(B23="","",INDEX('Rule Matrix'!$C$2:$C$142,MATCH(B23,'Rule Matrix'!$A$2:$A$142,0))) -> RCM self-invoice | E23: =IF(B23="","",INDEX('Rule Matrix'!$D$2:$D$142,MATCH(B23,'Rule Matrix'!$A$2:$A$142,0))) -> s.31(3)(f), Rule 47A | F23: =IF(B23="","",INDEX('Rule Matrix'!$F$2:$F$142,MATCH(B23,'Rule Matrix'!$A$2:$A$142,0))) -> Self-invoice issued within 30 days of receipt of supply | G23: =IF(B23="","",INDEX('Rule Matrix'!$G$2:$G$142,MATCH(B23,'Rule Matrix'!$A$2:$A$142,0))) -> Delay | H23: =IF(B23="","",INDEX('Rule Matrix'!$H$2:$H$142,MATCH(B23,'Rule Matrix'!$A$2:$A$142,0))) -> Low | I23: =IF(B23="","",INDEX('Rule Matrix'!$J$2:$J$142,MATCH(B23,'Rule Matrix'!$A$2:$A$142,0))) -> Issue self-invoices | Z23: =Applicability!A17 -> C-02 | AA23: =IF($Z$5=0,0,IF(AND(INDEX(Applicability!$E$17:$O$17,1,$Z$5)="Y",OR(Applicability!$D$17="",IFERROR(INDEX($B$4:$F$4,MATCH(Applicability!$D$17,$B$3:$F$3,0)),"N")="Y")),1,0)) -> 1 | AB23: =IF(AA23=1,SUM(AA$8:AA23),"") -> 15
A24: =IF(17>$B$5,"",17) -> 17 | B24: =IF(A24="","",INDEX($Z$8:$Z$148,MATCH(A24,$AB$8:$AB$148,0))) -> D-01 | C24: =IF(B24="","",INDEX('Rule Matrix'!$B$2:$B$142,MATCH(B24,'Rule Matrix'!$A$2:$A$142,0))) -> D. Place of Supply | D24: =IF(B24="","",INDEX('Rule Matrix'!$C$2:$C$142,MATCH(B24,'Rule Matrix'!$A$2:$A$142,0))) -> Tax head vs state codes | E24: =IF(B24="","",INDEX('Rule Matrix'!$D$2:$D$142,MATCH(B24,'Rule Matrix'!$A$2:$A$142,0))) -> IGST s.7, 8 | F24: =IF(B24="","",INDEX('Rule Matrix'!$F$2:$F$142,MATCH(B24,'Rule Matrix'!$A$2:$A$142,0))) -> Supplier state ≠ POS → IGST; same → CGST+SGST; mismatch flagged | G24: =IF(B24="","",INDEX('Rule Matrix'!$G$2:$G$142,MATCH(B24,'Rule Matrix'!$A$2:$A$142,0))) -> Any | H24: =IF(B24="","",INDEX('Rule Matrix'!$H$2:$H$142,MATCH(B24,'Rule Matrix'!$A$2:$A$142,0))) -> High | I24: =IF(B24="","",INDEX('Rule Matrix'!$J$2:$J$142,MATCH(B24,'Rule Matrix'!$A$2:$A$142,0))) -> s.77 / Rule 89 refund route; correct invoices | Z24: =Applicability!A18 -> C-03 | AA24: =IF($Z$5=0,0,IF(AND(INDEX(Applicability!$E$18:$O$18,1,$Z$5)="Y",OR(Applicability!$D$18="",IFERROR(INDEX($B$4:$F$4,MATCH(Applicability!$D$18,$B$3:$F$3,0)),"N")="Y")),1,0)) -> 1 | AB24: =IF(AA24=1,SUM(AA$8:AA24),"") -> 16
A25: =IF(18>$B$5,"",18) -> 18 | B25: =IF(A25="","",INDEX($Z$8:$Z$148,MATCH(A25,$AB$8:$AB$148,0))) -> D-02 | C25: =IF(B25="","",INDEX('Rule Matrix'!$B$2:$B$142,MATCH(B25,'Rule Matrix'!$A$2:$A$142,0))) -> D. Place of Supply | D25: =IF(B25="","",INDEX('Rule Matrix'!$C$2:$C$142,MATCH(B25,'Rule Matrix'!$A$2:$A$142,0))) -> Hotel/immovable property services | E25: =IF(B25="","",INDEX('Rule Matrix'!$D$2:$D$142,MATCH(B25,'Rule Matrix'!$A$2:$A$142,0))) -> IGST s.12(3) | F25: =IF(B25="","",INDEX('Rule Matrix'!$F$2:$F$142,MATCH(B25,'Rule Matrix'!$A$2:$A$142,0))) -> POS = location of property; out-of-state CGST/SGST → ITC not available to recipient | G25: =IF(B25="","",INDEX('Rule Matrix'!$G$2:$G$142,MATCH(B25,'Rule Matrix'!$A$2:$A$142,0))) -> Any | H25: =IF(B25="","",INDEX('Rule Matrix'!$H$2:$H$142,MATCH(B25,'Rule Matrix'!$A$2:$A$142,0))) -> Med | I25: =IF(B25="","",INDEX('Rule Matrix'!$J$2:$J$142,MATCH(B25,'Rule Matrix'!$A$2:$A$142,0))) -> Reverse; register in that state if recurring | Z25: =Applicability!A19 -> C-04 | AA25: =IF($Z$5=0,0,IF(AND(INDEX(Applicability!$E$19:$O$19,1,$Z$5)="Y",OR(Applicability!$D$19="",IFERROR(INDEX($B$4:$F$4,MATCH(Applicability!$D$19,$B$3:$F$3,0)),"N")="Y")),1,0)) -> 0 | AB25: =IF(AA25=1,SUM(AA$8:AA25),"")
A26: =IF(19>$B$5,"",19) -> 19 | B26: =IF(A26="","",INDEX($Z$8:$Z$148,MATCH(A26,$AB$8:$AB$148,0))) -> D-03 | C26: =IF(B26="","",INDEX('Rule Matrix'!$B$2:$B$142,MATCH(B26,'Rule Matrix'!$A$2:$A$142,0))) -> D. Place of Supply | D26: =IF(B26="","",INDEX('Rule Matrix'!$C$2:$C$142,MATCH(B26,'Rule Matrix'!$A$2:$A$142,0))) -> Restaurant/catering, training, events | E26: =IF(B26="","",INDEX('Rule Matrix'!$D$2:$D$142,MATCH(B26,'Rule Matrix'!$A$2:$A$142,0))) -> IGST s.12(4)(5)(7) | F26: =IF(B26="","",INDEX('Rule Matrix'!$F$2:$F$142,MATCH(B26,'Rule Matrix'!$A$2:$A$142,0))) -> Services performed in other state with other state CGST/SGST | G26: =IF(B26="","",INDEX('Rule Matrix'!$G$2:$G$142,MATCH(B26,'Rule Matrix'!$A$2:$A$142,0))) -> Any | H26: =IF(B26="","",INDEX('Rule Matrix'!$H$2:$H$142,MATCH(B26,'Rule Matrix'!$A$2:$A$142,0))) -> Med | I26: =IF(B26="","",INDEX('Rule Matrix'!$J$2:$J$142,MATCH(B26,'Rule Matrix'!$A$2:$A$142,0))) -> Reverse | Z26: =Applicability!A20 -> C-05 | AA26: =IF($Z$5=0,0,IF(AND(INDEX(Applicability!$E$20:$O$20,1,$Z$5)="Y",OR(Applicability!$D$20="",IFERROR(INDEX($B$4:$F$4,MATCH(Applicability!$D$20,$B$3:$F$3,0)),"N")="Y")),1,0)) -> 0 | AB26: =IF(AA26=1,SUM(AA$8:AA26),"")
A27: =IF(20>$B$5,"",20) -> 20 | B27: =IF(A27="","",INDEX($Z$8:$Z$148,MATCH(A27,$AB$8:$AB$148,0))) -> D-04 | C27: =IF(B27="","",INDEX('Rule Matrix'!$B$2:$B$142,MATCH(B27,'Rule Matrix'!$A$2:$A$142,0))) -> D. Place of Supply | D27: =IF(B27="","",INDEX('Rule Matrix'!$C$2:$C$142,MATCH(B27,'Rule Matrix'!$A$2:$A$142,0))) -> Goods transport / passenger transport | E27: =IF(B27="","",INDEX('Rule Matrix'!$D$2:$D$142,MATCH(B27,'Rule Matrix'!$A$2:$A$142,0))) -> IGST s.12(8)(9) | F27: =IF(B27="","",INDEX('Rule Matrix'!$F$2:$F$142,MATCH(B27,'Rule Matrix'!$A$2:$A$142,0))) -> POS per recipient location (registered) / boarding point; head consistency | G27: =IF(B27="","",INDEX('Rule Matrix'!$G$2:$G$142,MATCH(B27,'Rule Matrix'!$A$2:$A$142,0))) -> Any | H27: =IF(B27="","",INDEX('Rule Matrix'!$H$2:$H$142,MATCH(B27,'Rule Matrix'!$A$2:$A$142,0))) -> Low | I27: =IF(B27="","",INDEX('Rule Matrix'!$J$2:$J$142,MATCH(B27,'Rule Matrix'!$A$2:$A$142,0))) -> Correct | Z27: =Applicability!A21 -> D-01 | AA27: =IF($Z$5=0,0,IF(AND(INDEX(Applicability!$E$21:$O$21,1,$Z$5)="Y",OR(Applicability!$D$21="",IFERROR(INDEX($B$4:$F$4,MATCH(Applicability!$D$21,$B$3:$F$3,0)),"N")="Y")),1,0)) -> 1 | AB27: =IF(AA27=1,SUM(AA$8:AA27),"") -> 17
A28: =IF(21>$B$5,"",21) -> 21 | B28: =IF(A28="","",INDEX($Z$8:$Z$148,MATCH(A28,$AB$8:$AB$148,0))) -> D-05 | C28: =IF(B28="","",INDEX('Rule Matrix'!$B$2:$B$142,MATCH(B28,'Rule Matrix'!$A$2:$A$142,0))) -> D. Place of Supply | D28: =IF(B28="","",INDEX('Rule Matrix'!$C$2:$C$142,MATCH(B28,'Rule Matrix'!$A$2:$A$142,0))) -> Bill-to-ship-to goods | E28: =IF(B28="","",INDEX('Rule Matrix'!$D$2:$D$142,MATCH(B28,'Rule Matrix'!$A$2:$A$142,0))) -> IGST s.10(1)(b) | F28: =IF(B28="","",INDEX('Rule Matrix'!$F$2:$F$142,MATCH(B28,'Rule Matrix'!$A$2:$A$142,0))) -> POS = principal place of 'bill-to' party; verify tax head | G28: =IF(B28="","",INDEX('Rule Matrix'!$G$2:$G$142,MATCH(B28,'Rule Matrix'!$A$2:$A$142,0))) -> Any | H28: =IF(B28="","",INDEX('Rule Matrix'!$H$2:$H$142,MATCH(B28,'Rule Matrix'!$A$2:$A$142,0))) -> Med | I28: =IF(B28="","",INDEX('Rule Matrix'!$J$2:$J$142,MATCH(B28,'Rule Matrix'!$A$2:$A$142,0))) -> Correct | Z28: =Applicability!A22 -> D-02 | AA28: =IF($Z$5=0,0,IF(AND(INDEX(Applicability!$E$22:$O$22,1,$Z$5)="Y",OR(Applicability!$D$22="",IFERROR(INDEX($B$4:$F$4,MATCH(Applicability!$D$22,$B$3:$F$3,0)),"N")="Y")),1,0)) -> 1 | AB28: =IF(AA28=1,SUM(AA$8:AA28),"") -> 18
A29: =IF(22>$B$5,"",22) -> 22 | B29: =IF(A29="","",INDEX($Z$8:$Z$148,MATCH(A29,$AB$8:$AB$148,0))) -> D-06 | C29: =IF(B29="","",INDEX('Rule Matrix'!$B$2:$B$142,MATCH(B29,'Rule Matrix'!$A$2:$A$142,0))) -> D. Place of Supply | D29: =IF(B29="","",INDEX('Rule Matrix'!$C$2:$C$142,MATCH(B29,'Rule Matrix'!$A$2:$A$142,0))) -> B2C recipient address | E29: =IF(B29="","",INDEX('Rule Matrix'!$D$2:$D$142,MATCH(B29,'Rule Matrix'!$A$2:$A$142,0))) -> IGST s.10(1)(ca) | F29: =IF(B29="","",INDEX('Rule Matrix'!$F$2:$F$142,MATCH(B29,'Rule Matrix'!$A$2:$A$142,0))) -> B2C inter-state: recipient state recorded; else POS = supplier location | G29: =IF(B29="","",INDEX('Rule Matrix'!$G$2:$G$142,MATCH(B29,'Rule Matrix'!$A$2:$A$142,0))) -> Missing | H29: =IF(B29="","",INDEX('Rule Matrix'!$H$2:$H$142,MATCH(B29,'Rule Matrix'!$A$2:$A$142,0))) -> Low | I29: =IF(B29="","",INDEX('Rule Matrix'!$J$2:$J$142,MATCH(B29,'Rule Matrix'!$A$2:$A$142,0))) -> Capture address | Z29: =Applicability!A23 -> D-03 | AA29: =IF($Z$5=0,0,IF(AND(INDEX(Applicability!$E$23:$O$23,1,$Z$5)="Y",OR(Applicability!$D$23="",IFERROR(INDEX($B$4:$F$4,MATCH(Applicability!$D$23,$B$3:$F$3,0)),"N")="Y")),1,0)) -> 1 | AB29: =IF(AA29=1,SUM(AA$8:AA29),"") -> 19
A30: =IF(23>$B$5,"",23) -> 23 | B30: =IF(A30="","",INDEX($Z$8:$Z$148,MATCH(A30,$AB$8:$AB$148,0))) -> E-01 | C30: =IF(B30="","",INDEX('Rule Matrix'!$B$2:$B$142,MATCH(B30,'Rule Matrix'!$A$2:$A$142,0))) -> E. Blocked Credits s.17(5) | D30: =IF(B30="","",INDEX('Rule Matrix'!$C$2:$C$142,MATCH(B30,'Rule Matrix'!$A$2:$A$142,0))) -> Motor vehicles ≤13 seats | E30: =IF(B30="","",INDEX('Rule Matrix'!$D$2:$D$142,MATCH(B30,'Rule Matrix'!$A$2:$A$142,0))) -> s.17(5)(a),(ab) | F30: =IF(B30="","",INDEX('Rule Matrix'!$F$2:$F$142,MATCH(B30,'Rule Matrix'!$A$2:$A$142,0))) -> ITC on cars and their repairs/insurance unless used for further supply, passenger transport, driving training | G30: =IF(B30="","",INDEX('Rule Matrix'!$G$2:$G$142,MATCH(B30,'Rule Matrix'!$A$2:$A$142,0))) -> Any | H30: =IF(B30="","",INDEX('Rule Matrix'!$H$2:$H$142,MATCH(B30,'Rule Matrix'!$A$2:$A$142,0))) -> High | I30: =IF(B30="","",INDEX('Rule Matrix'!$J$2:$J$142,MATCH(B30,'Rule Matrix'!$A$2:$A$142,0))) -> Reverse | Z30: =Applicability!A24 -> D-04 | AA30: =IF($Z$5=0,0,IF(AND(INDEX(Applicability!$E$24:$O$24,1,$Z$5)="Y",OR(Applicability!$D$24="",IFERROR(INDEX($B$4:$F$4,MATCH(Applicability!$D$24,$B$3:$F$3,0)),"N")="Y")),1,0)) -> 1 | AB30: =IF(AA30=1,SUM(AA$8:AA30),"") -> 20
A31: =IF(24>$B$5,"",24) -> 24 | B31: =IF(A31="","",INDEX($Z$8:$Z$148,MATCH(A31,$AB$8:$AB$148,0))) -> E-02 | C31: =IF(B31="","",INDEX('Rule Matrix'!$B$2:$B$142,MATCH(B31,'Rule Matrix'!$A$2:$A$142,0))) -> E. Blocked Credits s.17(5) | D31: =IF(B31="","",INDEX('Rule Matrix'!$C$2:$C$142,MATCH(B31,'Rule Matrix'!$A$2:$A$142,0))) -> Vessels & aircraft | E31: =IF(B31="","",INDEX('Rule Matrix'!$D$2:$D$142,MATCH(B31,'Rule Matrix'!$A$2:$A$142,0))) -> s.17(5)(aa),(ab) | F31: =IF(B31="","",INDEX('Rule Matrix'!$F$2:$F$142,MATCH(B31,'Rule Matrix'!$A$2:$A$142,0))) -> ITC except permitted uses | G31: =IF(B31="","",INDEX('Rule Matrix'!$G$2:$G$142,MATCH(B31,'Rule Matrix'!$A$2:$A$142,0))) -> Any | H31: =IF(B31="","",INDEX('Rule Matrix'!$H$2:$H$142,MATCH(B31,'Rule Matrix'!$A$2:$A$142,0))) -> High | I31: =IF(B31="","",INDEX('Rule Matrix'!$J$2:$J$142,MATCH(B31,'Rule Matrix'!$A$2:$A$142,0))) -> Reverse | Z31: =Applicability!A25 -> D-05 | AA31: =IF($Z$5=0,0,IF(AND(INDEX(Applicability!$E$25:$O$25,1,$Z$5)="Y",OR(Applicability!$D$25="",IFERROR(INDEX($B$4:$F$4,MATCH(Applicability!$D$25,$B$3:$F$3,0)),"N")="Y")),1,0)) -> 1 | AB31: =IF(AA31=1,SUM(AA$8:AA31),"") -> 21
A32: =IF(25>$B$5,"",25) -> 25 | B32: =IF(A32="","",INDEX($Z$8:$Z$148,MATCH(A32,$AB$8:$AB$148,0))) -> E-03 | C32: =IF(B32="","",INDEX('Rule Matrix'!$B$2:$B$142,MATCH(B32,'Rule Matrix'!$A$2:$A$142,0))) -> E. Blocked Credits s.17(5) | D32: =IF(B32="","",INDEX('Rule Matrix'!$C$2:$C$142,MATCH(B32,'Rule Matrix'!$A$2:$A$142,0))) -> Food, beverages, outdoor catering | E32: =IF(B32="","",INDEX('Rule Matrix'!$D$2:$D$142,MATCH(B32,'Rule Matrix'!$A$2:$A$142,0))) -> s.17(5)(b)(i) | F32: =IF(B32="","",INDEX('Rule Matrix'!$F$2:$F$142,MATCH(B32,'Rule Matrix'!$A$2:$A$142,0))) -> ITC unless obligatory under law or same line of outward supply | G32: =IF(B32="","",INDEX('Rule Matrix'!$G$2:$G$142,MATCH(B32,'Rule Matrix'!$A$2:$A$142,0))) -> Any | H32: =IF(B32="","",INDEX('Rule Matrix'!$H$2:$H$142,MATCH(B32,'Rule Matrix'!$A$2:$A$142,0))) -> High | I32: =IF(B32="","",INDEX('Rule Matrix'!$J$2:$J$142,MATCH(B32,'Rule Matrix'!$A$2:$A$142,0))) -> Reverse | Z32: =Applicability!A26 -> D-06 | AA32: =IF($Z$5=0,0,IF(AND(INDEX(Applicability!$E$26:$O$26,1,$Z$5)="Y",OR(Applicability!$D$26="",IFERROR(INDEX($B$4:$F$4,MATCH(Applicability!$D$26,$B$3:$F$3,0)),"N")="Y")),1,0)) -> 1 | AB32: =IF(AA32=1,SUM(AA$8:AA32),"") -> 22
A33: =IF(26>$B$5,"",26) -> 26 | B33: =IF(A33="","",INDEX($Z$8:$Z$148,MATCH(A33,$AB$8:$AB$148,0))) -> E-04 | C33: =IF(B33="","",INDEX('Rule Matrix'!$B$2:$B$142,MATCH(B33,'Rule Matrix'!$A$2:$A$142,0))) -> E. Blocked Credits s.17(5) | D33: =IF(B33="","",INDEX('Rule Matrix'!$C$2:$C$142,MATCH(B33,'Rule Matrix'!$A$2:$A$142,0))) -> Beauty, health, cosmetic surgery | E33: =IF(B33="","",INDEX('Rule Matrix'!$D$2:$D$142,MATCH(B33,'Rule Matrix'!$A$2:$A$142,0))) -> s.17(5)(b)(i) | F33: =IF(B33="","",INDEX('Rule Matrix'!$F$2:$F$142,MATCH(B33,'Rule Matrix'!$A$2:$A$142,0))) -> Blocked unless same line of outward supply. Note: beauty/wellness now 5% without ITC w.e.f. 22.09.2025 (Notfn 15/2025-CT(R)) | G33: =IF(B33="","",INDEX('Rule Matrix'!$G$2:$G$142,MATCH(B33,'Rule Matrix'!$A$2:$A$142,0))) -> Any | H33: =IF(B33="","",INDEX('Rule Matrix'!$H$2:$H$142,MATCH(B33,'Rule Matrix'!$A$2:$A$142,0))) -> Med | I33: =IF(B33="","",INDEX('Rule Matrix'!$J$2:$J$142,MATCH(B33,'Rule Matrix'!$A$2:$A$142,0))) -> Reverse | Z33: =Applicability!A27 -> D-07 | AA33: =IF($Z$5=0,0,IF(AND(INDEX(Applicability!$E$27:$O$27,1,$Z$5)="Y",OR(Applicability!$D$27="",IFERROR(INDEX($B$4:$F$4,MATCH(Applicability!$D$27,$B$3:$F$3,0)),"N")="Y")),1,0)) -> 0 | AB33: =IF(AA33=1,SUM(AA$8:AA33),"")
A34: =IF(27>$B$5,"",27) -> 27 | B34: =IF(A34="","",INDEX($Z$8:$Z$148,MATCH(A34,$AB$8:$AB$148,0))) -> E-05 | C34: =IF(B34="","",INDEX('Rule Matrix'!$B$2:$B$142,MATCH(B34,'Rule Matrix'!$A$2:$A$142,0))) -> E. Blocked Credits s.17(5) | D34: =IF(B34="","",INDEX('Rule Matrix'!$C$2:$C$142,MATCH(B34,'Rule Matrix'!$A$2:$A$142,0))) -> Life & health insurance | E34: =IF(B34="","",INDEX('Rule Matrix'!$D$2:$D$142,MATCH(B34,'Rule Matrix'!$A$2:$A$142,0))) -> s.17(5)(b)(i) | F34: =IF(B34="","",INDEX('Rule Matrix'!$F$2:$F$142,MATCH(B34,'Rule Matrix'!$A$2:$A$142,0))) -> Individual life & health policies exempt w.e.f. 22.09.2025 (no ITC issue). Group / employer policies: ITC blocked unless obligatory under law (s.17(5)(b) proviso) | G34: =IF(B34="","",INDEX('Rule Matrix'!$G$2:$G$142,MATCH(B34,'Rule Matrix'!$A$2:$A$142,0))) -> Any | H34: =IF(B34="","",INDEX('Rule Matrix'!$H$2:$H$142,MATCH(B34,'Rule Matrix'!$A$2:$A$142,0))) -> Med | I34: =IF(B34="","",INDEX('Rule Matrix'!$J$2:$J$142,MATCH(B34,'Rule Matrix'!$A$2:$A$142,0))) -> Reverse | Z34: =Applicability!A28 -> D-08 | AA34: =IF($Z$5=0,0,IF(AND(INDEX(Applicability!$E$28:$O$28,1,$Z$5)="Y",OR(Applicability!$D$28="",IFERROR(INDEX($B$4:$F$4,MATCH(Applicability!$D$28,$B$3:$F$3,0)),"N")="Y")),1,0)) -> 0 | AB34: =IF(AA34=1,SUM(AA$8:AA34),"")
A35: =IF(28>$B$5,"",28) -> 28 | B35: =IF(A35="","",INDEX($Z$8:$Z$148,MATCH(A35,$AB$8:$AB$148,0))) -> E-06 | C35: =IF(B35="","",INDEX('Rule Matrix'!$B$2:$B$142,MATCH(B35,'Rule Matrix'!$A$2:$A$142,0))) -> E. Blocked Credits s.17(5) | D35: =IF(B35="","",INDEX('Rule Matrix'!$C$2:$C$142,MATCH(B35,'Rule Matrix'!$A$2:$A$142,0))) -> Club / fitness membership | E35: =IF(B35="","",INDEX('Rule Matrix'!$D$2:$D$142,MATCH(B35,'Rule Matrix'!$A$2:$A$142,0))) -> s.17(5)(b)(ii) | F35: =IF(B35="","",INDEX('Rule Matrix'!$F$2:$F$142,MATCH(B35,'Rule Matrix'!$A$2:$A$142,0))) -> Any ITC | G35: =IF(B35="","",INDEX('Rule Matrix'!$G$2:$G$142,MATCH(B35,'Rule Matrix'!$A$2:$A$142,0))) -> Any | H35: =IF(B35="","",INDEX('Rule Matrix'!$H$2:$H$142,MATCH(B35,'Rule Matrix'!$A$2:$A$142,0))) -> Med | I35: =IF(B35="","",INDEX('Rule Matrix'!$J$2:$J$142,MATCH(B35,'Rule Matrix'!$A$2:$A$142,0))) -> Reverse | Z35: =Applicability!A29 -> E-01 | AA35: =IF($Z$5=0,0,IF(AND(INDEX(Applicability!$E$29:$O$29,1,$Z$5)="Y",OR(Applicability!$D$29="",IFERROR(INDEX($B$4:$F$4,MATCH(Applicability!$D$29,$B$3:$F$3,0)),"N")="Y")),1,0)) -> 1 | AB35: =IF(AA35=1,SUM(AA$8:AA35),"") -> 23
A36: =IF(29>$B$5,"",29) -> 29 | B36: =IF(A36="","",INDEX($Z$8:$Z$148,MATCH(A36,$AB$8:$AB$148,0))) -> E-07 | C36: =IF(B36="","",INDEX('Rule Matrix'!$B$2:$B$142,MATCH(B36,'Rule Matrix'!$A$2:$A$142,0))) -> E. Blocked Credits s.17(5) | D36: =IF(B36="","",INDEX('Rule Matrix'!$C$2:$C$142,MATCH(B36,'Rule Matrix'!$A$2:$A$142,0))) -> Rent-a-cab | E36: =IF(B36="","",INDEX('Rule Matrix'!$D$2:$D$142,MATCH(B36,'Rule Matrix'!$A$2:$A$142,0))) -> s.17(5)(b)(i) | F36: =IF(B36="","",INDEX('Rule Matrix'!$F$2:$F$142,MATCH(B36,'Rule Matrix'!$A$2:$A$142,0))) -> Cab hire ITC unless obligatory / same outward supply | G36: =IF(B36="","",INDEX('Rule Matrix'!$G$2:$G$142,MATCH(B36,'Rule Matrix'!$A$2:$A$142,0))) -> Any | H36: =IF(B36="","",INDEX('Rule Matrix'!$H$2:$H$142,MATCH(B36,'Rule Matrix'!$A$2:$A$142,0))) -> Med | I36: =IF(B36="","",INDEX('Rule Matrix'!$J$2:$J$142,MATCH(B36,'Rule Matrix'!$A$2:$A$142,0))) -> Reverse | Z36: =Applicability!A30 -> E-02 | AA36: =IF($Z$5=0,0,IF(AND(INDEX(Applicability!$E$30:$O$30,1,$Z$5)="Y",OR(Applicability!$D$30="",IFERROR(INDEX($B$4:$F$4,MATCH(Applicability!$D$30,$B$3:$F$3,0)),"N")="Y")),1,0)) -> 1 | AB36: =IF(AA36=1,SUM(AA$8:AA36),"") -> 24
A37: =IF(30>$B$5,"",30) -> 30 | B37: =IF(A37="","",INDEX($Z$8:$Z$148,MATCH(A37,$AB$8:$AB$148,0))) -> E-08 | C37: =IF(B37="","",INDEX('Rule Matrix'!$B$2:$B$142,MATCH(B37,'Rule Matrix'!$A$2:$A$142,0))) -> E. Blocked Credits s.17(5) | D37: =IF(B37="","",INDEX('Rule Matrix'!$C$2:$C$142,MATCH(B37,'Rule Matrix'!$A$2:$A$142,0))) -> Employee travel benefits (LTC/vacation) | E37: =IF(B37="","",INDEX('Rule Matrix'!$D$2:$D$142,MATCH(B37,'Rule Matrix'!$A$2:$A$142,0))) -> s.17(5)(b)(iii) | F37: =IF(B37="","",INDEX('Rule Matrix'!$F$2:$F$142,MATCH(B37,'Rule Matrix'!$A$2:$A$142,0))) -> Any ITC | G37: =IF(B37="","",INDEX('Rule Matrix'!$G$2:$G$142,MATCH(B37,'Rule Matrix'!$A$2:$A$142,0))) -> Any | H37: =IF(B37="","",INDEX('Rule Matrix'!$H$2:$H$142,MATCH(B37,'Rule Matrix'!$A$2:$A$142,0))) -> Med | I37: =IF(B37="","",INDEX('Rule Matrix'!$J$2:$J$142,MATCH(B37,'Rule Matrix'!$A$2:$A$142,0))) -> Reverse | Z37: =Applicability!A31 -> E-03 | AA37: =IF($Z$5=0,0,IF(AND(INDEX(Applicability!$E$31:$O$31,1,$Z$5)="Y",OR(Applicability!$D$31="",IFERROR(INDEX($B$4:$F$4,MATCH(Applicability!$D$31,$B$3:$F$3,0)),"N")="Y")),1,0)) -> 1 | AB37: =IF(AA37=1,SUM(AA$8:AA37),"") -> 25
A38: =IF(31>$B$5,"",31) -> 31 | B38: =IF(A38="","",INDEX($Z$8:$Z$148,MATCH(A38,$AB$8:$AB$148,0))) -> E-09 | C38: =IF(B38="","",INDEX('Rule Matrix'!$B$2:$B$142,MATCH(B38,'Rule Matrix'!$A$2:$A$142,0))) -> E. Blocked Credits s.17(5) | D38: =IF(B38="","",INDEX('Rule Matrix'!$C$2:$C$142,MATCH(B38,'Rule Matrix'!$A$2:$A$142,0))) -> Works contract – immovable property | E38: =IF(B38="","",INDEX('Rule Matrix'!$D$2:$D$142,MATCH(B38,'Rule Matrix'!$A$2:$A$142,0))) -> s.17(5)(c) | F38: =IF(B38="","",INDEX('Rule Matrix'!$F$2:$F$142,MATCH(B38,'Rule Matrix'!$A$2:$A$142,0))) -> ITC on works contract services for construction of immovable property (other than 'plant and machinery') blocked, except where it is input service for further supply of works contract | G38: =IF(B38="","",INDEX('Rule Matrix'!$G$2:$G$142,MATCH(B38,'Rule Matrix'!$A$2:$A$142,0))) -> Any | H38: =IF(B38="","",INDEX('Rule Matrix'!$H$2:$H$142,MATCH(B38,'Rule Matrix'!$A$2:$A$142,0))) -> High | I38: =IF(B38="","",INDEX('Rule Matrix'!$J$2:$J$142,MATCH(B38,'Rule Matrix'!$A$2:$A$142,0))) -> Reverse | Z38: =Applicability!A32 -> E-04 | AA38: =IF($Z$5=0,0,IF(AND(INDEX(Applicability!$E$32:$O$32,1,$Z$5)="Y",OR(Applicability!$D$32="",IFERROR(INDEX($B$4:$F$4,MATCH(Applicability!$D$32,$B$3:$F$3,0)),"N")="Y")),1,0)) -> 1 | AB38: =IF(AA38=1,SUM(AA$8:AA38),"") -> 26
A39: =IF(32>$B$5,"",32) -> 32 | B39: =IF(A39="","",INDEX($Z$8:$Z$148,MATCH(A39,$AB$8:$AB$148,0))) -> E-10 | C39: =IF(B39="","",INDEX('Rule Matrix'!$B$2:$B$142,MATCH(B39,'Rule Matrix'!$A$2:$A$142,0))) -> E. Blocked Credits s.17(5) | D39: =IF(B39="","",INDEX('Rule Matrix'!$C$2:$C$142,MATCH(B39,'Rule Matrix'!$A$2:$A$142,0))) -> Construction on own account | E39: =IF(B39="","",INDEX('Rule Matrix'!$D$2:$D$142,MATCH(B39,'Rule Matrix'!$A$2:$A$142,0))) -> s.17(5)(d); Expl. 2 inserted by FA 2025 (retro 01.07.2017) | F39: =IF(B39="","",INDEX('Rule Matrix'!$F$2:$F$142,MATCH(B39,'Rule Matrix'!$A$2:$A$142,0))) -> 'plant or machinery' substituted by 'plant and machinery' retrospectively from 01.07.2017 – overrides functionality test of Safari Retreats (SC, 03.10.2024). Flag building/civil ITC even where property is let out | G39: =IF(B39="","",INDEX('Rule Matrix'!$G$2:$G$142,MATCH(B39,'Rule Matrix'!$A$2:$A$142,0))) -> Any | H39: =IF(B39="","",INDEX('Rule Matrix'!$H$2:$H$142,MATCH(B39,'Rule Matrix'!$A$2:$A$142,0))) -> High | I39: =IF(B39="","",INDEX('Rule Matrix'!$J$2:$J$142,MATCH(B39,'Rule Matrix'!$A$2:$A$142,0))) -> Reverse | Z39: =Applicability!A33 -> E-05 | AA39: =IF($Z$5=0,0,IF(AND(INDEX(Applicability!$E$33:$O$33,1,$Z$5)="Y",OR(Applicability!$D$33="",IFERROR(INDEX($B$4:$F$4,MATCH(Applicability!$D$33,$B$3:$F$3,0)),"N")="Y")),1,0)) -> 1 | AB39: =IF(AA39=1,SUM(AA$8:AA39),"") -> 27
A40: =IF(33>$B$5,"",33) -> 33 | B40: =IF(A40="","",INDEX($Z$8:$Z$148,MATCH(A40,$AB$8:$AB$148,0))) -> E-11 | C40: =IF(B40="","",INDEX('Rule Matrix'!$B$2:$B$142,MATCH(B40,'Rule Matrix'!$A$2:$A$142,0))) -> E. Blocked Credits s.17(5) | D40: =IF(B40="","",INDEX('Rule Matrix'!$C$2:$C$142,MATCH(B40,'Rule Matrix'!$A$2:$A$142,0))) -> Composition tax / NRTP | E40: =IF(B40="","",INDEX('Rule Matrix'!$D$2:$D$142,MATCH(B40,'Rule Matrix'!$A$2:$A$142,0))) -> s.17(5)(e),(f) | F40: =IF(B40="","",INDEX('Rule Matrix'!$F$2:$F$142,MATCH(B40,'Rule Matrix'!$A$2:$A$142,0))) -> ITC on goods/services where tax paid under composition or by NRTP (except imports) | G40: =IF(B40="","",INDEX('Rule Matrix'!$G$2:$G$142,MATCH(B40,'Rule Matrix'!$A$2:$A$142,0))) -> Any | H40: =IF(B40="","",INDEX('Rule Matrix'!$H$2:$H$142,MATCH(B40,'Rule Matrix'!$A$2:$A$142,0))) -> Med | I40: =IF(B40="","",INDEX('Rule Matrix'!$J$2:$J$142,MATCH(B40,'Rule Matrix'!$A$2:$A$142,0))) -> Reverse | Z40: =Applicability!A34 -> E-06 | AA40: =IF($Z$5=0,0,IF(AND(INDEX(Applicability!$E$34:$O$34,1,$Z$5)="Y",OR(Applicability!$D$34="",IFERROR(INDEX($B$4:$F$4,MATCH(Applicability!$D$34,$B$3:$F$3,0)),"N")="Y")),1,0)) -> 1 | AB40: =IF(AA40=1,SUM(AA$8:AA40),"") -> 28
A41: =IF(34>$B$5,"",34) -> 34 | B41: =IF(A41="","",INDEX($Z$8:$Z$148,MATCH(A41,$AB$8:$AB$148,0))) -> E-12 | C41: =IF(B41="","",INDEX('Rule Matrix'!$B$2:$B$142,MATCH(B41,'Rule Matrix'!$A$2:$A$142,0))) -> E. Blocked Credits s.17(5) | D41: =IF(B41="","",INDEX('Rule Matrix'!$C$2:$C$142,MATCH(B41,'Rule Matrix'!$A$2:$A$142,0))) -> CSR expenditure | E41: =IF(B41="","",INDEX('Rule Matrix'!$D$2:$D$142,MATCH(B41,'Rule Matrix'!$A$2:$A$142,0))) -> s.17(5)(fa) | F41: =IF(B41="","",INDEX('Rule Matrix'!$F$2:$F$142,MATCH(B41,'Rule Matrix'!$A$2:$A$142,0))) -> ITC on CSR spend (from 1.10.2023) | G41: =IF(B41="","",INDEX('Rule Matrix'!$G$2:$G$142,MATCH(B41,'Rule Matrix'!$A$2:$A$142,0))) -> Any | H41: =IF(B41="","",INDEX('Rule Matrix'!$H$2:$H$142,MATCH(B41,'Rule Matrix'!$A$2:$A$142,0))) -> High | I41: =IF(B41="","",INDEX('Rule Matrix'!$J$2:$J$142,MATCH(B41,'Rule Matrix'!$A$2:$A$142,0))) -> Reverse | Z41: =Applicability!A35 -> E-07 | AA41: =IF($Z$5=0,0,IF(AND(INDEX(Applicability!$E$35:$O$35,1,$Z$5)="Y",OR(Applicability!$D$35="",IFERROR(INDEX($B$4:$F$4,MATCH(Applicability!$D$35,$B$3:$F$3,0)),"N")="Y")),1,0)) -> 1 | AB41: =IF(AA41=1,SUM(AA$8:AA41),"") -> 29
A42: =IF(35>$B$5,"",35) -> 35 | B42: =IF(A42="","",INDEX($Z$8:$Z$148,MATCH(A42,$AB$8:$AB$148,0))) -> E-13 | C42: =IF(B42="","",INDEX('Rule Matrix'!$B$2:$B$142,MATCH(B42,'Rule Matrix'!$A$2:$A$142,0))) -> E. Blocked Credits s.17(5) | D42: =IF(B42="","",INDEX('Rule Matrix'!$C$2:$C$142,MATCH(B42,'Rule Matrix'!$A$2:$A$142,0))) -> Personal consumption | E42: =IF(B42="","",INDEX('Rule Matrix'!$D$2:$D$142,MATCH(B42,'Rule Matrix'!$A$2:$A$142,0))) -> s.17(5)(g) | F42: =IF(B42="","",INDEX('Rule Matrix'!$F$2:$F$142,MATCH(B42,'Rule Matrix'!$A$2:$A$142,0))) -> Director/employee personal expenses | G42: =IF(B42="","",INDEX('Rule Matrix'!$G$2:$G$142,MATCH(B42,'Rule Matrix'!$A$2:$A$142,0))) -> Any | H42: =IF(B42="","",INDEX('Rule Matrix'!$H$2:$H$142,MATCH(B42,'Rule Matrix'!$A$2:$A$142,0))) -> Med | I42: =IF(B42="","",INDEX('Rule Matrix'!$J$2:$J$142,MATCH(B42,'Rule Matrix'!$A$2:$A$142,0))) -> Reverse | Z42: =Applicability!A36 -> E-08 | AA42: =IF($Z$5=0,0,IF(AND(INDEX(Applicability!$E$36:$O$36,1,$Z$5)="Y",OR(Applicability!$D$36="",IFERROR(INDEX($B$4:$F$4,MATCH(Applicability!$D$36,$B$3:$F$3,0)),"N")="Y")),1,0)) -> 1 | AB42: =IF(AA42=1,SUM(AA$8:AA42),"") -> 30
A43: =IF(36>$B$5,"",36) -> 36 | B43: =IF(A43="","",INDEX($Z$8:$Z$148,MATCH(A43,$AB$8:$AB$148,0))) -> E-14 | C43: =IF(B43="","",INDEX('Rule Matrix'!$B$2:$B$142,MATCH(B43,'Rule Matrix'!$A$2:$A$142,0))) -> E. Blocked Credits s.17(5) | D43: =IF(B43="","",INDEX('Rule Matrix'!$C$2:$C$142,MATCH(B43,'Rule Matrix'!$A$2:$A$142,0))) -> Lost/stolen/destroyed/written off/gifts/samples | E43: =IF(B43="","",INDEX('Rule Matrix'!$D$2:$D$142,MATCH(B43,'Rule Matrix'!$A$2:$A$142,0))) -> s.17(5)(h) | F43: =IF(B43="","",INDEX('Rule Matrix'!$F$2:$F$142,MATCH(B43,'Rule Matrix'!$A$2:$A$142,0))) -> ITC on inputs so disposed; free samples/gifts | G43: =IF(B43="","",INDEX('Rule Matrix'!$G$2:$G$142,MATCH(B43,'Rule Matrix'!$A$2:$A$142,0))) -> Any | H43: =IF(B43="","",INDEX('Rule Matrix'!$H$2:$H$142,MATCH(B43,'Rule Matrix'!$A$2:$A$142,0))) -> High | I43: =IF(B43="","",INDEX('Rule Matrix'!$J$2:$J$142,MATCH(B43,'Rule Matrix'!$A$2:$A$142,0))) -> Reverse (Circular 92/2019) | Z43: =Applicability!A37 -> E-09 | AA43: =IF($Z$5=0,0,IF(AND(INDEX(Applicability!$E$37:$O$37,1,$Z$5)="Y",OR(Applicability!$D$37="",IFERROR(INDEX($B$4:$F$4,MATCH(Applicability!$D$37,$B$3:$F$3,0)),"N")="Y")),1,0)) -> 1 | AB43: =IF(AA43=1,SUM(AA$8:AA43),"") -> 31
A44: =IF(37>$B$5,"",37) -> 37 | B44: =IF(A44="","",INDEX($Z$8:$Z$148,MATCH(A44,$AB$8:$AB$148,0))) -> E-15 | C44: =IF(B44="","",INDEX('Rule Matrix'!$B$2:$B$142,MATCH(B44,'Rule Matrix'!$A$2:$A$142,0))) -> E. Blocked Credits s.17(5) | D44: =IF(B44="","",INDEX('Rule Matrix'!$C$2:$C$142,MATCH(B44,'Rule Matrix'!$A$2:$A$142,0))) -> Tax paid under s.74/74A | E44: =IF(B44="","",INDEX('Rule Matrix'!$D$2:$D$142,MATCH(B44,'Rule Matrix'!$A$2:$A$142,0))) -> s.17(5)(i) | F44: =IF(B44="","",INDEX('Rule Matrix'!$F$2:$F$142,MATCH(B44,'Rule Matrix'!$A$2:$A$142,0))) -> ITC claimed on tax paid in fraud proceedings | G44: =IF(B44="","",INDEX('Rule Matrix'!$G$2:$G$142,MATCH(B44,'Rule Matrix'!$A$2:$A$142,0))) -> Any | H44: =IF(B44="","",INDEX('Rule Matrix'!$H$2:$H$142,MATCH(B44,'Rule Matrix'!$A$2:$A$142,0))) -> Med | I44: =IF(B44="","",INDEX('Rule Matrix'!$J$2:$J$142,MATCH(B44,'Rule Matrix'!$A$2:$A$142,0))) -> Reverse | Z44: =Applicability!A38 -> E-10 | AA44: =IF($Z$5=0,0,IF(AND(INDEX(Applicability!$E$38:$O$38,1,$Z$5)="Y",OR(Applicability!$D$38="",IFERROR(INDEX($B$4:$F$4,MATCH(Applicability!$D$38,$B$3:$F$3,0)),"N")="Y")),1,0)) -> 1 | AB44: =IF(AA44=1,SUM(AA$8:AA44),"") -> 32
A45: =IF(38>$B$5,"",38) -> 38 | B45: =IF(A45="","",INDEX($Z$8:$Z$148,MATCH(A45,$AB$8:$AB$148,0))) -> F-01 | C45: =IF(B45="","",INDEX('Rule Matrix'!$B$2:$B$142,MATCH(B45,'Rule Matrix'!$A$2:$A$142,0))) -> F. Reversals & Apportionment | D45: =IF(B45="","",INDEX('Rule Matrix'!$C$2:$C$142,MATCH(B45,'Rule Matrix'!$A$2:$A$142,0))) -> Common credit – exempt turnover | E45: =IF(B45="","",INDEX('Rule Matrix'!$D$2:$D$142,MATCH(B45,'Rule Matrix'!$A$2:$A$142,0))) -> s.17(2), Rule 42/43 | F45: =IF(B45="","",INDEX('Rule Matrix'!$F$2:$F$142,MATCH(B45,'Rule Matrix'!$A$2:$A$142,0))) -> Compute D1/D2/C3; exempt T/O incl. land/building sale, securities @1% of sale value, interest (non-banks) | G45: =IF(B45="","",INDEX('Rule Matrix'!$G$2:$G$142,MATCH(B45,'Rule Matrix'!$A$2:$A$142,0))) -> Diff > ₹1,000 | H45: =IF(B45="","",INDEX('Rule Matrix'!$H$2:$H$142,MATCH(B45,'Rule Matrix'!$A$2:$A$142,0))) -> High | I45: =IF(B45="","",INDEX('Rule Matrix'!$J$2:$J$142,MATCH(B45,'Rule Matrix'!$A$2:$A$142,0))) -> Reverse; annual true-up by Sept return | Z45: =Applicability!A39 -> E-11 | AA45: =IF($Z$5=0,0,IF(AND(INDEX(Applicability!$E$39:$O$39,1,$Z$5)="Y",OR(Applicability!$D$39="",IFERROR(INDEX($B$4:$F$4,MATCH(Applicability!$D$39,$B$3:$F$3,0)),"N")="Y")),1,0)) -> 1 | AB45: =IF(AA45=1,SUM(AA$8:AA45),"") -> 33
A46: =IF(39>$B$5,"",39) -> 39 | B46: =IF(A46="","",INDEX($Z$8:$Z$148,MATCH(A46,$AB$8:$AB$148,0))) -> F-02 | C46: =IF(B46="","",INDEX('Rule Matrix'!$B$2:$B$142,MATCH(B46,'Rule Matrix'!$A$2:$A$142,0))) -> F. Reversals & Apportionment | D46: =IF(B46="","",INDEX('Rule Matrix'!$C$2:$C$142,MATCH(B46,'Rule Matrix'!$A$2:$A$142,0))) -> Non-business use | E46: =IF(B46="","",INDEX('Rule Matrix'!$D$2:$D$142,MATCH(B46,'Rule Matrix'!$A$2:$A$142,0))) -> s.17(1) | F46: =IF(B46="","",INDEX('Rule Matrix'!$F$2:$F$142,MATCH(B46,'Rule Matrix'!$A$2:$A$142,0))) -> Common ITC used for non-business purposes (D1 5%-type computation) | G46: =IF(B46="","",INDEX('Rule Matrix'!$G$2:$G$142,MATCH(B46,'Rule Matrix'!$A$2:$A$142,0))) -> Any | H46: =IF(B46="","",INDEX('Rule Matrix'!$H$2:$H$142,MATCH(B46,'Rule Matrix'!$A$2:$A$142,0))) -> Med | I46: =IF(B46="","",INDEX('Rule Matrix'!$J$2:$J$142,MATCH(B46,'Rule Matrix'!$A$2:$A$142,0))) -> Reverse | Z46: =Applicability!A40 -> E-12 | AA46: =IF($Z$5=0,0,IF(AND(INDEX(Applicability!$E$40:$O$40,1,$Z$5)="Y",OR(Applicability!$D$40="",IFERROR(INDEX($B$4:$F$4,MATCH(Applicability!$D$40,$B$3:$F$3,0)),"N")="Y")),1,0)) -> 1 | AB46: =IF(AA46=1,SUM(AA$8:AA46),"") -> 34
A47: =IF(40>$B$5,"",40) -> 40 | B47: =IF(A47="","",INDEX($Z$8:$Z$148,MATCH(A47,$AB$8:$AB$148,0))) -> F-04 | C47: =IF(B47="","",INDEX('Rule Matrix'!$B$2:$B$142,MATCH(B47,'Rule Matrix'!$A$2:$A$142,0))) -> F. Reversals & Apportionment | D47: =IF(B47="","",INDEX('Rule Matrix'!$C$2:$C$142,MATCH(B47,'Rule Matrix'!$A$2:$A$142,0))) -> Capital goods sold within 5 yrs | E47: =IF(B47="","",INDEX('Rule Matrix'!$D$2:$D$142,MATCH(B47,'Rule Matrix'!$A$2:$A$142,0))) -> s.18(6), Rule 44(6) | F47: =IF(B47="","",INDEX('Rule Matrix'!$F$2:$F$142,MATCH(B47,'Rule Matrix'!$A$2:$A$142,0))) -> Pay higher of ITC reduced 5%/quarter or tax on transaction value | G47: =IF(B47="","",INDEX('Rule Matrix'!$G$2:$G$142,MATCH(B47,'Rule Matrix'!$A$2:$A$142,0))) -> Any | H47: =IF(B47="","",INDEX('Rule Matrix'!$H$2:$H$142,MATCH(B47,'Rule Matrix'!$A$2:$A$142,0))) -> Med | I47: =IF(B47="","",INDEX('Rule Matrix'!$J$2:$J$142,MATCH(B47,'Rule Matrix'!$A$2:$A$142,0))) -> Pay difference | Z47: =Applicability!A41 -> E-13 | AA47: =IF($Z$5=0,0,IF(AND(INDEX(Applicability!$E$41:$O$41,1,$Z$5)="Y",OR(Applicability!$D$41="",IFERROR(INDEX($B$4:$F$4,MATCH(Applicability!$D$41,$B$3:$F$3,0)),"N")="Y")),1,0)) -> 1 | AB47: =IF(AA47=1,SUM(AA$8:AA47),"") -> 35
A48: =IF(41>$B$5,"",41) -> 41 | B48: =IF(A48="","",INDEX($Z$8:$Z$148,MATCH(A48,$AB$8:$AB$148,0))) -> F-05 | C48: =IF(B48="","",INDEX('Rule Matrix'!$B$2:$B$142,MATCH(B48,'Rule Matrix'!$A$2:$A$142,0))) -> F. Reversals & Apportionment | D48: =IF(B48="","",INDEX('Rule Matrix'!$C$2:$C$142,MATCH(B48,'Rule Matrix'!$A$2:$A$142,0))) -> Registration cancellation / composition switch | E48: =IF(B48="","",INDEX('Rule Matrix'!$D$2:$D$142,MATCH(B48,'Rule Matrix'!$A$2:$A$142,0))) -> s.18(4), s.29(5), Rule 44 | F48: =IF(B48="","",INDEX('Rule Matrix'!$F$2:$F$142,MATCH(B48,'Rule Matrix'!$A$2:$A$142,0))) -> ITC on stock & capital goods reversed | G48: =IF(B48="","",INDEX('Rule Matrix'!$G$2:$G$142,MATCH(B48,'Rule Matrix'!$A$2:$A$142,0))) -> Any | H48: =IF(B48="","",INDEX('Rule Matrix'!$H$2:$H$142,MATCH(B48,'Rule Matrix'!$A$2:$A$142,0))) -> High | I48: =IF(B48="","",INDEX('Rule Matrix'!$J$2:$J$142,MATCH(B48,'Rule Matrix'!$A$2:$A$142,0))) -> ITC-03 / GSTR-10 | Z48: =Applicability!A42 -> E-14 | AA48: =IF($Z$5=0,0,IF(AND(INDEX(Applicability!$E$42:$O$42,1,$Z$5)="Y",OR(Applicability!$D$42="",IFERROR(INDEX($B$4:$F$4,MATCH(Applicability!$D$42,$B$3:$F$3,0)),"N")="Y")),1,0)) -> 1 | AB48: =IF(AA48=1,SUM(AA$8:AA48),"") -> 36
A49: =IF(42>$B$5,"",42) -> 42 | B49: =IF(A49="","",INDEX($Z$8:$Z$148,MATCH(A49,$AB$8:$AB$148,0))) -> F-06 | C49: =IF(B49="","",INDEX('Rule Matrix'!$B$2:$B$142,MATCH(B49,'Rule Matrix'!$A$2:$A$142,0))) -> F. Reversals & Apportionment | D49: =IF(B49="","",INDEX('Rule Matrix'!$C$2:$C$142,MATCH(B49,'Rule Matrix'!$A$2:$A$142,0))) -> Rule 86B cash payment | E49: =IF(B49="","",INDEX('Rule Matrix'!$D$2:$D$142,MATCH(B49,'Rule Matrix'!$A$2:$A$142,0))) -> Rule 86B | F49: =IF(B49="","",INDEX('Rule Matrix'!$F$2:$F$142,MATCH(B49,'Rule Matrix'!$A$2:$A$142,0))) -> Taxable T/O > ₹50 lakh/month: min 1% cash unless exemption | G49: =IF(B49="","",INDEX('Rule Matrix'!$G$2:$G$142,MATCH(B49,'Rule Matrix'!$A$2:$A$142,0))) -> Breach | H49: =IF(B49="","",INDEX('Rule Matrix'!$H$2:$H$142,MATCH(B49,'Rule Matrix'!$A$2:$A$142,0))) -> Med | I49: =IF(B49="","",INDEX('Rule Matrix'!$J$2:$J$142,MATCH(B49,'Rule Matrix'!$A$2:$A$142,0))) -> Pay in cash | Z49: =Applicability!A43 -> E-15 | AA49: =IF($Z$5=0,0,IF(AND(INDEX(Applicability!$E$43:$O$43,1,$Z$5)="Y",OR(Applicability!$D$43="",IFERROR(INDEX($B$4:$F$4,MATCH(Applicability!$D$43,$B$3:$F$3,0)),"N")="Y")),1,0)) -> 1 | AB49: =IF(AA49=1,SUM(AA$8:AA49),"") -> 37
A50: =IF(43>$B$5,"",43) -> 43 | B50: =IF(A50="","",INDEX($Z$8:$Z$148,MATCH(A50,$AB$8:$AB$148,0))) -> G-01 | C50: =IF(B50="","",INDEX('Rule Matrix'!$B$2:$B$142,MATCH(B50,'Rule Matrix'!$A$2:$A$142,0))) -> G. Outward Supplies | D50: =IF(B50="","",INDEX('Rule Matrix'!$C$2:$C$142,MATCH(B50,'Rule Matrix'!$A$2:$A$142,0))) -> Turnover reconciliation | E50: =IF(B50="","",INDEX('Rule Matrix'!$D$2:$D$142,MATCH(B50,'Rule Matrix'!$A$2:$A$142,0))) -> s.35, s.44 | F50: =IF(B50="","",INDEX('Rule Matrix'!$F$2:$F$142,MATCH(B50,'Rule Matrix'!$A$2:$A$142,0))) -> Books = GSTR-1 = 3B = GSTR-9 (Table 4/5) | G50: =IF(B50="","",INDEX('Rule Matrix'!$G$2:$G$142,MATCH(B50,'Rule Matrix'!$A$2:$A$142,0))) -> Diff > ₹10,000 or 0.1% | H50: =IF(B50="","",INDEX('Rule Matrix'!$H$2:$H$142,MATCH(B50,'Rule Matrix'!$A$2:$A$142,0))) -> High | I50: =IF(B50="","",INDEX('Rule Matrix'!$J$2:$J$142,MATCH(B50,'Rule Matrix'!$A$2:$A$142,0))) -> Pay via DRC-03; reply DRC-01B (Rule 88C) | Z50: =Applicability!A44 -> F-01 | AA50: =IF($Z$5=0,0,IF(AND(INDEX(Applicability!$E$44:$O$44,1,$Z$5)="Y",OR(Applicability!$D$44="",IFERROR(INDEX($B$4:$F$4,MATCH(Applicability!$D$44,$B$3:$F$3,0)),"N")="Y")),1,0)) -> 1 | AB50: =IF(AA50=1,SUM(AA$8:AA50),"") -> 38
A51: =IF(44>$B$5,"",44) -> 44 | B51: =IF(A51="","",INDEX($Z$8:$Z$148,MATCH(A51,$AB$8:$AB$148,0))) -> G-02 | C51: =IF(B51="","",INDEX('Rule Matrix'!$B$2:$B$142,MATCH(B51,'Rule Matrix'!$A$2:$A$142,0))) -> G. Outward Supplies | D51: =IF(B51="","",INDEX('Rule Matrix'!$C$2:$C$142,MATCH(B51,'Rule Matrix'!$A$2:$A$142,0))) -> GSTR-1 vs 3B liability | E51: =IF(B51="","",INDEX('Rule Matrix'!$D$2:$D$142,MATCH(B51,'Rule Matrix'!$A$2:$A$142,0))) -> Rule 88C | F51: =IF(B51="","",INDEX('Rule Matrix'!$F$2:$F$142,MATCH(B51,'Rule Matrix'!$A$2:$A$142,0))) -> Month-wise liability; 1 > 3B | G51: =IF(B51="","",INDEX('Rule Matrix'!$G$2:$G$142,MATCH(B51,'Rule Matrix'!$A$2:$A$142,0))) -> Beyond threshold | H51: =IF(B51="","",INDEX('Rule Matrix'!$H$2:$H$142,MATCH(B51,'Rule Matrix'!$A$2:$A$142,0))) -> High | I51: =IF(B51="","",INDEX('Rule Matrix'!$J$2:$J$142,MATCH(B51,'Rule Matrix'!$A$2:$A$142,0))) -> Pay; reply DRC-01B | Z51: =Applicability!A45 -> F-02 | AA51: =IF($Z$5=0,0,IF(AND(INDEX(Applicability!$E$45:$O$45,1,$Z$5)="Y",OR(Applicability!$D$45="",IFERROR(INDEX($B$4:$F$4,MATCH(Applicability!$D$45,$B$3:$F$3,0)),"N")="Y")),1,0)) -> 1 | AB51: =IF(AA51=1,SUM(AA$8:AA51),"") -> 39
A52: =IF(45>$B$5,"",45) -> 45 | B52: =IF(A52="","",INDEX($Z$8:$Z$148,MATCH(A52,$AB$8:$AB$148,0))) -> G-03 | C52: =IF(B52="","",INDEX('Rule Matrix'!$B$2:$B$142,MATCH(B52,'Rule Matrix'!$A$2:$A$142,0))) -> G. Outward Supplies | D52: =IF(B52="","",INDEX('Rule Matrix'!$C$2:$C$142,MATCH(B52,'Rule Matrix'!$A$2:$A$142,0))) -> e-invoice vs GSTR-1 | E52: =IF(B52="","",INDEX('Rule Matrix'!$D$2:$D$142,MATCH(B52,'Rule Matrix'!$A$2:$A$142,0))) -> Rule 48(4) | F52: =IF(B52="","",INDEX('Rule Matrix'!$F$2:$F$142,MATCH(B52,'Rule Matrix'!$A$2:$A$142,0))) -> All B2B invoices above threshold have IRN; IRN value = GSTR-1 | G52: =IF(B52="","",INDEX('Rule Matrix'!$G$2:$G$142,MATCH(B52,'Rule Matrix'!$A$2:$A$142,0))) -> Any | H52: =IF(B52="","",INDEX('Rule Matrix'!$H$2:$H$142,MATCH(B52,'Rule Matrix'!$A$2:$A$142,0))) -> High | I52: =IF(B52="","",INDEX('Rule Matrix'!$J$2:$J$142,MATCH(B52,'Rule Matrix'!$A$2:$A$142,0))) -> Generate IRN / correct | Z52: =Applicability!A46 -> F-03 | AA52: =IF($Z$5=0,0,IF(AND(INDEX(Applicability!$E$46:$O$46,1,$Z$5)="Y",OR(Applicability!$D$46="",IFERROR(INDEX($B$4:$F$4,MATCH(Applicability!$D$46,$B$3:$F$3,0)),"N")="Y")),1,0)) -> 0 | AB52: =IF(AA52=1,SUM(AA$8:AA52),"")
A53: =IF(46>$B$5,"",46) -> 46 | B53: =IF(A53="","",INDEX($Z$8:$Z$148,MATCH(A53,$AB$8:$AB$148,0))) -> G-04 | C53: =IF(B53="","",INDEX('Rule Matrix'!$B$2:$B$142,MATCH(B53,'Rule Matrix'!$A$2:$A$142,0))) -> G. Outward Supplies | D53: =IF(B53="","",INDEX('Rule Matrix'!$C$2:$C$142,MATCH(B53,'Rule Matrix'!$A$2:$A$142,0))) -> e-invoice applicability & 30-day limit | E53: =IF(B53="","",INDEX('Rule Matrix'!$D$2:$D$142,MATCH(B53,'Rule Matrix'!$A$2:$A$142,0))) -> Notfn 13/2020-CT; 10/2023 | F53: =IF(B53="","",INDEX('Rule Matrix'!$F$2:$F$142,MATCH(B53,'Rule Matrix'!$A$2:$A$142,0))) -> AATO > ₹5 cr → mandatory; AATO ≥ ₹10 cr → report within 30 days | G53: =IF(B53="","",INDEX('Rule Matrix'!$G$2:$G$142,MATCH(B53,'Rule Matrix'!$A$2:$A$142,0))) -> Any | H53: =IF(B53="","",INDEX('Rule Matrix'!$H$2:$H$142,MATCH(B53,'Rule Matrix'!$A$2:$A$142,0))) -> Med | I53: =IF(B53="","",INDEX('Rule Matrix'!$J$2:$J$142,MATCH(B53,'Rule Matrix'!$A$2:$A$142,0))) -> Comply | Z53: =Applicability!A47 -> F-04 | AA53: =IF($Z$5=0,0,IF(AND(INDEX(Applicability!$E$47:$O$47,1,$Z$5)="Y",OR(Applicability!$D$47="",IFERROR(INDEX($B$4:$F$4,MATCH(Applicability!$D$47,$B$3:$F$3,0)),"N")="Y")),1,0)) -> 1 | AB53: =IF(AA53=1,SUM(AA$8:AA53),"") -> 40
A54: =IF(47>$B$5,"",47) -> 47 | B54: =IF(A54="","",INDEX($Z$8:$Z$148,MATCH(A54,$AB$8:$AB$148,0))) -> G-05 | C54: =IF(B54="","",INDEX('Rule Matrix'!$B$2:$B$142,MATCH(B54,'Rule Matrix'!$A$2:$A$142,0))) -> G. Outward Supplies | D54: =IF(B54="","",INDEX('Rule Matrix'!$C$2:$C$142,MATCH(B54,'Rule Matrix'!$A$2:$A$142,0))) -> E-way bill vs sales | E54: =IF(B54="","",INDEX('Rule Matrix'!$D$2:$D$142,MATCH(B54,'Rule Matrix'!$A$2:$A$142,0))) -> Rule 138 | F54: =IF(B54="","",INDEX('Rule Matrix'!$F$2:$F$142,MATCH(B54,'Rule Matrix'!$A$2:$A$142,0))) -> EWB generated without invoice in GSTR-1 → suppressed sales | G54: =IF(B54="","",INDEX('Rule Matrix'!$G$2:$G$142,MATCH(B54,'Rule Matrix'!$A$2:$A$142,0))) -> Any | H54: =IF(B54="","",INDEX('Rule Matrix'!$H$2:$H$142,MATCH(B54,'Rule Matrix'!$A$2:$A$142,0))) -> High | I54: =IF(B54="","",INDEX('Rule Matrix'!$J$2:$J$142,MATCH(B54,'Rule Matrix'!$A$2:$A$142,0))) -> Explain/pay | Z54: =Applicability!A48 -> F-05 | AA54: =IF($Z$5=0,0,IF(AND(INDEX(Applicability!$E$48:$O$48,1,$Z$5)="Y",OR(Applicability!$D$48="",IFERROR(INDEX($B$4:$F$4,MATCH(Applicability!$D$48,$B$3:$F$3,0)),"N")="Y")),1,0)) -> 1 | AB54: =IF(AA54=1,SUM(AA$8:AA54),"") -> 41
A55: =IF(48>$B$5,"",48) -> 48 | B55: =IF(A55="","",INDEX($Z$8:$Z$148,MATCH(A55,$AB$8:$AB$148,0))) -> G-06 | C55: =IF(B55="","",INDEX('Rule Matrix'!$B$2:$B$142,MATCH(B55,'Rule Matrix'!$A$2:$A$142,0))) -> G. Outward Supplies | D55: =IF(B55="","",INDEX('Rule Matrix'!$C$2:$C$142,MATCH(B55,'Rule Matrix'!$A$2:$A$142,0))) -> Other income scan | E55: =IF(B55="","",INDEX('Rule Matrix'!$D$2:$D$142,MATCH(B55,'Rule Matrix'!$A$2:$A$142,0))) -> s.7, s.15 | F55: =IF(B55="","",INDEX('Rule Matrix'!$F$2:$F$142,MATCH(B55,'Rule Matrix'!$A$2:$A$142,0))) -> Taxability of scrap sale, asset sale, rent, late-payment interest (s.15(2)(d)), notice pay, canteen recovery, commission, mgmt fees. LD/penalties for breach not taxable (Circ 178/10/2022); RBI-mandated penal charges of banks/NBFCs not taxable (Circ 245/02/2025) | G55: =IF(B55="","",INDEX('Rule Matrix'!$G$2:$G$142,MATCH(B55,'Rule Matrix'!$A$2:$A$142,0))) -> Any untaxed | H55: =IF(B55="","",INDEX('Rule Matrix'!$H$2:$H$142,MATCH(B55,'Rule Matrix'!$A$2:$A$142,0))) -> High | I55: =IF(B55="","",INDEX('Rule Matrix'!$J$2:$J$142,MATCH(B55,'Rule Matrix'!$A$2:$A$142,0))) -> Pay tax | Z55: =Applicability!A49 -> F-06 | AA55: =IF($Z$5=0,0,IF(AND(INDEX(Applicability!$E$49:$O$49,1,$Z$5)="Y",OR(Applicability!$D$49="",IFERROR(INDEX($B$4:$F$4,MATCH(Applicability!$D$49,$B$3:$F$3,0)),"N")="Y")),1,0)) -> 1 | AB55: =IF(AA55=1,SUM(AA$8:AA55),"") -> 42
A56: =IF(49>$B$5,"",49) -> 49 | B56: =IF(A56="","",INDEX($Z$8:$Z$148,MATCH(A56,$AB$8:$AB$148,0))) -> G-07 | C56: =IF(B56="","",INDEX('Rule Matrix'!$B$2:$B$142,MATCH(B56,'Rule Matrix'!$A$2:$A$142,0))) -> G. Outward Supplies | D56: =IF(B56="","",INDEX('Rule Matrix'!$C$2:$C$142,MATCH(B56,'Rule Matrix'!$A$2:$A$142,0))) -> Schedule I deemed supplies | E56: =IF(B56="","",INDEX('Rule Matrix'!$D$2:$D$142,MATCH(B56,'Rule Matrix'!$A$2:$A$142,0))) -> Sch. I, Rule 28 | F56: =IF(B56="","",INDEX('Rule Matrix'!$F$2:$F$142,MATCH(B56,'Rule Matrix'!$A$2:$A$142,0))) -> Stock transfer to other GSTIN; RP supplies w/o consideration; gifts to employee > ₹50k | G56: =IF(B56="","",INDEX('Rule Matrix'!$G$2:$G$142,MATCH(B56,'Rule Matrix'!$A$2:$A$142,0))) -> Any | H56: =IF(B56="","",INDEX('Rule Matrix'!$H$2:$H$142,MATCH(B56,'Rule Matrix'!$A$2:$A$142,0))) -> High | I56: =IF(B56="","",INDEX('Rule Matrix'!$J$2:$J$142,MATCH(B56,'Rule Matrix'!$A$2:$A$142,0))) -> Pay tax | Z56: =Applicability!A50 -> F-07 | AA56: =IF($Z$5=0,0,IF(AND(INDEX(Applicability!$E$50:$O$50,1,$Z$5)="Y",OR(Applicability!$D$50="",IFERROR(INDEX($B$4:$F$4,MATCH(Applicability!$D$50,$B$3:$F$3,0)),"N")="Y")),1,0)) -> 0 | AB56: =IF(AA56=1,SUM(AA$8:AA56),"")
A57: =IF(50>$B$5,"",50) -> 50 | B57: =IF(A57="","",INDEX($Z$8:$Z$148,MATCH(A57,$AB$8:$AB$148,0))) -> G-08 | C57: =IF(B57="","",INDEX('Rule Matrix'!$B$2:$B$142,MATCH(B57,'Rule Matrix'!$A$2:$A$142,0))) -> G. Outward Supplies | D57: =IF(B57="","",INDEX('Rule Matrix'!$C$2:$C$142,MATCH(B57,'Rule Matrix'!$A$2:$A$142,0))) -> Related party valuation | E57: =IF(B57="","",INDEX('Rule Matrix'!$D$2:$D$142,MATCH(B57,'Rule Matrix'!$A$2:$A$142,0))) -> s.15(4), Rule 28 | F57: =IF(B57="","",INDEX('Rule Matrix'!$F$2:$F$142,MATCH(B57,'Rule Matrix'!$A$2:$A$142,0))) -> RP transaction value vs open market; full ITC buyer exception (2nd proviso Rule 28) | G57: =IF(B57="","",INDEX('Rule Matrix'!$G$2:$G$142,MATCH(B57,'Rule Matrix'!$A$2:$A$142,0))) -> Deviation | H57: =IF(B57="","",INDEX('Rule Matrix'!$H$2:$H$142,MATCH(B57,'Rule Matrix'!$A$2:$A$142,0))) -> Med | I57: =IF(B57="","",INDEX('Rule Matrix'!$J$2:$J$142,MATCH(B57,'Rule Matrix'!$A$2:$A$142,0))) -> Re-value | Z57: =Applicability!A51 -> G-01 | AA57: =IF($Z$5=0,0,IF(AND(INDEX(Applicability!$E$51:$O$51,1,$Z$5)="Y",OR(Applicability!$D$51="",IFERROR(INDEX($B$4:$F$4,MATCH(Applicability!$D$51,$B$3:$F$3,0)),"N")="Y")),1,0)) -> 1 | AB57: =IF(AA57=1,SUM(AA$8:AA57),"") -> 43
A58: =IF(51>$B$5,"",51) -> 51 | B58: =IF(A58="","",INDEX($Z$8:$Z$148,MATCH(A58,$AB$8:$AB$148,0))) -> G-09 | C58: =IF(B58="","",INDEX('Rule Matrix'!$B$2:$B$142,MATCH(B58,'Rule Matrix'!$A$2:$A$142,0))) -> G. Outward Supplies | D58: =IF(B58="","",INDEX('Rule Matrix'!$C$2:$C$142,MATCH(B58,'Rule Matrix'!$A$2:$A$142,0))) -> Advances received | E58: =IF(B58="","",INDEX('Rule Matrix'!$D$2:$D$142,MATCH(B58,'Rule Matrix'!$A$2:$A$142,0))) -> s.12, s.13 | F58: =IF(B58="","",INDEX('Rule Matrix'!$F$2:$F$142,MATCH(B58,'Rule Matrix'!$A$2:$A$142,0))) -> Tax on advances for services; not for goods (Notfn 66/2017) | G58: =IF(B58="","",INDEX('Rule Matrix'!$G$2:$G$142,MATCH(B58,'Rule Matrix'!$A$2:$A$142,0))) -> Any | H58: =IF(B58="","",INDEX('Rule Matrix'!$H$2:$H$142,MATCH(B58,'Rule Matrix'!$A$2:$A$142,0))) -> Med | I58: =IF(B58="","",INDEX('Rule Matrix'!$J$2:$J$142,MATCH(B58,'Rule Matrix'!$A$2:$A$142,0))) -> Pay; adjust on invoice | Z58: =Applicability!A52 -> G-02 | AA58: =IF($Z$5=0,0,IF(AND(INDEX(Applicability!$E$52:$O$52,1,$Z$5)="Y",OR(Applicability!$D$52="",IFERROR(INDEX($B$4:$F$4,MATCH(Applicability!$D$52,$B$3:$F$3,0)),"N")="Y")),1,0)) -> 1 | AB58: =IF(AA58=1,SUM(AA$8:AA58),"") -> 44
A59: =IF(52>$B$5,"",52) -> 52 | B59: =IF(A59="","",INDEX($Z$8:$Z$148,MATCH(A59,$AB$8:$AB$148,0))) -> G-10 | C59: =IF(B59="","",INDEX('Rule Matrix'!$B$2:$B$142,MATCH(B59,'Rule Matrix'!$A$2:$A$142,0))) -> G. Outward Supplies | D59: =IF(B59="","",INDEX('Rule Matrix'!$C$2:$C$142,MATCH(B59,'Rule Matrix'!$A$2:$A$142,0))) -> Rate & HSN validation | E59: =IF(B59="","",INDEX('Rule Matrix'!$D$2:$D$142,MATCH(B59,'Rule Matrix'!$A$2:$A$142,0))) -> Rate notfns; s.14 | F59: =IF(B59="","",INDEX('Rule Matrix'!$F$2:$F$142,MATCH(B59,'Rule Matrix'!$A$2:$A$142,0))) -> HSN-rate master check; rate change at 22.9.2025 (GST 2.0) applied per s.14 time-of-supply | G59: =IF(B59="","",INDEX('Rule Matrix'!$G$2:$G$142,MATCH(B59,'Rule Matrix'!$A$2:$A$142,0))) -> Any | H59: =IF(B59="","",INDEX('Rule Matrix'!$H$2:$H$142,MATCH(B59,'Rule Matrix'!$A$2:$A$142,0))) -> High | I59: =IF(B59="","",INDEX('Rule Matrix'!$J$2:$J$142,MATCH(B59,'Rule Matrix'!$A$2:$A$142,0))) -> Pay / credit note | Z59: =Applicability!A53 -> G-03 | AA59: =IF($Z$5=0,0,IF(AND(INDEX(Applicability!$E$53:$O$53,1,$Z$5)="Y",OR(Applicability!$D$53="",IFERROR(INDEX($B$4:$F$4,MATCH(Applicability!$D$53,$B$3:$F$3,0)),"N")="Y")),1,0)) -> 1 | AB59: =IF(AA59=1,SUM(AA$8:AA59),"") -> 45
A60: =IF(53>$B$5,"",53) -> 53 | B60: =IF(A60="","",INDEX($Z$8:$Z$148,MATCH(A60,$AB$8:$AB$148,0))) -> G-11 | C60: =IF(B60="","",INDEX('Rule Matrix'!$B$2:$B$142,MATCH(B60,'Rule Matrix'!$A$2:$A$142,0))) -> G. Outward Supplies | D60: =IF(B60="","",INDEX('Rule Matrix'!$C$2:$C$142,MATCH(B60,'Rule Matrix'!$A$2:$A$142,0))) -> Exempt/nil/non-GST classification | E60: =IF(B60="","",INDEX('Rule Matrix'!$D$2:$D$142,MATCH(B60,'Rule Matrix'!$A$2:$A$142,0))) -> s.11, exemption notfns | F60: =IF(B60="","",INDEX('Rule Matrix'!$F$2:$F$142,MATCH(B60,'Rule Matrix'!$A$2:$A$142,0))) -> Exemption entry validity; condition compliance | G60: =IF(B60="","",INDEX('Rule Matrix'!$G$2:$G$142,MATCH(B60,'Rule Matrix'!$A$2:$A$142,0))) -> Any | H60: =IF(B60="","",INDEX('Rule Matrix'!$H$2:$H$142,MATCH(B60,'Rule Matrix'!$A$2:$A$142,0))) -> Med | I60: =IF(B60="","",INDEX('Rule Matrix'!$J$2:$J$142,MATCH(B60,'Rule Matrix'!$A$2:$A$142,0))) -> Pay | Z60: =Applicability!A54 -> G-04 | AA60: =IF($Z$5=0,0,IF(AND(INDEX(Applicability!$E$54:$O$54,1,$Z$5)="Y",OR(Applicability!$D$54="",IFERROR(INDEX($B$4:$F$4,MATCH(Applicability!$D$54,$B$3:$F$3,0)),"N")="Y")),1,0)) -> 1 | AB60: =IF(AA60=1,SUM(AA$8:AA60),"") -> 46
A61: =IF(54>$B$5,"",54) -> 54 | B61: =IF(A61="","",INDEX($Z$8:$Z$148,MATCH(A61,$AB$8:$AB$148,0))) -> G-12 | C61: =IF(B61="","",INDEX('Rule Matrix'!$B$2:$B$142,MATCH(B61,'Rule Matrix'!$A$2:$A$142,0))) -> G. Outward Supplies | D61: =IF(B61="","",INDEX('Rule Matrix'!$C$2:$C$142,MATCH(B61,'Rule Matrix'!$A$2:$A$142,0))) -> Invoice series gaps | E61: =IF(B61="","",INDEX('Rule Matrix'!$D$2:$D$142,MATCH(B61,'Rule Matrix'!$A$2:$A$142,0))) -> Rule 46(b) | F61: =IF(B61="","",INDEX('Rule Matrix'!$F$2:$F$142,MATCH(B61,'Rule Matrix'!$A$2:$A$142,0))) -> Missing/cancelled invoice numbers | G61: =IF(B61="","",INDEX('Rule Matrix'!$G$2:$G$142,MATCH(B61,'Rule Matrix'!$A$2:$A$142,0))) -> Any | H61: =IF(B61="","",INDEX('Rule Matrix'!$H$2:$H$142,MATCH(B61,'Rule Matrix'!$A$2:$A$142,0))) -> Med | I61: =IF(B61="","",INDEX('Rule Matrix'!$J$2:$J$142,MATCH(B61,'Rule Matrix'!$A$2:$A$142,0))) -> Explain | Z61: =Applicability!A55 -> G-05 | AA61: =IF($Z$5=0,0,IF(AND(INDEX(Applicability!$E$55:$O$55,1,$Z$5)="Y",OR(Applicability!$D$55="",IFERROR(INDEX($B$4:$F$4,MATCH(Applicability!$D$55,$B$3:$F$3,0)),"N")="Y")),1,0)) -> 1 | AB61: =IF(AA61=1,SUM(AA$8:AA61),"") -> 47
A62: =IF(55>$B$5,"",55) -> 55 | B62: =IF(A62="","",INDEX($Z$8:$Z$148,MATCH(A62,$AB$8:$AB$148,0))) -> G-14 | C62: =IF(B62="","",INDEX('Rule Matrix'!$B$2:$B$142,MATCH(B62,'Rule Matrix'!$A$2:$A$142,0))) -> G. Outward Supplies | D62: =IF(B62="","",INDEX('Rule Matrix'!$C$2:$C$142,MATCH(B62,'Rule Matrix'!$A$2:$A$142,0))) -> TDS/TCS credits vs turnover | E62: =IF(B62="","",INDEX('Rule Matrix'!$D$2:$D$142,MATCH(B62,'Rule Matrix'!$A$2:$A$142,0))) -> s.51, s.52 | F62: =IF(B62="","",INDEX('Rule Matrix'!$F$2:$F$142,MATCH(B62,'Rule Matrix'!$A$2:$A$142,0))) -> Turnover implied by TDS/TCS ≤ declared turnover | G62: =IF(B62="","",INDEX('Rule Matrix'!$G$2:$G$142,MATCH(B62,'Rule Matrix'!$A$2:$A$142,0))) -> Any | H62: =IF(B62="","",INDEX('Rule Matrix'!$H$2:$H$142,MATCH(B62,'Rule Matrix'!$A$2:$A$142,0))) -> Med | I62: =IF(B62="","",INDEX('Rule Matrix'!$J$2:$J$142,MATCH(B62,'Rule Matrix'!$A$2:$A$142,0))) -> Reconcile | Z62: =Applicability!A56 -> G-06 | AA62: =IF($Z$5=0,0,IF(AND(INDEX(Applicability!$E$56:$O$56,1,$Z$5)="Y",OR(Applicability!$D$56="",IFERROR(INDEX($B$4:$F$4,MATCH(Applicability!$D$56,$B$3:$F$3,0)),"N")="Y")),1,0)) -> 1 | AB62: =IF(AA62=1,SUM(AA$8:AA62),"") -> 48
A63: =IF(56>$B$5,"",56) -> 56 | B63: =IF(A63="","",INDEX($Z$8:$Z$148,MATCH(A63,$AB$8:$AB$148,0))) -> G-15 | C63: =IF(B63="","",INDEX('Rule Matrix'!$B$2:$B$142,MATCH(B63,'Rule Matrix'!$A$2:$A$142,0))) -> G. Outward Supplies | D63: =IF(B63="","",INDEX('Rule Matrix'!$C$2:$C$142,MATCH(B63,'Rule Matrix'!$A$2:$A$142,0))) -> Amendment time limit | E63: =IF(B63="","",INDEX('Rule Matrix'!$D$2:$D$142,MATCH(B63,'Rule Matrix'!$A$2:$A$142,0))) -> s.37(3), s.39(9) | F63: =IF(B63="","",INDEX('Rule Matrix'!$F$2:$F$142,MATCH(B63,'Rule Matrix'!$A$2:$A$142,0))) -> Amendments made within 30 Nov next FY | G63: =IF(B63="","",INDEX('Rule Matrix'!$G$2:$G$142,MATCH(B63,'Rule Matrix'!$A$2:$A$142,0))) -> Late | H63: =IF(B63="","",INDEX('Rule Matrix'!$H$2:$H$142,MATCH(B63,'Rule Matrix'!$A$2:$A$142,0))) -> Low | I63: =IF(B63="","",INDEX('Rule Matrix'!$J$2:$J$142,MATCH(B63,'Rule Matrix'!$A$2:$A$142,0))) -> — | Z63: =Applicability!A57 -> G-07 | AA63: =IF($Z$5=0,0,IF(AND(INDEX(Applicability!$E$57:$O$57,1,$Z$5)="Y",OR(Applicability!$D$57="",IFERROR(INDEX($B$4:$F$4,MATCH(Applicability!$D$57,$B$3:$F$3,0)),"N")="Y")),1,0)) -> 1 | AB63: =IF(AA63=1,SUM(AA$8:AA63),"") -> 49
A64: =IF(57>$B$5,"",57) -> 57 | B64: =IF(A64="","",INDEX($Z$8:$Z$148,MATCH(A64,$AB$8:$AB$148,0))) -> H-01 | C64: =IF(B64="","",INDEX('Rule Matrix'!$B$2:$B$142,MATCH(B64,'Rule Matrix'!$A$2:$A$142,0))) -> H. Credit & Debit Notes | D64: =IF(B64="","",INDEX('Rule Matrix'!$C$2:$C$142,MATCH(B64,'Rule Matrix'!$A$2:$A$142,0))) -> CN time limit | E64: =IF(B64="","",INDEX('Rule Matrix'!$D$2:$D$142,MATCH(B64,'Rule Matrix'!$A$2:$A$142,0))) -> s.34(2) | F64: =IF(B64="","",INDEX('Rule Matrix'!$F$2:$F$142,MATCH(B64,'Rule Matrix'!$A$2:$A$142,0))) -> CN issued / declared by earlier of 30 Nov next FY or annual return | G64: =IF(B64="","",INDEX('Rule Matrix'!$G$2:$G$142,MATCH(B64,'Rule Matrix'!$A$2:$A$142,0))) -> Late | H64: =IF(B64="","",INDEX('Rule Matrix'!$H$2:$H$142,MATCH(B64,'Rule Matrix'!$A$2:$A$142,0))) -> High | I64: =IF(B64="","",INDEX('Rule Matrix'!$J$2:$J$142,MATCH(B64,'Rule Matrix'!$A$2:$A$142,0))) -> Reverse reduction | Z64: =Applicability!A58 -> G-08 | AA64: =IF($Z$5=0,0,IF(AND(INDEX(Applicability!$E$58:$O$58,1,$Z$5)="Y",OR(Applicability!$D$58="",IFERROR(INDEX($B$4:$F$4,MATCH(Applicability!$D$58,$B$3:$F$3,0)),"N")="Y")),1,0)) -> 1 | AB64: =IF(AA64=1,SUM(AA$8:AA64),"") -> 50
A65: =IF(58>$B$5,"",58) -> 58 | B65: =IF(A65="","",INDEX($Z$8:$Z$148,MATCH(A65,$AB$8:$AB$148,0))) -> H-02 | C65: =IF(B65="","",INDEX('Rule Matrix'!$B$2:$B$142,MATCH(B65,'Rule Matrix'!$A$2:$A$142,0))) -> H. Credit & Debit Notes | D65: =IF(B65="","",INDEX('Rule Matrix'!$C$2:$C$142,MATCH(B65,'Rule Matrix'!$A$2:$A$142,0))) -> CN linkage to invoice | E65: =IF(B65="","",INDEX('Rule Matrix'!$D$2:$D$142,MATCH(B65,'Rule Matrix'!$A$2:$A$142,0))) -> s.34(1), Circ 212/2024 | F65: =IF(B65="","",INDEX('Rule Matrix'!$F$2:$F$142,MATCH(B65,'Rule Matrix'!$A$2:$A$142,0))) -> Each CN linked to original invoice(s) | G65: =IF(B65="","",INDEX('Rule Matrix'!$G$2:$G$142,MATCH(B65,'Rule Matrix'!$A$2:$A$142,0))) -> Missing | H65: =IF(B65="","",INDEX('Rule Matrix'!$H$2:$H$142,MATCH(B65,'Rule Matrix'!$A$2:$A$142,0))) -> Med | I65: =IF(B65="","",INDEX('Rule Matrix'!$J$2:$J$142,MATCH(B65,'Rule Matrix'!$A$2:$A$142,0))) -> Link | Z65: =Applicability!A59 -> G-09 | AA65: =IF($Z$5=0,0,IF(AND(INDEX(Applicability!$E$59:$O$59,1,$Z$5)="Y",OR(Applicability!$D$59="",IFERROR(INDEX($B$4:$F$4,MATCH(Applicability!$D$59,$B$3:$F$3,0)),"N")="Y")),1,0)) -> 1 | AB65: =IF(AA65=1,SUM(AA$8:AA65),"") -> 51
A66: =IF(59>$B$5,"",59) -> 59 | B66: =IF(A66="","",INDEX($Z$8:$Z$148,MATCH(A66,$AB$8:$AB$148,0))) -> H-03 | C66: =IF(B66="","",INDEX('Rule Matrix'!$B$2:$B$142,MATCH(B66,'Rule Matrix'!$A$2:$A$142,0))) -> H. Credit & Debit Notes | D66: =IF(B66="","",INDEX('Rule Matrix'!$C$2:$C$142,MATCH(B66,'Rule Matrix'!$A$2:$A$142,0))) -> Recipient ITC reversal for tax reduction | E66: =IF(B66="","",INDEX('Rule Matrix'!$D$2:$D$142,MATCH(B66,'Rule Matrix'!$A$2:$A$142,0))) -> s.34(2) proviso subst. by FA 2025 w.e.f. 01.10.2025 (Notfn 16/2025-CT); IMS; Circ 212/2024 (earlier CNs) | F66: =IF(B66="","",INDEX('Rule Matrix'!$F$2:$F$142,MATCH(B66,'Rule Matrix'!$A$2:$A$142,0))) -> CNs from 01.10.2025: output reduction only if registered recipient reversed attributable ITC (IMS accept); IMS-rejected CN adds back to supplier liability. Earlier CNs: incidence-not-passed test / CA certificate route (Circ 212/2024) | G66: =IF(B66="","",INDEX('Rule Matrix'!$G$2:$G$142,MATCH(B66,'Rule Matrix'!$A$2:$A$142,0))) -> Unproved | H66: =IF(B66="","",INDEX('Rule Matrix'!$H$2:$H$142,MATCH(B66,'Rule Matrix'!$A$2:$A$142,0))) -> High | I66: =IF(B66="","",INDEX('Rule Matrix'!$J$2:$J$142,MATCH(B66,'Rule Matrix'!$A$2:$A$142,0))) -> Obtain certificate | Z66: =Applicability!A60 -> G-10 | AA66: =IF($Z$5=0,0,IF(AND(INDEX(Applicability!$E$60:$O$60,1,$Z$5)="Y",OR(Applicability!$D$60="",IFERROR(INDEX($B$4:$F$4,MATCH(Applicability!$D$60,$B$3:$F$3,0)),"N")="Y")),1,0)) -> 1 | AB66: =IF(AA66=1,SUM(AA$8:AA66),"") -> 52
A67: =IF(60>$B$5,"",60) -> 60 | B67: =IF(A67="","",INDEX($Z$8:$Z$148,MATCH(A67,$AB$8:$AB$148,0))) -> H-04 | C67: =IF(B67="","",INDEX('Rule Matrix'!$B$2:$B$142,MATCH(B67,'Rule Matrix'!$A$2:$A$142,0))) -> H. Credit & Debit Notes | D67: =IF(B67="","",INDEX('Rule Matrix'!$C$2:$C$142,MATCH(B67,'Rule Matrix'!$A$2:$A$142,0))) -> Post-sale discounts | E67: =IF(B67="","",INDEX('Rule Matrix'!$D$2:$D$142,MATCH(B67,'Rule Matrix'!$A$2:$A$142,0))) -> s.15(3)(b); Circ 92/2019, 251/08/2025; FA 2026 substitution – awaiting notification | F67: =IF(B67="","",INDEX('Rule Matrix'!$F$2:$F$142,MATCH(B67,'Rule Matrix'!$A$2:$A$142,0))) -> Until FA 2026 amendment notified: pre-agreement + invoice linkage + recipient ITC reversal. Financial/commercial CN: no output reduction, and recipient need NOT reverse ITC (Circ 251/2025). Discount is dealer consideration only if tied to end-customer agreement; promotion taxable only if agreed service | G67: =IF(B67="","",INDEX('Rule Matrix'!$G$2:$G$142,MATCH(B67,'Rule Matrix'!$A$2:$A$142,0))) -> Non-compliant | H67: =IF(B67="","",INDEX('Rule Matrix'!$H$2:$H$142,MATCH(B67,'Rule Matrix'!$A$2:$A$142,0))) -> High | I67: =IF(B67="","",INDEX('Rule Matrix'!$J$2:$J$142,MATCH(B67,'Rule Matrix'!$A$2:$A$142,0))) -> Re-issue as financial CN | Z67: =Applicability!A61 -> G-11 | AA67: =IF($Z$5=0,0,IF(AND(INDEX(Applicability!$E$61:$O$61,1,$Z$5)="Y",OR(Applicability!$D$61="",IFERROR(INDEX($B$4:$F$4,MATCH(Applicability!$D$61,$B$3:$F$3,0)),"N")="Y")),1,0)) -> 1 | AB67: =IF(AA67=1,SUM(AA$8:AA67),"") -> 53
A68: =IF(61>$B$5,"",61) -> 61 | B68: =IF(A68="","",INDEX($Z$8:$Z$148,MATCH(A68,$AB$8:$AB$148,0))) -> H-05 | C68: =IF(B68="","",INDEX('Rule Matrix'!$B$2:$B$142,MATCH(B68,'Rule Matrix'!$A$2:$A$142,0))) -> H. Credit & Debit Notes | D68: =IF(B68="","",INDEX('Rule Matrix'!$C$2:$C$142,MATCH(B68,'Rule Matrix'!$A$2:$A$142,0))) -> Books CN vs GST CN | E68: =IF(B68="","",INDEX('Rule Matrix'!$D$2:$D$142,MATCH(B68,'Rule Matrix'!$A$2:$A$142,0))) -> — | F68: =IF(B68="","",INDEX('Rule Matrix'!$F$2:$F$142,MATCH(B68,'Rule Matrix'!$A$2:$A$142,0))) -> Financial CNs (no GST) vs GST CNs – explain difference | G68: =IF(B68="","",INDEX('Rule Matrix'!$G$2:$G$142,MATCH(B68,'Rule Matrix'!$A$2:$A$142,0))) -> Diff | H68: =IF(B68="","",INDEX('Rule Matrix'!$H$2:$H$142,MATCH(B68,'Rule Matrix'!$A$2:$A$142,0))) -> Low | I68: =IF(B68="","",INDEX('Rule Matrix'!$J$2:$J$142,MATCH(B68,'Rule Matrix'!$A$2:$A$142,0))) -> Reconcile | Z68: =Applicability!A62 -> G-12 | AA68: =IF($Z$5=0,0,IF(AND(INDEX(Applicability!$E$62:$O$62,1,$Z$5)="Y",OR(Applicability!$D$62="",IFERROR(INDEX($B$4:$F$4,MATCH(Applicability!$D$62,$B$3:$F$3,0)),"N")="Y")),1,0)) -> 1 | AB68: =IF(AA68=1,SUM(AA$8:AA68),"") -> 54
A69: =IF(62>$B$5,"",62) -> 62 | B69: =IF(A69="","",INDEX($Z$8:$Z$148,MATCH(A69,$AB$8:$AB$148,0))) -> H-06 | C69: =IF(B69="","",INDEX('Rule Matrix'!$B$2:$B$142,MATCH(B69,'Rule Matrix'!$A$2:$A$142,0))) -> H. Credit & Debit Notes | D69: =IF(B69="","",INDEX('Rule Matrix'!$C$2:$C$142,MATCH(B69,'Rule Matrix'!$A$2:$A$142,0))) -> Purchase-side CNs | E69: =IF(B69="","",INDEX('Rule Matrix'!$D$2:$D$142,MATCH(B69,'Rule Matrix'!$A$2:$A$142,0))) -> s.16, s.34 | F69: =IF(B69="","",INDEX('Rule Matrix'!$F$2:$F$142,MATCH(B69,'Rule Matrix'!$A$2:$A$142,0))) -> CNs received in 2B reversed in 3B; IMS rejected/pending CNs tracked | G69: =IF(B69="","",INDEX('Rule Matrix'!$G$2:$G$142,MATCH(B69,'Rule Matrix'!$A$2:$A$142,0))) -> Any | H69: =IF(B69="","",INDEX('Rule Matrix'!$H$2:$H$142,MATCH(B69,'Rule Matrix'!$A$2:$A$142,0))) -> High | I69: =IF(B69="","",INDEX('Rule Matrix'!$J$2:$J$142,MATCH(B69,'Rule Matrix'!$A$2:$A$142,0))) -> Reverse in 3B | Z69: =Applicability!A63 -> G-13 | AA69: =IF($Z$5=0,0,IF(AND(INDEX(Applicability!$E$63:$O$63,1,$Z$5)="Y",OR(Applicability!$D$63="",IFERROR(INDEX($B$4:$F$4,MATCH(Applicability!$D$63,$B$3:$F$3,0)),"N")="Y")),1,0)) -> 0 | AB69: =IF(AA69=1,SUM(AA$8:AA69),"")
A70: =IF(63>$B$5,"",63) -> 63 | B70: =IF(A70="","",INDEX($Z$8:$Z$148,MATCH(A70,$AB$8:$AB$148,0))) -> H-07 | C70: =IF(B70="","",INDEX('Rule Matrix'!$B$2:$B$142,MATCH(B70,'Rule Matrix'!$A$2:$A$142,0))) -> H. Credit & Debit Notes | D70: =IF(B70="","",INDEX('Rule Matrix'!$C$2:$C$142,MATCH(B70,'Rule Matrix'!$A$2:$A$142,0))) -> Debit notes – ITC time limit | E70: =IF(B70="","",INDEX('Rule Matrix'!$D$2:$D$142,MATCH(B70,'Rule Matrix'!$A$2:$A$142,0))) -> s.16(4) as amended by FA 2020 w.e.f. 01.01.2021 | F70: =IF(B70="","",INDEX('Rule Matrix'!$F$2:$F$142,MATCH(B70,'Rule Matrix'!$A$2:$A$142,0))) -> Time limit reckoned from DN date, not original invoice | G70: =IF(B70="","",INDEX('Rule Matrix'!$G$2:$G$142,MATCH(B70,'Rule Matrix'!$A$2:$A$142,0))) -> Mis-applied | H70: =IF(B70="","",INDEX('Rule Matrix'!$H$2:$H$142,MATCH(B70,'Rule Matrix'!$A$2:$A$142,0))) -> Low | I70: =IF(B70="","",INDEX('Rule Matrix'!$J$2:$J$142,MATCH(B70,'Rule Matrix'!$A$2:$A$142,0))) -> Correct | Z70: =Applicability!A64 -> G-14 | AA70: =IF($Z$5=0,0,IF(AND(INDEX(Applicability!$E$64:$O$64,1,$Z$5)="Y",OR(Applicability!$D$64="",IFERROR(INDEX($B$4:$F$4,MATCH(Applicability!$D$64,$B$3:$F$3,0)),"N")="Y")),1,0)) -> 1 | AB70: =IF(AA70=1,SUM(AA$8:AA70),"") -> 55
A71: =IF(64>$B$5,"",64) -> 64 | B71: =IF(A71="","",INDEX($Z$8:$Z$148,MATCH(A71,$AB$8:$AB$148,0))) -> H-08 | C71: =IF(B71="","",INDEX('Rule Matrix'!$B$2:$B$142,MATCH(B71,'Rule Matrix'!$A$2:$A$142,0))) -> H. Credit & Debit Notes | D71: =IF(B71="","",INDEX('Rule Matrix'!$C$2:$C$142,MATCH(B71,'Rule Matrix'!$A$2:$A$142,0))) -> Unusual CN pattern | E71: =IF(B71="","",INDEX('Rule Matrix'!$D$2:$D$142,MATCH(B71,'Rule Matrix'!$A$2:$A$142,0))) -> — | F71: =IF(B71="","",INDEX('Rule Matrix'!$F$2:$F$142,MATCH(B71,'Rule Matrix'!$A$2:$A$142,0))) -> High CN % to same party / year-end CNs reversing sales | G71: =IF(B71="","",INDEX('Rule Matrix'!$G$2:$G$142,MATCH(B71,'Rule Matrix'!$A$2:$A$142,0))) -> > 10% of party sales | H71: =IF(B71="","",INDEX('Rule Matrix'!$H$2:$H$142,MATCH(B71,'Rule Matrix'!$A$2:$A$142,0))) -> Med | I71: =IF(B71="","",INDEX('Rule Matrix'!$J$2:$J$142,MATCH(B71,'Rule Matrix'!$A$2:$A$142,0))) -> Review | Z71: =Applicability!A65 -> G-15 | AA71: =IF($Z$5=0,0,IF(AND(INDEX(Applicability!$E$65:$O$65,1,$Z$5)="Y",OR(Applicability!$D$65="",IFERROR(INDEX($B$4:$F$4,MATCH(Applicability!$D$65,$B$3:$F$3,0)),"N")="Y")),1,0)) -> 1 | AB71: =IF(AA71=1,SUM(AA$8:AA71),"") -> 56
A72: =IF(65>$B$5,"",65) -> 65 | B72: =IF(A72="","",INDEX($Z$8:$Z$148,MATCH(A72,$AB$8:$AB$148,0))) -> I-01 | C72: =IF(B72="","",INDEX('Rule Matrix'!$B$2:$B$142,MATCH(B72,'Rule Matrix'!$A$2:$A$142,0))) -> I. Annual Report Linkages | D72: =IF(B72="","",INDEX('Rule Matrix'!$C$2:$C$142,MATCH(B72,'Rule Matrix'!$A$2:$A$142,0))) -> Capex additions vs capital goods ITC | E72: =IF(B72="","",INDEX('Rule Matrix'!$D$2:$D$142,MATCH(B72,'Rule Matrix'!$A$2:$A$142,0))) -> s.17(5)(c)(d) | F72: =IF(B72="","",INDEX('Rule Matrix'!$F$2:$F$142,MATCH(B72,'Rule Matrix'!$A$2:$A$142,0))) -> Building/civil CWIP with ITC; P&M classification | G72: =IF(B72="","",INDEX('Rule Matrix'!$G$2:$G$142,MATCH(B72,'Rule Matrix'!$A$2:$A$142,0))) -> Any | H72: =IF(B72="","",INDEX('Rule Matrix'!$H$2:$H$142,MATCH(B72,'Rule Matrix'!$A$2:$A$142,0))) -> High | I72: =IF(B72="","",INDEX('Rule Matrix'!$J$2:$J$142,MATCH(B72,'Rule Matrix'!$A$2:$A$142,0))) -> Reverse | Z72: =Applicability!A66 -> H-01 | AA72: =IF($Z$5=0,0,IF(AND(INDEX(Applicability!$E$66:$O$66,1,$Z$5)="Y",OR(Applicability!$D$66="",IFERROR(INDEX($B$4:$F$4,MATCH(Applicability!$D$66,$B$3:$F$3,0)),"N")="Y")),1,0)) -> 1 | AB72: =IF(AA72=1,SUM(AA$8:AA72),"") -> 57
A73: =IF(66>$B$5,"",66) -> 66 | B73: =IF(A73="","",INDEX($Z$8:$Z$148,MATCH(A73,$AB$8:$AB$148,0))) -> I-02 | C73: =IF(B73="","",INDEX('Rule Matrix'!$B$2:$B$142,MATCH(B73,'Rule Matrix'!$A$2:$A$142,0))) -> I. Annual Report Linkages | D73: =IF(B73="","",INDEX('Rule Matrix'!$C$2:$C$142,MATCH(B73,'Rule Matrix'!$A$2:$A$142,0))) -> Expense heads vs 3CD cl.44 | E73: =IF(B73="","",INDEX('Rule Matrix'!$D$2:$D$142,MATCH(B73,'Rule Matrix'!$A$2:$A$142,0))) -> s.16, s.17 | F73: =IF(B73="","",INDEX('Rule Matrix'!$F$2:$F$142,MATCH(B73,'Rule Matrix'!$A$2:$A$142,0))) -> ITC claimed on expenses shown as unregistered/exempt/composition in cl.44 | G73: =IF(B73="","",INDEX('Rule Matrix'!$G$2:$G$142,MATCH(B73,'Rule Matrix'!$A$2:$A$142,0))) -> Any | H73: =IF(B73="","",INDEX('Rule Matrix'!$H$2:$H$142,MATCH(B73,'Rule Matrix'!$A$2:$A$142,0))) -> High | I73: =IF(B73="","",INDEX('Rule Matrix'!$J$2:$J$142,MATCH(B73,'Rule Matrix'!$A$2:$A$142,0))) -> Reverse | Z73: =Applicability!A67 -> H-02 | AA73: =IF($Z$5=0,0,IF(AND(INDEX(Applicability!$E$67:$O$67,1,$Z$5)="Y",OR(Applicability!$D$67="",IFERROR(INDEX($B$4:$F$4,MATCH(Applicability!$D$67,$B$3:$F$3,0)),"N")="Y")),1,0)) -> 1 | AB73: =IF(AA73=1,SUM(AA$8:AA73),"") -> 58
A74: =IF(67>$B$5,"",67) -> 67 | B74: =IF(A74="","",INDEX($Z$8:$Z$148,MATCH(A74,$AB$8:$AB$148,0))) -> I-03 | C74: =IF(B74="","",INDEX('Rule Matrix'!$B$2:$B$142,MATCH(B74,'Rule Matrix'!$A$2:$A$142,0))) -> I. Annual Report Linkages | D74: =IF(B74="","",INDEX('Rule Matrix'!$C$2:$C$142,MATCH(B74,'Rule Matrix'!$A$2:$A$142,0))) -> Inventory losses & write-offs | E74: =IF(B74="","",INDEX('Rule Matrix'!$D$2:$D$142,MATCH(B74,'Rule Matrix'!$A$2:$A$142,0))) -> s.17(5)(h) | F74: =IF(B74="","",INDEX('Rule Matrix'!$F$2:$F$142,MATCH(B74,'Rule Matrix'!$A$2:$A$142,0))) -> Shortages, obsolescence, destruction written off without ITC reversal | G74: =IF(B74="","",INDEX('Rule Matrix'!$G$2:$G$142,MATCH(B74,'Rule Matrix'!$A$2:$A$142,0))) -> Any | H74: =IF(B74="","",INDEX('Rule Matrix'!$H$2:$H$142,MATCH(B74,'Rule Matrix'!$A$2:$A$142,0))) -> High | I74: =IF(B74="","",INDEX('Rule Matrix'!$J$2:$J$142,MATCH(B74,'Rule Matrix'!$A$2:$A$142,0))) -> Reverse | Z74: =Applicability!A68 -> H-03 | AA74: =IF($Z$5=0,0,IF(AND(INDEX(Applicability!$E$68:$O$68,1,$Z$5)="Y",OR(Applicability!$D$68="",IFERROR(INDEX($B$4:$F$4,MATCH(Applicability!$D$68,$B$3:$F$3,0)),"N")="Y")),1,0)) -> 1 | AB74: =IF(AA74=1,SUM(AA$8:AA74),"") -> 59
A75: =IF(68>$B$5,"",68) -> 68 | B75: =IF(A75="","",INDEX($Z$8:$Z$148,MATCH(A75,$AB$8:$AB$148,0))) -> I-04 | C75: =IF(B75="","",INDEX('Rule Matrix'!$B$2:$B$142,MATCH(B75,'Rule Matrix'!$A$2:$A$142,0))) -> I. Annual Report Linkages | D75: =IF(B75="","",INDEX('Rule Matrix'!$C$2:$C$142,MATCH(B75,'Rule Matrix'!$A$2:$A$142,0))) -> Trade payables > 180 days | E75: =IF(B75="","",INDEX('Rule Matrix'!$D$2:$D$142,MATCH(B75,'Rule Matrix'!$A$2:$A$142,0))) -> Rule 37 | F75: =IF(B75="","",INDEX('Rule Matrix'!$F$2:$F$142,MATCH(B75,'Rule Matrix'!$A$2:$A$142,0))) -> Cross-check with ITC reversal | G75: =IF(B75="","",INDEX('Rule Matrix'!$G$2:$G$142,MATCH(B75,'Rule Matrix'!$A$2:$A$142,0))) -> Any gap | H75: =IF(B75="","",INDEX('Rule Matrix'!$H$2:$H$142,MATCH(B75,'Rule Matrix'!$A$2:$A$142,0))) -> High | I75: =IF(B75="","",INDEX('Rule Matrix'!$J$2:$J$142,MATCH(B75,'Rule Matrix'!$A$2:$A$142,0))) -> Reverse | Z75: =Applicability!A69 -> H-04 | AA75: =IF($Z$5=0,0,IF(AND(INDEX(Applicability!$E$69:$O$69,1,$Z$5)="Y",OR(Applicability!$D$69="",IFERROR(INDEX($B$4:$F$4,MATCH(Applicability!$D$69,$B$3:$F$3,0)),"N")="Y")),1,0)) -> 1 | AB75: =IF(AA75=1,SUM(AA$8:AA75),"") -> 60
A76: =IF(69>$B$5,"",69) -> 69 | B76: =IF(A76="","",INDEX($Z$8:$Z$148,MATCH(A76,$AB$8:$AB$148,0))) -> I-05 | C76: =IF(B76="","",INDEX('Rule Matrix'!$B$2:$B$142,MATCH(B76,'Rule Matrix'!$A$2:$A$142,0))) -> I. Annual Report Linkages | D76: =IF(B76="","",INDEX('Rule Matrix'!$C$2:$C$142,MATCH(B76,'Rule Matrix'!$A$2:$A$142,0))) -> Year-end accruals | E76: =IF(B76="","",INDEX('Rule Matrix'!$D$2:$D$142,MATCH(B76,'Rule Matrix'!$A$2:$A$142,0))) -> s.16(2)(a) | F76: =IF(B76="","",INDEX('Rule Matrix'!$F$2:$F$142,MATCH(B76,'Rule Matrix'!$A$2:$A$142,0))) -> ITC claimed on provisions without invoice | G76: =IF(B76="","",INDEX('Rule Matrix'!$G$2:$G$142,MATCH(B76,'Rule Matrix'!$A$2:$A$142,0))) -> Any | H76: =IF(B76="","",INDEX('Rule Matrix'!$H$2:$H$142,MATCH(B76,'Rule Matrix'!$A$2:$A$142,0))) -> Med | I76: =IF(B76="","",INDEX('Rule Matrix'!$J$2:$J$142,MATCH(B76,'Rule Matrix'!$A$2:$A$142,0))) -> Reverse | Z76: =Applicability!A70 -> H-05 | AA76: =IF($Z$5=0,0,IF(AND(INDEX(Applicability!$E$70:$O$70,1,$Z$5)="Y",OR(Applicability!$D$70="",IFERROR(INDEX($B$4:$F$4,MATCH(Applicability!$D$70,$B$3:$F$3,0)),"N")="Y")),1,0)) -> 1 | AB76: =IF(AA76=1,SUM(AA$8:AA76),"") -> 61
A77: =IF(70>$B$5,"",70) -> 70 | B77: =IF(A77="","",INDEX($Z$8:$Z$148,MATCH(A77,$AB$8:$AB$148,0))) -> I-06 | C77: =IF(B77="","",INDEX('Rule Matrix'!$B$2:$B$142,MATCH(B77,'Rule Matrix'!$A$2:$A$142,0))) -> I. Annual Report Linkages | D77: =IF(B77="","",INDEX('Rule Matrix'!$C$2:$C$142,MATCH(B77,'Rule Matrix'!$A$2:$A$142,0))) -> Bad debts written off | E77: =IF(B77="","",INDEX('Rule Matrix'!$D$2:$D$142,MATCH(B77,'Rule Matrix'!$A$2:$A$142,0))) -> s.34 | F77: =IF(B77="","",INDEX('Rule Matrix'!$F$2:$F$142,MATCH(B77,'Rule Matrix'!$A$2:$A$142,0))) -> Output tax reduced without valid CN | G77: =IF(B77="","",INDEX('Rule Matrix'!$G$2:$G$142,MATCH(B77,'Rule Matrix'!$A$2:$A$142,0))) -> Any | H77: =IF(B77="","",INDEX('Rule Matrix'!$H$2:$H$142,MATCH(B77,'Rule Matrix'!$A$2:$A$142,0))) -> Med | I77: =IF(B77="","",INDEX('Rule Matrix'!$J$2:$J$142,MATCH(B77,'Rule Matrix'!$A$2:$A$142,0))) -> Reverse | Z77: =Applicability!A71 -> H-06 | AA77: =IF($Z$5=0,0,IF(AND(INDEX(Applicability!$E$71:$O$71,1,$Z$5)="Y",OR(Applicability!$D$71="",IFERROR(INDEX($B$4:$F$4,MATCH(Applicability!$D$71,$B$3:$F$3,0)),"N")="Y")),1,0)) -> 1 | AB77: =IF(AA77=1,SUM(AA$8:AA77),"") -> 62
A78: =IF(71>$B$5,"",71) -> 71 | B78: =IF(A78="","",INDEX($Z$8:$Z$148,MATCH(A78,$AB$8:$AB$148,0))) -> I-07 | C78: =IF(B78="","",INDEX('Rule Matrix'!$B$2:$B$142,MATCH(B78,'Rule Matrix'!$A$2:$A$142,0))) -> I. Annual Report Linkages | D78: =IF(B78="","",INDEX('Rule Matrix'!$C$2:$C$142,MATCH(B78,'Rule Matrix'!$A$2:$A$142,0))) -> Contingent liabilities & CARO (vii) | E78: =IF(B78="","",INDEX('Rule Matrix'!$D$2:$D$142,MATCH(B78,'Rule Matrix'!$A$2:$A$142,0))) -> — | F78: =IF(B78="","",INDEX('Rule Matrix'!$F$2:$F$142,MATCH(B78,'Rule Matrix'!$A$2:$A$142,0))) -> Disputed/undisputed GST dues, pending notices captured | G78: =IF(B78="","",INDEX('Rule Matrix'!$G$2:$G$142,MATCH(B78,'Rule Matrix'!$A$2:$A$142,0))) -> Any | H78: =IF(B78="","",INDEX('Rule Matrix'!$H$2:$H$142,MATCH(B78,'Rule Matrix'!$A$2:$A$142,0))) -> Med | I78: =IF(B78="","",INDEX('Rule Matrix'!$J$2:$J$142,MATCH(B78,'Rule Matrix'!$A$2:$A$142,0))) -> Track / provide | Z78: =Applicability!A72 -> H-07 | AA78: =IF($Z$5=0,0,IF(AND(INDEX(Applicability!$E$72:$O$72,1,$Z$5)="Y",OR(Applicability!$D$72="",IFERROR(INDEX($B$4:$F$4,MATCH(Applicability!$D$72,$B$3:$F$3,0)),"N")="Y")),1,0)) -> 1 | AB78: =IF(AA78=1,SUM(AA$8:AA78),"") -> 63
A79: =IF(72>$B$5,"",72) -> 72 | B79: =IF(A79="","",INDEX($Z$8:$Z$148,MATCH(A79,$AB$8:$AB$148,0))) -> I-08 | C79: =IF(B79="","",INDEX('Rule Matrix'!$B$2:$B$142,MATCH(B79,'Rule Matrix'!$A$2:$A$142,0))) -> I. Annual Report Linkages | D79: =IF(B79="","",INDEX('Rule Matrix'!$C$2:$C$142,MATCH(B79,'Rule Matrix'!$A$2:$A$142,0))) -> Deferred revenue / unbilled revenue | E79: =IF(B79="","",INDEX('Rule Matrix'!$D$2:$D$142,MATCH(B79,'Rule Matrix'!$A$2:$A$142,0))) -> s.12, s.13, s.31 | F79: =IF(B79="","",INDEX('Rule Matrix'!$F$2:$F$142,MATCH(B79,'Rule Matrix'!$A$2:$A$142,0))) -> Time of supply triggered on milestones/due date vs invoicing | G79: =IF(B79="","",INDEX('Rule Matrix'!$G$2:$G$142,MATCH(B79,'Rule Matrix'!$A$2:$A$142,0))) -> Any | H79: =IF(B79="","",INDEX('Rule Matrix'!$H$2:$H$142,MATCH(B79,'Rule Matrix'!$A$2:$A$142,0))) -> Med | I79: =IF(B79="","",INDEX('Rule Matrix'!$J$2:$J$142,MATCH(B79,'Rule Matrix'!$A$2:$A$142,0))) -> Pay | Z79: =Applicability!A73 -> H-08 | AA79: =IF($Z$5=0,0,IF(AND(INDEX(Applicability!$E$73:$O$73,1,$Z$5)="Y",OR(Applicability!$D$73="",IFERROR(INDEX($B$4:$F$4,MATCH(Applicability!$D$73,$B$3:$F$3,0)),"N")="Y")),1,0)) -> 1 | AB79: =IF(AA79=1,SUM(AA$8:AA79),"") -> 64
A80: =IF(73>$B$5,"",73) -> 73 | B80: =IF(A80="","",INDEX($Z$8:$Z$148,MATCH(A80,$AB$8:$AB$148,0))) -> J-01 | C80: =IF(B80="","",INDEX('Rule Matrix'!$B$2:$B$142,MATCH(B80,'Rule Matrix'!$A$2:$A$142,0))) -> J. Interest, Fees, Payments | D80: =IF(B80="","",INDEX('Rule Matrix'!$C$2:$C$142,MATCH(B80,'Rule Matrix'!$A$2:$A$142,0))) -> Interest on delayed payment | E80: =IF(B80="","",INDEX('Rule Matrix'!$D$2:$D$142,MATCH(B80,'Rule Matrix'!$A$2:$A$142,0))) -> s.50(1), proviso | F80: =IF(B80="","",INDEX('Rule Matrix'!$F$2:$F$142,MATCH(B80,'Rule Matrix'!$A$2:$A$142,0))) -> 18% on net cash liability paid late | G80: =IF(B80="","",INDEX('Rule Matrix'!$G$2:$G$142,MATCH(B80,'Rule Matrix'!$A$2:$A$142,0))) -> Any | H80: =IF(B80="","",INDEX('Rule Matrix'!$H$2:$H$142,MATCH(B80,'Rule Matrix'!$A$2:$A$142,0))) -> Med | I80: =IF(B80="","",INDEX('Rule Matrix'!$J$2:$J$142,MATCH(B80,'Rule Matrix'!$A$2:$A$142,0))) -> Pay via DRC-03 | Z80: =Applicability!A74 -> I-01 | AA80: =IF($Z$5=0,0,IF(AND(INDEX(Applicability!$E$74:$O$74,1,$Z$5)="Y",OR(Applicability!$D$74="",IFERROR(INDEX($B$4:$F$4,MATCH(Applicability!$D$74,$B$3:$F$3,0)),"N")="Y")),1,0)) -> 1 | AB80: =IF(AA80=1,SUM(AA$8:AA80),"") -> 65
A81: =IF(74>$B$5,"",74) -> 74 | B81: =IF(A81="","",INDEX($Z$8:$Z$148,MATCH(A81,$AB$8:$AB$148,0))) -> J-02 | C81: =IF(B81="","",INDEX('Rule Matrix'!$B$2:$B$142,MATCH(B81,'Rule Matrix'!$A$2:$A$142,0))) -> J. Interest, Fees, Payments | D81: =IF(B81="","",INDEX('Rule Matrix'!$C$2:$C$142,MATCH(B81,'Rule Matrix'!$A$2:$A$142,0))) -> Interest on wrong ITC availed & utilised | E81: =IF(B81="","",INDEX('Rule Matrix'!$D$2:$D$142,MATCH(B81,'Rule Matrix'!$A$2:$A$142,0))) -> s.50(3), Rule 88B | F81: =IF(B81="","",INDEX('Rule Matrix'!$F$2:$F$142,MATCH(B81,'Rule Matrix'!$A$2:$A$142,0))) -> 18% only when ITC utilised (ledger balance below wrong ITC) | G81: =IF(B81="","",INDEX('Rule Matrix'!$G$2:$G$142,MATCH(B81,'Rule Matrix'!$A$2:$A$142,0))) -> Any | H81: =IF(B81="","",INDEX('Rule Matrix'!$H$2:$H$142,MATCH(B81,'Rule Matrix'!$A$2:$A$142,0))) -> High | I81: =IF(B81="","",INDEX('Rule Matrix'!$J$2:$J$142,MATCH(B81,'Rule Matrix'!$A$2:$A$142,0))) -> Pay | Z81: =Applicability!A75 -> I-02 | AA81: =IF($Z$5=0,0,IF(AND(INDEX(Applicability!$E$75:$O$75,1,$Z$5)="Y",OR(Applicability!$D$75="",IFERROR(INDEX($B$4:$F$4,MATCH(Applicability!$D$75,$B$3:$F$3,0)),"N")="Y")),1,0)) -> 1 | AB81: =IF(AA81=1,SUM(AA$8:AA81),"") -> 66
A82: =IF(75>$B$5,"",75) -> 75 | B82: =IF(A82="","",INDEX($Z$8:$Z$148,MATCH(A82,$AB$8:$AB$148,0))) -> J-03 | C82: =IF(B82="","",INDEX('Rule Matrix'!$B$2:$B$142,MATCH(B82,'Rule Matrix'!$A$2:$A$142,0))) -> J. Interest, Fees, Payments | D82: =IF(B82="","",INDEX('Rule Matrix'!$C$2:$C$142,MATCH(B82,'Rule Matrix'!$A$2:$A$142,0))) -> Late fees | E82: =IF(B82="","",INDEX('Rule Matrix'!$D$2:$D$142,MATCH(B82,'Rule Matrix'!$A$2:$A$142,0))) -> s.47 | F82: =IF(B82="","",INDEX('Rule Matrix'!$F$2:$F$142,MATCH(B82,'Rule Matrix'!$A$2:$A$142,0))) -> GSTR-1/3B/9 late fee computation | G82: =IF(B82="","",INDEX('Rule Matrix'!$G$2:$G$142,MATCH(B82,'Rule Matrix'!$A$2:$A$142,0))) -> Any | H82: =IF(B82="","",INDEX('Rule Matrix'!$H$2:$H$142,MATCH(B82,'Rule Matrix'!$A$2:$A$142,0))) -> Low | I82: =IF(B82="","",INDEX('Rule Matrix'!$J$2:$J$142,MATCH(B82,'Rule Matrix'!$A$2:$A$142,0))) -> Pay | Z82: =Applicability!A76 -> I-03 | AA82: =IF($Z$5=0,0,IF(AND(INDEX(Applicability!$E$76:$O$76,1,$Z$5)="Y",OR(Applicability!$D$76="",IFERROR(INDEX($B$4:$F$4,MATCH(Applicability!$D$76,$B$3:$F$3,0)),"N")="Y")),1,0)) -> 1 | AB82: =IF(AA82=1,SUM(AA$8:AA82),"") -> 67
A83: =IF(76>$B$5,"",76) -> 76 | B83: =IF(A83="","",INDEX($Z$8:$Z$148,MATCH(A83,$AB$8:$AB$148,0))) -> J-04 | C83: =IF(B83="","",INDEX('Rule Matrix'!$B$2:$B$142,MATCH(B83,'Rule Matrix'!$A$2:$A$142,0))) -> J. Interest, Fees, Payments | D83: =IF(B83="","",INDEX('Rule Matrix'!$C$2:$C$142,MATCH(B83,'Rule Matrix'!$A$2:$A$142,0))) -> DRC-03 mapping | E83: =IF(B83="","",INDEX('Rule Matrix'!$D$2:$D$142,MATCH(B83,'Rule Matrix'!$A$2:$A$142,0))) -> Rule 142(2) | F83: =IF(B83="","",INDEX('Rule Matrix'!$F$2:$F$142,MATCH(B83,'Rule Matrix'!$A$2:$A$142,0))) -> Each voluntary payment mapped to issue & period; ledger debit correct | G83: =IF(B83="","",INDEX('Rule Matrix'!$G$2:$G$142,MATCH(B83,'Rule Matrix'!$A$2:$A$142,0))) -> Unmapped | H83: =IF(B83="","",INDEX('Rule Matrix'!$H$2:$H$142,MATCH(B83,'Rule Matrix'!$A$2:$A$142,0))) -> Low | I83: =IF(B83="","",INDEX('Rule Matrix'!$J$2:$J$142,MATCH(B83,'Rule Matrix'!$A$2:$A$142,0))) -> Map / DRC-03A | Z83: =Applicability!A77 -> I-04 | AA83: =IF($Z$5=0,0,IF(AND(INDEX(Applicability!$E$77:$O$77,1,$Z$5)="Y",OR(Applicability!$D$77="",IFERROR(INDEX($B$4:$F$4,MATCH(Applicability!$D$77,$B$3:$F$3,0)),"N")="Y")),1,0)) -> 1 | AB83: =IF(AA83=1,SUM(AA$8:AA83),"") -> 68
A84: =IF(77>$B$5,"",77) -> 77 | B84: =IF(A84="","",INDEX($Z$8:$Z$148,MATCH(A84,$AB$8:$AB$148,0))) -> K-01 | C84: =IF(B84="","",INDEX('Rule Matrix'!$B$2:$B$142,MATCH(B84,'Rule Matrix'!$A$2:$A$142,0))) -> K. Sec 73 / 74 / 74A Applicability | D84: =IF(B84="","",INDEX('Rule Matrix'!$C$2:$C$142,MATCH(B84,'Rule Matrix'!$A$2:$A$142,0))) -> Proceeding section by FY | E84: =IF(B84="","",INDEX('Rule Matrix'!$D$2:$D$142,MATCH(B84,'Rule Matrix'!$A$2:$A$142,0))) -> s.73, 74 (up to FY 2023-24); s.74A (FY 2024-25 onwards) – F(No.2)A 2024 | F84: =IF(B84="","",INDEX('Rule Matrix'!$F$2:$F$142,MATCH(B84,'Rule Matrix'!$A$2:$A$142,0))) -> FY ≤ 2023-24 → s.73 (non-fraud) / s.74 (fraud); FY ≥ 2024-25 → s.74A | G84: =IF(B84="","",INDEX('Rule Matrix'!$G$2:$G$142,MATCH(B84,'Rule Matrix'!$A$2:$A$142,0))) -> Every flagged issue | H84: =IF(B84="","",INDEX('Rule Matrix'!$H$2:$H$142,MATCH(B84,'Rule Matrix'!$A$2:$A$142,0))) -> High | I84: =IF(B84="","",INDEX('Rule Matrix'!$J$2:$J$142,MATCH(B84,'Rule Matrix'!$A$2:$A$142,0))) -> Tag each Fail row via 'Sec 73-74 Classifier' sheet | Z84: =Applicability!A78 -> I-05 | AA84: =IF($Z$5=0,0,IF(AND(INDEX(Applicability!$E$78:$O$78,1,$Z$5)="Y",OR(Applicability!$D$78="",IFERROR(INDEX($B$4:$F$4,MATCH(Applicability!$D$78,$B$3:$F$3,0)),"N")="Y")),1,0)) -> 1 | AB84: =IF(AA84=1,SUM(AA$8:AA84),"") -> 69
A85: =IF(78>$B$5,"",78) -> 78 | B85: =IF(A85="","",INDEX($Z$8:$Z$148,MATCH(A85,$AB$8:$AB$148,0))) -> K-02 | C85: =IF(B85="","",INDEX('Rule Matrix'!$B$2:$B$142,MATCH(B85,'Rule Matrix'!$A$2:$A$142,0))) -> K. Sec 73 / 74 / 74A Applicability | D85: =IF(B85="","",INDEX('Rule Matrix'!$C$2:$C$142,MATCH(B85,'Rule Matrix'!$A$2:$A$142,0))) -> Fraud / suppression indicators | E85: =IF(B85="","",INDEX('Rule Matrix'!$D$2:$D$142,MATCH(B85,'Rule Matrix'!$A$2:$A$142,0))) -> s.74 Expl. 2; s.74A; Uniworth Textiles (2013) 9 SCC 753; Pushpam Pharmaceuticals 1995 Supp (3) SCC 462; Continental Foundation JV (2007) 10 SCC 337 | F85: =IF(B85="","",INDEX('Rule Matrix'!$F$2:$F$142,MATCH(B85,'Rule Matrix'!$A$2:$A$142,0))) -> Fake invoices / ITC without supply, non-existent vendor, circular trading, non-declaration in returns, not furnishing info on request, wilful misstatement. Defence: mere non-payment, bona fide interpretational dispute or data mismatch ≠ suppression; SCN must specifically allege and evidence intent | G85: =IF(B85="","",INDEX('Rule Matrix'!$G$2:$G$142,MATCH(B85,'Rule Matrix'!$A$2:$A$142,0))) -> Any Y | H85: =IF(B85="","",INDEX('Rule Matrix'!$H$2:$H$142,MATCH(B85,'Rule Matrix'!$A$2:$A$142,0))) -> High | I85: =IF(B85="","",INDEX('Rule Matrix'!$J$2:$J$142,MATCH(B85,'Rule Matrix'!$A$2:$A$142,0))) -> Classify as fraud limb; build defence file | Z85: =Applicability!A79 -> I-06 | AA85: =IF($Z$5=0,0,IF(AND(INDEX(Applicability!$E$79:$O$79,1,$Z$5)="Y",OR(Applicability!$D$79="",IFERROR(INDEX($B$4:$F$4,MATCH(Applicability!$D$79,$B$3:$F$3,0)),"N")="Y")),1,0)) -> 1 | AB85: =IF(AA85=1,SUM(AA$8:AA85),"") -> 70
A86: =IF(79>$B$5,"",79) -> 79 | B86: =IF(A86="","",INDEX($Z$8:$Z$148,MATCH(A86,$AB$8:$AB$148,0))) -> K-03 | C86: =IF(B86="","",INDEX('Rule Matrix'!$B$2:$B$142,MATCH(B86,'Rule Matrix'!$A$2:$A$142,0))) -> K. Sec 73 / 74 / 74A Applicability | D86: =IF(B86="","",INDEX('Rule Matrix'!$C$2:$C$142,MATCH(B86,'Rule Matrix'!$A$2:$A$142,0))) -> Limitation – SCN & order | E86: =IF(B86="","",INDEX('Rule Matrix'!$D$2:$D$142,MATCH(B86,'Rule Matrix'!$A$2:$A$142,0))) -> s.73(2)(10), 74(2)(10), 74A(2)(10) | F86: =IF(B86="","",INDEX('Rule Matrix'!$F$2:$F$142,MATCH(B86,'Rule Matrix'!$A$2:$A$142,0))) -> 73: order 3 yrs, SCN 3 months earlier; 74: order 5 yrs, SCN 6 months earlier; 74A: SCN 42 months, order 12 months from SCN (+6 extendable) | G86: =IF(B86="","",INDEX('Rule Matrix'!$G$2:$G$142,MATCH(B86,'Rule Matrix'!$A$2:$A$142,0))) -> SCN after deadline | H86: =IF(B86="","",INDEX('Rule Matrix'!$H$2:$H$142,MATCH(B86,'Rule Matrix'!$A$2:$A$142,0))) -> High | I86: =IF(B86="","",INDEX('Rule Matrix'!$J$2:$J$142,MATCH(B86,'Rule Matrix'!$A$2:$A$142,0))) -> Plead limitation | Z86: =Applicability!A80 -> I-07 | AA86: =IF($Z$5=0,0,IF(AND(INDEX(Applicability!$E$80:$O$80,1,$Z$5)="Y",OR(Applicability!$D$80="",IFERROR(INDEX($B$4:$F$4,MATCH(Applicability!$D$80,$B$3:$F$3,0)),"N")="Y")),1,0)) -> 1 | AB86: =IF(AA86=1,SUM(AA$8:AA86),"") -> 71
A87: =IF(80>$B$5,"",80) -> 80 | B87: =IF(A87="","",INDEX($Z$8:$Z$148,MATCH(A87,$AB$8:$AB$148,0))) -> K-04 | C87: =IF(B87="","",INDEX('Rule Matrix'!$B$2:$B$142,MATCH(B87,'Rule Matrix'!$A$2:$A$142,0))) -> K. Sec 73 / 74 / 74A Applicability | D87: =IF(B87="","",INDEX('Rule Matrix'!$C$2:$C$142,MATCH(B87,'Rule Matrix'!$A$2:$A$142,0))) -> s.74A de minimis | E87: =IF(B87="","",INDEX('Rule Matrix'!$D$2:$D$142,MATCH(B87,'Rule Matrix'!$A$2:$A$142,0))) -> s.74A(1) proviso | F87: =IF(B87="","",INDEX('Rule Matrix'!$F$2:$F$142,MATCH(B87,'Rule Matrix'!$A$2:$A$142,0))) -> No SCN under s.74A where tax involved in a FY < ₹1,000 | G87: =IF(B87="","",INDEX('Rule Matrix'!$G$2:$G$142,MATCH(B87,'Rule Matrix'!$A$2:$A$142,0))) -> < ₹1,000 | H87: =IF(B87="","",INDEX('Rule Matrix'!$H$2:$H$142,MATCH(B87,'Rule Matrix'!$A$2:$A$142,0))) -> Low | I87: =IF(B87="","",INDEX('Rule Matrix'!$J$2:$J$142,MATCH(B87,'Rule Matrix'!$A$2:$A$142,0))) -> Object to SCN | Z87: =Applicability!A81 -> I-08 | AA87: =IF($Z$5=0,0,IF(AND(INDEX(Applicability!$E$81:$O$81,1,$Z$5)="Y",OR(Applicability!$D$81="",IFERROR(INDEX($B$4:$F$4,MATCH(Applicability!$D$81,$B$3:$F$3,0)),"N")="Y")),1,0)) -> 1 | AB87: =IF(AA87=1,SUM(AA$8:AA87),"") -> 72
A88: =IF(81>$B$5,"",81) -> 81 | B88: =IF(A88="","",INDEX($Z$8:$Z$148,MATCH(A88,$AB$8:$AB$148,0))) -> K-05 | C88: =IF(B88="","",INDEX('Rule Matrix'!$B$2:$B$142,MATCH(B88,'Rule Matrix'!$A$2:$A$142,0))) -> K. Sec 73 / 74 / 74A Applicability | D88: =IF(B88="","",INDEX('Rule Matrix'!$C$2:$C$142,MATCH(B88,'Rule Matrix'!$A$2:$A$142,0))) -> COVID extension (s.73 only) | E88: =IF(B88="","",INDEX('Rule Matrix'!$D$2:$D$142,MATCH(B88,'Rule Matrix'!$A$2:$A$142,0))) -> Notfn 13/2022, 9/2023, 56/2023 (s.168A); Tata Play (Mad HC, 12.06.2025) struck down; Brunda Infra (Telangana HC) upheld; SC SLP HCC-SEW-MEIL-AAG JV | F88: =IF(B88="","",INDEX('Rule Matrix'!$F$2:$F$142,MATCH(B88,'Rule Matrix'!$A$2:$A$142,0))) -> Order deadlines: FY17-18 31.12.2023; FY18-19 30.04.2024; FY19-20 31.08.2024. Validity sub judice before SC – plead limitation where orders rely on these extensions | G88: =IF(B88="","",INDEX('Rule Matrix'!$G$2:$G$142,MATCH(B88,'Rule Matrix'!$A$2:$A$142,0))) -> Order after date | H88: =IF(B88="","",INDEX('Rule Matrix'!$H$2:$H$142,MATCH(B88,'Rule Matrix'!$A$2:$A$142,0))) -> Med | I88: =IF(B88="","",INDEX('Rule Matrix'!$J$2:$J$142,MATCH(B88,'Rule Matrix'!$A$2:$A$142,0))) -> Plead limitation | Z88: =Applicability!A82 -> J-01 | AA88: =IF($Z$5=0,0,IF(AND(INDEX(Applicability!$E$82:$O$82,1,$Z$5)="Y",OR(Applicability!$D$82="",IFERROR(INDEX($B$4:$F$4,MATCH(Applicability!$D$82,$B$3:$F$3,0)),"N")="Y")),1,0)) -> 1 | AB88: =IF(AA88=1,SUM(AA$8:AA88),"") -> 73
A89: =IF(82>$B$5,"",82) -> 82 | B89: =IF(A89="","",INDEX($Z$8:$Z$148,MATCH(A89,$AB$8:$AB$148,0))) -> K-06 | C89: =IF(B89="","",INDEX('Rule Matrix'!$B$2:$B$142,MATCH(B89,'Rule Matrix'!$A$2:$A$142,0))) -> K. Sec 73 / 74 / 74A Applicability | D89: =IF(B89="","",INDEX('Rule Matrix'!$C$2:$C$142,MATCH(B89,'Rule Matrix'!$A$2:$A$142,0))) -> Pre-SCN voluntary payment | E89: =IF(B89="","",INDEX('Rule Matrix'!$D$2:$D$142,MATCH(B89,'Rule Matrix'!$A$2:$A$142,0))) -> s.73(5)(6), 74(5)(6), 74A(5)(8) | F89: =IF(B89="","",INDEX('Rule Matrix'!$F$2:$F$142,MATCH(B89,'Rule Matrix'!$A$2:$A$142,0))) -> Tax + interest paid before SCN: no SCN; penalty nil (non-fraud) / 15% (fraud) | G89: =IF(B89="","",INDEX('Rule Matrix'!$G$2:$G$142,MATCH(B89,'Rule Matrix'!$A$2:$A$142,0))) -> — | H89: =IF(B89="","",INDEX('Rule Matrix'!$H$2:$H$142,MATCH(B89,'Rule Matrix'!$A$2:$A$142,0))) -> Med | I89: =IF(B89="","",INDEX('Rule Matrix'!$J$2:$J$142,MATCH(B89,'Rule Matrix'!$A$2:$A$142,0))) -> Pay via DRC-03 with interest, intimate | Z89: =Applicability!A83 -> J-02 | AA89: =IF($Z$5=0,0,IF(AND(INDEX(Applicability!$E$83:$O$83,1,$Z$5)="Y",OR(Applicability!$D$83="",IFERROR(INDEX($B$4:$F$4,MATCH(Applicability!$D$83,$B$3:$F$3,0)),"N")="Y")),1,0)) -> 1 | AB89: =IF(AA89=1,SUM(AA$8:AA89),"") -> 74
A90: =IF(83>$B$5,"",83) -> 83 | B90: =IF(A90="","",INDEX($Z$8:$Z$148,MATCH(A90,$AB$8:$AB$148,0))) -> K-07 | C90: =IF(B90="","",INDEX('Rule Matrix'!$B$2:$B$142,MATCH(B90,'Rule Matrix'!$A$2:$A$142,0))) -> K. Sec 73 / 74 / 74A Applicability | D90: =IF(B90="","",INDEX('Rule Matrix'!$C$2:$C$142,MATCH(B90,'Rule Matrix'!$A$2:$A$142,0))) -> Penalty exposure by payment stage | E90: =IF(B90="","",INDEX('Rule Matrix'!$D$2:$D$142,MATCH(B90,'Rule Matrix'!$A$2:$A$142,0))) -> s.73(8)(9)(11), 74(8)(9)(10)(11), 74A(5)(8)(9) | F90: =IF(B90="","",INDEX('Rule Matrix'!$F$2:$F$142,MATCH(B90,'Rule Matrix'!$A$2:$A$142,0))) -> Non-fraud: nil if paid within 30 days of SCN (60 for 74A), else 10% or ₹10,000 higher. Fraud: 15% pre-SCN / 25% within 30 (60) days of SCN / 50% within 30 (60) days of order / 100% | G90: =IF(B90="","",INDEX('Rule Matrix'!$G$2:$G$142,MATCH(B90,'Rule Matrix'!$A$2:$A$142,0))) -> — | H90: =IF(B90="","",INDEX('Rule Matrix'!$H$2:$H$142,MATCH(B90,'Rule Matrix'!$A$2:$A$142,0))) -> High | I90: =IF(B90="","",INDEX('Rule Matrix'!$J$2:$J$142,MATCH(B90,'Rule Matrix'!$A$2:$A$142,0))) -> Choose payment timing | Z90: =Applicability!A84 -> J-03 | AA90: =IF($Z$5=0,0,IF(AND(INDEX(Applicability!$E$84:$O$84,1,$Z$5)="Y",OR(Applicability!$D$84="",IFERROR(INDEX($B$4:$F$4,MATCH(Applicability!$D$84,$B$3:$F$3,0)),"N")="Y")),1,0)) -> 1 | AB90: =IF(AA90=1,SUM(AA$8:AA90),"") -> 75
A91: =IF(84>$B$5,"",84) -> 84 | B91: =IF(A91="","",INDEX($Z$8:$Z$148,MATCH(A91,$AB$8:$AB$148,0))) -> K-08 | C91: =IF(B91="","",INDEX('Rule Matrix'!$B$2:$B$142,MATCH(B91,'Rule Matrix'!$A$2:$A$142,0))) -> K. Sec 73 / 74 / 74A Applicability | D91: =IF(B91="","",INDEX('Rule Matrix'!$C$2:$C$142,MATCH(B91,'Rule Matrix'!$A$2:$A$142,0))) -> s.128A waiver eligibility | E91: =IF(B91="","",INDEX('Rule Matrix'!$D$2:$D$142,MATCH(B91,'Rule Matrix'!$A$2:$A$142,0))) -> s.128A, Rule 164 | F91: =IF(B91="","",INDEX('Rule Matrix'!$F$2:$F$142,MATCH(B91,'Rule Matrix'!$A$2:$A$142,0))) -> Interest & penalty waived if full tax paid by 31.03.2025; not for erroneous refunds | G91: =IF(B91="","",INDEX('Rule Matrix'!$G$2:$G$142,MATCH(B91,'Rule Matrix'!$A$2:$A$142,0))) -> Eligible cases | H91: =IF(B91="","",INDEX('Rule Matrix'!$H$2:$H$142,MATCH(B91,'Rule Matrix'!$A$2:$A$142,0))) -> Med | I91: =IF(B91="","",INDEX('Rule Matrix'!$J$2:$J$142,MATCH(B91,'Rule Matrix'!$A$2:$A$142,0))) -> Check application (SPL-01/02) status | Z91: =Applicability!A85 -> J-04 | AA91: =IF($Z$5=0,0,IF(AND(INDEX(Applicability!$E$85:$O$85,1,$Z$5)="Y",OR(Applicability!$D$85="",IFERROR(INDEX($B$4:$F$4,MATCH(Applicability!$D$85,$B$3:$F$3,0)),"N")="Y")),1,0)) -> 1 | AB91: =IF(AA91=1,SUM(AA$8:AA91),"") -> 76
A92: =IF(85>$B$5,"",85) -> 85 | B92: =IF(A92="","",INDEX($Z$8:$Z$148,MATCH(A92,$AB$8:$AB$148,0))) -> K-09 | C92: =IF(B92="","",INDEX('Rule Matrix'!$B$2:$B$142,MATCH(B92,'Rule Matrix'!$A$2:$A$142,0))) -> K. Sec 73 / 74 / 74A Applicability | D92: =IF(B92="","",INDEX('Rule Matrix'!$C$2:$C$142,MATCH(B92,'Rule Matrix'!$A$2:$A$142,0))) -> Fraud not established | E92: =IF(B92="","",INDEX('Rule Matrix'!$D$2:$D$142,MATCH(B92,'Rule Matrix'!$A$2:$A$142,0))) -> s.75(2) | F92: =IF(B92="","",INDEX('Rule Matrix'!$F$2:$F$142,MATCH(B92,'Rule Matrix'!$A$2:$A$142,0))) -> If fraud limb fails before appellate authority, re-determine as non-fraud within non-fraud limitation | G92: =IF(B92="","",INDEX('Rule Matrix'!$G$2:$G$142,MATCH(B92,'Rule Matrix'!$A$2:$A$142,0))) -> — | H92: =IF(B92="","",INDEX('Rule Matrix'!$H$2:$H$142,MATCH(B92,'Rule Matrix'!$A$2:$A$142,0))) -> Med | I92: =IF(B92="","",INDEX('Rule Matrix'!$J$2:$J$142,MATCH(B92,'Rule Matrix'!$A$2:$A$142,0))) -> Plead s.75(2) | Z92: =Applicability!A86 -> K-01 | AA92: =IF($Z$5=0,0,IF(AND(INDEX(Applicability!$E$86:$O$86,1,$Z$5)="Y",OR(Applicability!$D$86="",IFERROR(INDEX($B$4:$F$4,MATCH(Applicability!$D$86,$B$3:$F$3,0)),"N")="Y")),1,0)) -> 1 | AB92: =IF(AA92=1,SUM(AA$8:AA92),"") -> 77
A93: =IF(86>$B$5,"",86) -> 86 | B93: =IF(A93="","",INDEX($Z$8:$Z$148,MATCH(A93,$AB$8:$AB$148,0))) -> K-10 | C93: =IF(B93="","",INDEX('Rule Matrix'!$B$2:$B$142,MATCH(B93,'Rule Matrix'!$A$2:$A$142,0))) -> K. Sec 73 / 74 / 74A Applicability | D93: =IF(B93="","",INDEX('Rule Matrix'!$C$2:$C$142,MATCH(B93,'Rule Matrix'!$A$2:$A$142,0))) -> Erroneous refunds | E93: =IF(B93="","",INDEX('Rule Matrix'!$D$2:$D$142,MATCH(B93,'Rule Matrix'!$A$2:$A$142,0))) -> s.73(10), 74(10), 74A(2) | F93: =IF(B93="","",INDEX('Rule Matrix'!$F$2:$F$142,MATCH(B93,'Rule Matrix'!$A$2:$A$142,0))) -> Limitation from date of refund order, not annual return | G93: =IF(B93="","",INDEX('Rule Matrix'!$G$2:$G$142,MATCH(B93,'Rule Matrix'!$A$2:$A$142,0))) -> — | H93: =IF(B93="","",INDEX('Rule Matrix'!$H$2:$H$142,MATCH(B93,'Rule Matrix'!$A$2:$A$142,0))) -> Med | I93: =IF(B93="","",INDEX('Rule Matrix'!$J$2:$J$142,MATCH(B93,'Rule Matrix'!$A$2:$A$142,0))) -> Compute separately | Z93: =Applicability!A87 -> K-02 | AA93: =IF($Z$5=0,0,IF(AND(INDEX(Applicability!$E$87:$O$87,1,$Z$5)="Y",OR(Applicability!$D$87="",IFERROR(INDEX($B$4:$F$4,MATCH(Applicability!$D$87,$B$3:$F$3,0)),"N")="Y")),1,0)) -> 1 | AB93: =IF(AA93=1,SUM(AA$8:AA93),"") -> 78
A94: =IF(87>$B$5,"",87) -> 87 | B94: =IF(A94="","",INDEX($Z$8:$Z$148,MATCH(A94,$AB$8:$AB$148,0))) -> K-11 | C94: =IF(B94="","",INDEX('Rule Matrix'!$B$2:$B$142,MATCH(B94,'Rule Matrix'!$A$2:$A$142,0))) -> K. Sec 73 / 74 / 74A Applicability | D94: =IF(B94="","",INDEX('Rule Matrix'!$C$2:$C$142,MATCH(B94,'Rule Matrix'!$A$2:$A$142,0))) -> Recurring issues – statement route | E94: =IF(B94="","",INDEX('Rule Matrix'!$D$2:$D$142,MATCH(B94,'Rule Matrix'!$A$2:$A$142,0))) -> s.73(3), 74(3), 74A(3) | F94: =IF(B94="","",INDEX('Rule Matrix'!$F$2:$F$142,MATCH(B94,'Rule Matrix'!$A$2:$A$142,0))) -> Same grounds for later periods via statement (DRC-02) – no fresh SCN needed | G94: =IF(B94="","",INDEX('Rule Matrix'!$G$2:$G$142,MATCH(B94,'Rule Matrix'!$A$2:$A$142,0))) -> Repeat issue | H94: =IF(B94="","",INDEX('Rule Matrix'!$H$2:$H$142,MATCH(B94,'Rule Matrix'!$A$2:$A$142,0))) -> Low | I94: =IF(B94="","",INDEX('Rule Matrix'!$J$2:$J$142,MATCH(B94,'Rule Matrix'!$A$2:$A$142,0))) -> Track across periods | Z94: =Applicability!A88 -> K-03 | AA94: =IF($Z$5=0,0,IF(AND(INDEX(Applicability!$E$88:$O$88,1,$Z$5)="Y",OR(Applicability!$D$88="",IFERROR(INDEX($B$4:$F$4,MATCH(Applicability!$D$88,$B$3:$F$3,0)),"N")="Y")),1,0)) -> 1 | AB94: =IF(AA94=1,SUM(AA$8:AA94),"") -> 79
A95: =IF(88>$B$5,"",88) -> 88 | B95: =IF(A95="","",INDEX($Z$8:$Z$148,MATCH(A95,$AB$8:$AB$148,0))) -> L-01 | C95: =IF(B95="","",INDEX('Rule Matrix'!$B$2:$B$142,MATCH(B95,'Rule Matrix'!$A$2:$A$142,0))) -> L. Industry-Specific | D95: =IF(B95="","",INDEX('Rule Matrix'!$C$2:$C$142,MATCH(B95,'Rule Matrix'!$A$2:$A$142,0))) -> Residential project rate & ITC bar | E95: =IF(B95="","",INDEX('Rule Matrix'!$D$2:$D$142,MATCH(B95,'Rule Matrix'!$A$2:$A$142,0))) -> Notfn 11/2017-CTR entries (i),(ia)-(if) as amended by 3/2019 | F95: =IF(B95="","",INDEX('Rule Matrix'!$F$2:$F$142,MATCH(B95,'Rule Matrix'!$A$2:$A$142,0))) -> Residential RREP/non-RREP at concessional rate without ITC; no ITC claimed on such projects; ongoing-project option exercised | G95: =IF(B95="","",INDEX('Rule Matrix'!$G$2:$G$142,MATCH(B95,'Rule Matrix'!$A$2:$A$142,0))) -> Any ITC | H95: =IF(B95="","",INDEX('Rule Matrix'!$H$2:$H$142,MATCH(B95,'Rule Matrix'!$A$2:$A$142,0))) -> High | I95: =IF(B95="","",INDEX('Rule Matrix'!$J$2:$J$142,MATCH(B95,'Rule Matrix'!$A$2:$A$142,0))) -> Reverse ITC | Z95: =Applicability!A89 -> K-04 | AA95: =IF($Z$5=0,0,IF(AND(INDEX(Applicability!$E$89:$O$89,1,$Z$5)="Y",OR(Applicability!$D$89="",IFERROR(INDEX($B$4:$F$4,MATCH(Applicability!$D$89,$B$3:$F$3,0)),"N")="Y")),1,0)) -> 1 | AB95: =IF(AA95=1,SUM(AA$8:AA95),"") -> 80
A96: =IF(89>$B$5,"",89) -> 89 | B96: =IF(A96="","",INDEX($Z$8:$Z$148,MATCH(A96,$AB$8:$AB$148,0))) -> L-02 | C96: =IF(B96="","",INDEX('Rule Matrix'!$B$2:$B$142,MATCH(B96,'Rule Matrix'!$A$2:$A$142,0))) -> L. Industry-Specific | D96: =IF(B96="","",INDEX('Rule Matrix'!$C$2:$C$142,MATCH(B96,'Rule Matrix'!$A$2:$A$142,0))) -> 80% procurement from registered persons | E96: =IF(B96="","",INDEX('Rule Matrix'!$D$2:$D$142,MATCH(B96,'Rule Matrix'!$A$2:$A$142,0))) -> Notfn 3/2019, 7/2019-CTR | F96: =IF(B96="","",INDEX('Rule Matrix'!$F$2:$F$142,MATCH(B96,'Rule Matrix'!$A$2:$A$142,0))) -> Inputs/input services from registered ≥ 80% (project-wise, FY-wise); shortfall RCM @18%; cement from URP always RCM at applicable rate (18% w.e.f. 22.09.2025, earlier 28%); capital goods from URP at applicable rate | G96: =IF(B96="","",INDEX('Rule Matrix'!$G$2:$G$142,MATCH(B96,'Rule Matrix'!$A$2:$A$142,0))) -> Shortfall | H96: =IF(B96="","",INDEX('Rule Matrix'!$H$2:$H$142,MATCH(B96,'Rule Matrix'!$A$2:$A$142,0))) -> High | I96: =IF(B96="","",INDEX('Rule Matrix'!$J$2:$J$142,MATCH(B96,'Rule Matrix'!$A$2:$A$142,0))) -> Pay RCM via DRC-03/3B | Z96: =Applicability!A90 -> K-05 | AA96: =IF($Z$5=0,0,IF(AND(INDEX(Applicability!$E$90:$O$90,1,$Z$5)="Y",OR(Applicability!$D$90="",IFERROR(INDEX($B$4:$F$4,MATCH(Applicability!$D$90,$B$3:$F$3,0)),"N")="Y")),1,0)) -> 1 | AB96: =IF(AA96=1,SUM(AA$8:AA96),"") -> 81
A97: =IF(90>$B$5,"",90) -> 90 | B97: =IF(A97="","",INDEX($Z$8:$Z$148,MATCH(A97,$AB$8:$AB$148,0))) -> L-03 | C97: =IF(B97="","",INDEX('Rule Matrix'!$B$2:$B$142,MATCH(B97,'Rule Matrix'!$A$2:$A$142,0))) -> L. Industry-Specific | D97: =IF(B97="","",INDEX('Rule Matrix'!$C$2:$C$142,MATCH(B97,'Rule Matrix'!$A$2:$A$142,0))) -> Land value deduction | E97: =IF(B97="","",INDEX('Rule Matrix'!$D$2:$D$142,MATCH(B97,'Rule Matrix'!$A$2:$A$142,0))) -> Notfn 11/2017-CTR para 2 | F97: =IF(B97="","",INDEX('Rule Matrix'!$F$2:$F$142,MATCH(B97,'Rule Matrix'!$A$2:$A$142,0))) -> Deemed land value 1/3 of total consideration deducted; no other land deduction | G97: =IF(B97="","",INDEX('Rule Matrix'!$G$2:$G$142,MATCH(B97,'Rule Matrix'!$A$2:$A$142,0))) -> Deviation | H97: =IF(B97="","",INDEX('Rule Matrix'!$H$2:$H$142,MATCH(B97,'Rule Matrix'!$A$2:$A$142,0))) -> Med | I97: =IF(B97="","",INDEX('Rule Matrix'!$J$2:$J$142,MATCH(B97,'Rule Matrix'!$A$2:$A$142,0))) -> Correct valuation | Z97: =Applicability!A91 -> K-06 | AA97: =IF($Z$5=0,0,IF(AND(INDEX(Applicability!$E$91:$O$91,1,$Z$5)="Y",OR(Applicability!$D$91="",IFERROR(INDEX($B$4:$F$4,MATCH(Applicability!$D$91,$B$3:$F$3,0)),"N")="Y")),1,0)) -> 1 | AB97: =IF(AA97=1,SUM(AA$8:AA97),"") -> 82
A98: =IF(91>$B$5,"",91) -> 91 | B98: =IF(A98="","",INDEX($Z$8:$Z$148,MATCH(A98,$AB$8:$AB$148,0))) -> L-04 | C98: =IF(B98="","",INDEX('Rule Matrix'!$B$2:$B$142,MATCH(B98,'Rule Matrix'!$A$2:$A$142,0))) -> L. Industry-Specific | D98: =IF(B98="","",INDEX('Rule Matrix'!$C$2:$C$142,MATCH(B98,'Rule Matrix'!$A$2:$A$142,0))) -> TDR / FSI / long-term lease premium | E98: =IF(B98="","",INDEX('Rule Matrix'!$D$2:$D$142,MATCH(B98,'Rule Matrix'!$A$2:$A$142,0))) -> Notfn 4/2019, 5/2019-CTR, 13/2017-CTR | F98: =IF(B98="","",INDEX('Rule Matrix'!$F$2:$F$142,MATCH(B98,'Rule Matrix'!$A$2:$A$142,0))) -> RCM on TDR/FSI/upfront lease premium; exemption proportion for residential units sold before CC; tax on unsold area at CC | G98: =IF(B98="","",INDEX('Rule Matrix'!$G$2:$G$142,MATCH(B98,'Rule Matrix'!$A$2:$A$142,0))) -> Any | H98: =IF(B98="","",INDEX('Rule Matrix'!$H$2:$H$142,MATCH(B98,'Rule Matrix'!$A$2:$A$142,0))) -> High | I98: =IF(B98="","",INDEX('Rule Matrix'!$J$2:$J$142,MATCH(B98,'Rule Matrix'!$A$2:$A$142,0))) -> Pay RCM on due time of supply | Z98: =Applicability!A92 -> K-07 | AA98: =IF($Z$5=0,0,IF(AND(INDEX(Applicability!$E$92:$O$92,1,$Z$5)="Y",OR(Applicability!$D$92="",IFERROR(INDEX($B$4:$F$4,MATCH(Applicability!$D$92,$B$3:$F$3,0)),"N")="Y")),1,0)) -> 1 | AB98: =IF(AA98=1,SUM(AA$8:AA98),"") -> 83
A99: =IF(92>$B$5,"",92) -> 92 | B99: =IF(A99="","",INDEX($Z$8:$Z$148,MATCH(A99,$AB$8:$AB$148,0))) -> L-05 | C99: =IF(B99="","",INDEX('Rule Matrix'!$B$2:$B$142,MATCH(B99,'Rule Matrix'!$A$2:$A$142,0))) -> L. Industry-Specific | D99: =IF(B99="","",INDEX('Rule Matrix'!$C$2:$C$142,MATCH(B99,'Rule Matrix'!$A$2:$A$142,0))) -> Completion certificate & unsold units | E99: =IF(B99="","",INDEX('Rule Matrix'!$D$2:$D$142,MATCH(B99,'Rule Matrix'!$A$2:$A$142,0))) -> Sch III para 5(b), Rule 42/43 (Annexure for RE) | F99: =IF(B99="","",INDEX('Rule Matrix'!$F$2:$F$142,MATCH(B99,'Rule Matrix'!$A$2:$A$142,0))) -> Sales after CC not a supply; common ITC reversal for area unsold on CC | G99: =IF(B99="","",INDEX('Rule Matrix'!$G$2:$G$142,MATCH(B99,'Rule Matrix'!$A$2:$A$142,0))) -> Any | H99: =IF(B99="","",INDEX('Rule Matrix'!$H$2:$H$142,MATCH(B99,'Rule Matrix'!$A$2:$A$142,0))) -> High | I99: =IF(B99="","",INDEX('Rule Matrix'!$J$2:$J$142,MATCH(B99,'Rule Matrix'!$A$2:$A$142,0))) -> Reverse ITC | Z99: =Applicability!A93 -> K-08 | AA99: =IF($Z$5=0,0,IF(AND(INDEX(Applicability!$E$93:$O$93,1,$Z$5)="Y",OR(Applicability!$D$93="",IFERROR(INDEX($B$4:$F$4,MATCH(Applicability!$D$93,$B$3:$F$3,0)),"N")="Y")),1,0)) -> 1 | AB99: =IF(AA99=1,SUM(AA$8:AA99),"") -> 84
A100: =IF(93>$B$5,"",93) -> 93 | B100: =IF(A100="","",INDEX($Z$8:$Z$148,MATCH(A100,$AB$8:$AB$148,0))) -> L-06 | C100: =IF(B100="","",INDEX('Rule Matrix'!$B$2:$B$142,MATCH(B100,'Rule Matrix'!$A$2:$A$142,0))) -> L. Industry-Specific | D100: =IF(B100="","",INDEX('Rule Matrix'!$C$2:$C$142,MATCH(B100,'Rule Matrix'!$A$2:$A$142,0))) -> Joint development – landowner share | E100: =IF(B100="","",INDEX('Rule Matrix'!$D$2:$D$142,MATCH(B100,'Rule Matrix'!$A$2:$A$142,0))) -> Notfn 11/2017, 4/2019-CTR; s.15 | F100: =IF(B100="","",INDEX('Rule Matrix'!$F$2:$F$142,MATCH(B100,'Rule Matrix'!$A$2:$A$142,0))) -> Construction service to landowner valued at similar flat price; landowner TDR/development rights RCM | G100: =IF(B100="","",INDEX('Rule Matrix'!$G$2:$G$142,MATCH(B100,'Rule Matrix'!$A$2:$A$142,0))) -> Any | H100: =IF(B100="","",INDEX('Rule Matrix'!$H$2:$H$142,MATCH(B100,'Rule Matrix'!$A$2:$A$142,0))) -> High | I100: =IF(B100="","",INDEX('Rule Matrix'!$J$2:$J$142,MATCH(B100,'Rule Matrix'!$A$2:$A$142,0))) -> Pay tax | Z100: =Applicability!A94 -> K-09 | AA100: =IF($Z$5=0,0,IF(AND(INDEX(Applicability!$E$94:$O$94,1,$Z$5)="Y",OR(Applicability!$D$94="",IFERROR(INDEX($B$4:$F$4,MATCH(Applicability!$D$94,$B$3:$F$3,0)),"N")="Y")),1,0)) -> 1 | AB100: =IF(AA100=1,SUM(AA$8:AA100),"") -> 85
A101: =IF(94>$B$5,"",94) -> 94 | B101: =IF(A101="","",INDEX($Z$8:$Z$148,MATCH(A101,$AB$8:$AB$148,0))) -> L-07 | C101: =IF(B101="","",INDEX('Rule Matrix'!$B$2:$B$142,MATCH(B101,'Rule Matrix'!$A$2:$A$142,0))) -> L. Industry-Specific | D101: =IF(B101="","",INDEX('Rule Matrix'!$C$2:$C$142,MATCH(B101,'Rule Matrix'!$A$2:$A$142,0))) -> Booking cancellations | E101: =IF(B101="","",INDEX('Rule Matrix'!$D$2:$D$142,MATCH(B101,'Rule Matrix'!$A$2:$A$142,0))) -> s.34 | F101: =IF(B101="","",INDEX('Rule Matrix'!$F$2:$F$142,MATCH(B101,'Rule Matrix'!$A$2:$A$142,0))) -> CN within s.34 time limit; linked to original demand invoice | G101: =IF(B101="","",INDEX('Rule Matrix'!$G$2:$G$142,MATCH(B101,'Rule Matrix'!$A$2:$A$142,0))) -> Late CN | H101: =IF(B101="","",INDEX('Rule Matrix'!$H$2:$H$142,MATCH(B101,'Rule Matrix'!$A$2:$A$142,0))) -> Med | I101: =IF(B101="","",INDEX('Rule Matrix'!$J$2:$J$142,MATCH(B101,'Rule Matrix'!$A$2:$A$142,0))) -> Issue CN within limit | Z101: =Applicability!A95 -> K-10 | AA101: =IF($Z$5=0,0,IF(AND(INDEX(Applicability!$E$95:$O$95,1,$Z$5)="Y",OR(Applicability!$D$95="",IFERROR(INDEX($B$4:$F$4,MATCH(Applicability!$D$95,$B$3:$F$3,0)),"N")="Y")),1,0)) -> 1 | AB101: =IF(AA101=1,SUM(AA$8:AA101),"") -> 86
...

Sheet Summary
A1: Module | B1: Total | C1: High | D1: Med | E1: Low | F1: Fail | G1: Pending | H1: Exposure (₹)
A2: A. Data Integrity | B2: =COUNTIF('Rule Matrix'!$B$2:$B$142,A2) -> 3 | C2: =COUNTIFS('Rule Matrix'!$B$2:$B$142,A2,'Rule Matrix'!$H$2:$H$142,"High") -> 1 | D2: =COUNTIFS('Rule Matrix'!$B$2:$B$142,A2,'Rule Matrix'!$H$2:$H$142,"Med") -> 2 | E2: =COUNTIFS('Rule Matrix'!$B$2:$B$142,A2,'Rule Matrix'!$H$2:$H$142,"Low") -> 0 | F2: =COUNTIFS('Rule Matrix'!$B$2:$B$142,A2,'Rule Matrix'!$K$2:$K$142,"Fail") -> 1 | G2: =COUNTIFS('Rule Matrix'!$B$2:$B$142,A2,'Rule Matrix'!$K$2:$K$142,"Pending") -> 2 | H2: =SUMIFS('Rule Matrix'!$L$2:$L$142,'Rule Matrix'!$B$2:$B$142,A2) -> 125000
A3: B. ITC Eligibility (s.16) | B3: =COUNTIF('Rule Matrix'!$B$2:$B$142,A3) -> 11 | C3: =COUNTIFS('Rule Matrix'!$B$2:$B$142,A3,'Rule Matrix'!$H$2:$H$142,"High") -> 8 | D3: =COUNTIFS('Rule Matrix'!$B$2:$B$142,A3,'Rule Matrix'!$H$2:$H$142,"Med") -> 3 | E3: =COUNTIFS('Rule Matrix'!$B$2:$B$142,A3,'Rule Matrix'!$H$2:$H$142,"Low") -> 0 | F3: =COUNTIFS('Rule Matrix'!$B$2:$B$142,A3,'Rule Matrix'!$K$2:$K$142,"Fail") -> 0 | G3: =COUNTIFS('Rule Matrix'!$B$2:$B$142,A3,'Rule Matrix'!$K$2:$K$142,"Pending") -> 11 | H3: =SUMIFS('Rule Matrix'!$L$2:$L$142,'Rule Matrix'!$B$2:$B$142,A3) -> 0
A4: C. RCM | B4: =COUNTIF('Rule Matrix'!$B$2:$B$142,A4) -> 5 | C4: =COUNTIFS('Rule Matrix'!$B$2:$B$142,A4,'Rule Matrix'!$H$2:$H$142,"High") -> 3 | D4: =COUNTIFS('Rule Matrix'!$B$2:$B$142,A4,'Rule Matrix'!$H$2:$H$142,"Med") -> 1 | E4: =COUNTIFS('Rule Matrix'!$B$2:$B$142,A4,'Rule Matrix'!$H$2:$H$142,"Low") -> 1 | F4: =COUNTIFS('Rule Matrix'!$B$2:$B$142,A4,'Rule Matrix'!$K$2:$K$142,"Fail") -> 0 | G4: =COUNTIFS('Rule Matrix'!$B$2:$B$142,A4,'Rule Matrix'!$K$2:$K$142,"Pending") -> 5 | H4: =SUMIFS('Rule Matrix'!$L$2:$L$142,'Rule Matrix'!$B$2:$B$142,A4) -> 0
A5: D. Place of Supply | B5: =COUNTIF('Rule Matrix'!$B$2:$B$142,A5) -> 8 | C5: =COUNTIFS('Rule Matrix'!$B$2:$B$142,A5,'Rule Matrix'!$H$2:$H$142,"High") -> 2 | D5: =COUNTIFS('Rule Matrix'!$B$2:$B$142,A5,'Rule Matrix'!$H$2:$H$142,"Med") -> 4 | E5: =COUNTIFS('Rule Matrix'!$B$2:$B$142,A5,'Rule Matrix'!$H$2:$H$142,"Low") -> 2 | F5: =COUNTIFS('Rule Matrix'!$B$2:$B$142,A5,'Rule Matrix'!$K$2:$K$142,"Fail") -> 0 | G5: =COUNTIFS('Rule Matrix'!$B$2:$B$142,A5,'Rule Matrix'!$K$2:$K$142,"Pending") -> 8 | H5: =SUMIFS('Rule Matrix'!$L$2:$L$142,'Rule Matrix'!$B$2:$B$142,A5) -> 0
A6: E. Blocked Credits s.17(5) | B6: =COUNTIF('Rule Matrix'!$B$2:$B$142,A6) -> 15 | C6: =COUNTIFS('Rule Matrix'!$B$2:$B$142,A6,'Rule Matrix'!$H$2:$H$142,"High") -> 7 | D6: =COUNTIFS('Rule Matrix'!$B$2:$B$142,A6,'Rule Matrix'!$H$2:$H$142,"Med") -> 8 | E6: =COUNTIFS('Rule Matrix'!$B$2:$B$142,A6,'Rule Matrix'!$H$2:$H$142,"Low") -> 0 | F6: =COUNTIFS('Rule Matrix'!$B$2:$B$142,A6,'Rule Matrix'!$K$2:$K$142,"Fail") -> 0 | G6: =COUNTIFS('Rule Matrix'!$B$2:$B$142,A6,'Rule Matrix'!$K$2:$K$142,"Pending") -> 15 | H6: =SUMIFS('Rule Matrix'!$L$2:$L$142,'Rule Matrix'!$B$2:$B$142,A6) -> 0
A7: F. Reversals & Apportionment | B7: =COUNTIF('Rule Matrix'!$B$2:$B$142,A7) -> 7 | C7: =COUNTIFS('Rule Matrix'!$B$2:$B$142,A7,'Rule Matrix'!$H$2:$H$142,"High") -> 3 | D7: =COUNTIFS('Rule Matrix'!$B$2:$B$142,A7,'Rule Matrix'!$H$2:$H$142,"Med") -> 4 | E7: =COUNTIFS('Rule Matrix'!$B$2:$B$142,A7,'Rule Matrix'!$H$2:$H$142,"Low") -> 0 | F7: =COUNTIFS('Rule Matrix'!$B$2:$B$142,A7,'Rule Matrix'!$K$2:$K$142,"Fail") -> 0 | G7: =COUNTIFS('Rule Matrix'!$B$2:$B$142,A7,'Rule Matrix'!$K$2:$K$142,"Pending") -> 7 | H7: =SUMIFS('Rule Matrix'!$L$2:$L$142,'Rule Matrix'!$B$2:$B$142,A7) -> 0
A8: G. Outward Supplies | B8: =COUNTIF('Rule Matrix'!$B$2:$B$142,A8) -> 15 | C8: =COUNTIFS('Rule Matrix'!$B$2:$B$142,A8,'Rule Matrix'!$H$2:$H$142,"High") -> 8 | D8: =COUNTIFS('Rule Matrix'!$B$2:$B$142,A8,'Rule Matrix'!$H$2:$H$142,"Med") -> 6 | E8: =COUNTIFS('Rule Matrix'!$B$2:$B$142,A8,'Rule Matrix'!$H$2:$H$142,"Low") -> 1 | F8: =COUNTIFS('Rule Matrix'!$B$2:$B$142,A8,'Rule Matrix'!$K$2:$K$142,"Fail") -> 0 | G8: =COUNTIFS('Rule Matrix'!$B$2:$B$142,A8,'Rule Matrix'!$K$2:$K$142,"Pending") -> 15 | H8: =SUMIFS('Rule Matrix'!$L$2:$L$142,'Rule Matrix'!$B$2:$B$142,A8) -> 0
A9: H. Credit & Debit Notes | B9: =COUNTIF('Rule Matrix'!$B$2:$B$142,A9) -> 8 | C9: =COUNTIFS('Rule Matrix'!$B$2:$B$142,A9,'Rule Matrix'!$H$2:$H$142,"High") -> 4 | D9: =COUNTIFS('Rule Matrix'!$B$2:$B$142,A9,'Rule Matrix'!$H$2:$H$142,"Med") -> 2 | E9: =COUNTIFS('Rule Matrix'!$B$2:$B$142,A9,'Rule Matrix'!$H$2:$H$142,"Low") -> 2 | F9: =COUNTIFS('Rule Matrix'!$B$2:$B$142,A9,'Rule Matrix'!$K$2:$K$142,"Fail") -> 0 | G9: =COUNTIFS('Rule Matrix'!$B$2:$B$142,A9,'Rule Matrix'!$K$2:$K$142,"Pending") -> 8 | H9: =SUMIFS('Rule Matrix'!$L$2:$L$142,'Rule Matrix'!$B$2:$B$142,A9) -> 0
A10: I. Annual Report Linkages | B10: =COUNTIF('Rule Matrix'!$B$2:$B$142,A10) -> 8 | C10: =COUNTIFS('Rule Matrix'!$B$2:$B$142,A10,'Rule Matrix'!$H$2:$H$142,"High") -> 4 | D10: =COUNTIFS('Rule Matrix'!$B$2:$B$142,A10,'Rule Matrix'!$H$2:$H$142,"Med") -> 4 | E10: =COUNTIFS('Rule Matrix'!$B$2:$B$142,A10,'Rule Matrix'!$H$2:$H$142,"Low") -> 0 | F10: =COUNTIFS('Rule Matrix'!$B$2:$B$142,A10,'Rule Matrix'!$K$2:$K$142,"Fail") -> 0 | G10: =COUNTIFS('Rule Matrix'!$B$2:$B$142,A10,'Rule Matrix'!$K$2:$K$142,"Pending") -> 8 | H10: =SUMIFS('Rule Matrix'!$L$2:$L$142,'Rule Matrix'!$B$2:$B$142,A10) -> 0
A11: J. Interest, Fees, Payments | B11: =COUNTIF('Rule Matrix'!$B$2:$B$142,A11) -> 4 | C11: =COUNTIFS('Rule Matrix'!$B$2:$B$142,A11,'Rule Matrix'!$H$2:$H$142,"High") -> 1 | D11: =COUNTIFS('Rule Matrix'!$B$2:$B$142,A11,'Rule Matrix'!$H$2:$H$142,"Med") -> 1 | E11: =COUNTIFS('Rule Matrix'!$B$2:$B$142,A11,'Rule Matrix'!$H$2:$H$142,"Low") -> 2 | F11: =COUNTIFS('Rule Matrix'!$B$2:$B$142,A11,'Rule Matrix'!$K$2:$K$142,"Fail") -> 0 | G11: =COUNTIFS('Rule Matrix'!$B$2:$B$142,A11,'Rule Matrix'!$K$2:$K$142,"Pending") -> 4 | H11: =SUMIFS('Rule Matrix'!$L$2:$L$142,'Rule Matrix'!$B$2:$B$142,A11) -> 0
A12: K. Sec 73 / 74 / 74A Applicability | B12: =COUNTIF('Rule Matrix'!$B$2:$B$142,A12) -> 11 | C12: =COUNTIFS('Rule Matrix'!$B$2:$B$142,A12,'Rule Matrix'!$H$2:$H$142,"High") -> 4 | D12: =COUNTIFS('Rule Matrix'!$B$2:$B$142,A12,'Rule Matrix'!$H$2:$H$142,"Med") -> 5 | E12: =COUNTIFS('Rule Matrix'!$B$2:$B$142,A12,'Rule Matrix'!$H$2:$H$142,"Low") -> 2 | F12: =COUNTIFS('Rule Matrix'!$B$2:$B$142,A12,'Rule Matrix'!$K$2:$K$142,"Fail") -> 0 | G12: =COUNTIFS('Rule Matrix'!$B$2:$B$142,A12,'Rule Matrix'!$K$2:$K$142,"Pending") -> 11 | H12: =SUMIFS('Rule Matrix'!$L$2:$L$142,'Rule Matrix'!$B$2:$B$142,A12) -> 0
A13: L. Industry-Specific | B13: =COUNTIF('Rule Matrix'!$B$2:$B$142,A13) -> 46 | C13: =COUNTIFS('Rule Matrix'!$B$2:$B$142,A13,'Rule Matrix'!$H$2:$H$142,"High") -> 21 | D13: =COUNTIFS('Rule Matrix'!$B$2:$B$142,A13,'Rule Matrix'!$H$2:$H$142,"Med") -> 23 | E13: =COUNTIFS('Rule Matrix'!$B$2:$B$142,A13,'Rule Matrix'!$H$2:$H$142,"Low") -> 2 | F13: =COUNTIFS('Rule Matrix'!$B$2:$B$142,A13,'Rule Matrix'!$K$2:$K$142,"Fail") -> 0 | G13: =COUNTIFS('Rule Matrix'!$B$2:$B$142,A13,'Rule Matrix'!$K$2:$K$142,"Pending") -> 46 | H13: =SUMIFS('Rule Matrix'!$L$2:$L$142,'Rule Matrix'!$B$2:$B$142,A13) -> 0
A14: Total | B14: =SUM(B2:B13) -> 141 | C14: =SUM(C2:C13) -> 66 | D14: =SUM(D2:D13) -> 63 | E14: =SUM(E2:E13) -> 12 | F14: =SUM(F2:F13) -> 1 | G14: =SUM(G2:G13) -> 140 | H14: =SUM(H2:H13) -> 125000

Sheet Rule Matrix
A1: Rule ID | B1: Module | C1: Check | D1: Legal Reference | E1: Data Sources | F1: Logic / Test | G1: Threshold | H1: Severity | I1: Exposure Basis | J1: Action | K1: Status | L1: Exposure (₹) | M1: Remarks
A2: A-01 | B2: A. Data Integrity | C2: GSTIN master validation | D2: Rule 10A/21A | E2: GSTIN master (API), purchase register | F2: Check each vendor/customer GSTIN active on invoice date; flag cancelled (incl. retrospective), suspended, composition | G2: Any mismatch | H2: High | I2: ITC on invoices of non-active/composition vendors | J2: Reverse ITC; obtain vendor clarification | K2: Pending
A3: A-02 | B3: A. Data Integrity | C3: Period & return filing completeness | D3: s.37/39/44 | E3: Return filing status | F3: All GSTR-1/3B/9/9C filed for all periods; compute delay days | G3: Any non-filing | H3: Med | I3: Late fee + interest | J3: File pending; pay late fee | K3: Fail | L3: 125000 | M3: Sample: excess ITC Jul-25
A4: A-03 | B4: A. Data Integrity | C4: Books vs return data completeness | D4: — | E4: TB, registers, GSTR-1/3B | F4: Sum of registers = GL control accounts; all GSTINs of PAN covered | G4: Diff > ₹1,000 | H4: Med | I4: N/A | J4: Reconcile registers to GL | K4: Pending
A5: B-01 | B5: B. ITC Eligibility (s.16) | C5: ITC claimed vs GSTR-2B | D5: s.16(2)(aa), Rule 36(4) | E5: GSTR-3B Table 4, GSTR-2B | F5: Line-level match: GSTIN+Inv No+Date+Taxable+Tax; ITC in 3B > 2B → excess | G5: Diff > ₹1,000/month or > 1% | H5: High | I5: Excess ITC + 18% interest | J5: Reverse via DRC-03; respond to DRC-01C (Rule 88D) | K5: Pending
A6: B-02 | B6: B. ITC Eligibility (s.16) | C6: ITC in books but not in 2B | D6: s.16(2)(aa) | E6: Purchase register, GSTR-2B | F6: Invoices in books absent in 2B/IMS | G6: Any | H6: Med | I6: Tax on unmatched invoices | J6: Vendor follow-up; defer claim | K6: Pending
A7: B-03 | B7: B. ITC Eligibility (s.16) | C7: Receipt of goods/services | D7: s.16(2)(b) | E7: GRN, e-way bill, purchase register | F7: Invoice without GRN/EWB for goods; bill-to-ship-to documentation | G7: Any | H7: High | I7: ITC on unsupported invoices | J7: Obtain proof of receipt | K7: Pending
A8: B-04 | B8: B. ITC Eligibility (s.16) | C8: Supplier tax payment (Rule 37A) | D8: s.16(2)(c), Rule 37A; Suncraft Energy (Cal HC; SC dismissed SLP, Dec 2023) | E8: GSTR-2B, vendor 3B filing status | F8: Vendor 3B not filed by 30 Sept of next FY → reverse by 30 Nov. Defence: ITC cannot be denied to bona fide buyer solely for supplier default without first proceeding against supplier | G8: Any | H8: High | I8: ITC of such vendors | J8: Reverse by 30 Nov; reclaim once vendor files | K8: Pending
A9: B-05 | B9: B. ITC Eligibility (s.16) | C9: Payment within 180 days | D9: Rule 37, s.16(2) 2nd proviso | E9: Payables ageing, bank ledger | F9: Unpaid value > 180 days from invoice date (excl. RCM, deemed supply) | G9: Any | H9: High | I9: Proportionate ITC + interest | J9: Reverse in 3B; reclaim on payment | K9: Pending
A10: B-06 | B10: B. ITC Eligibility (s.16) | C10: Depreciation on tax component | D10: s.16(3) | E10: Fixed asset register, ITC ledger | F10: Capital goods where ITC claimed AND GST capitalised in cost | G10: Any | H10: High | I10: ITC on such assets | J10: Reverse ITC or de-capitalise | K10: Pending
A11: B-07 | B11: B. ITC Eligibility (s.16) | C11: Time limit for ITC | D11: s.16(4), 16(5), 16(6) | E11: 3B claim period, invoice/DN date | F11: Claimed after earlier of 30 Nov next FY / annual return date; DN date used for DN | G11: Any | H11: High | I11: Time-barred ITC | J11: Reverse; check 16(5)/(6) relaxation | K11: Pending
A12: B-08 | B12: B. ITC Eligibility (s.16) | C12: Duplicate ITC | D12: s.16 | E12: Purchase register, 3B | F12: Same GSTIN+Inv No claimed twice / across GSTINs / periods | G12: Any | H12: High | I12: Duplicate ITC | J12: Reverse | K12: Pending
A13: B-09 | B13: B. ITC Eligibility (s.16) | C13: Import IGST | D13: s.16, Rule 36(1)(d) | E13: ICEGATE BoE, 2B, 3B 4(A)(1) | F13: BoE IGST in books = 2B = 3B | G13: Diff > ₹1,000 | H13: Med | I13: Excess ITC | J13: Reconcile; amend | K13: Pending
A14: B-10 | B14: B. ITC Eligibility (s.16) | C14: ITC on invoices from cancelled/composition vendors | D14: s.16, s.10(4) | E14: GSTIN master, 2B | F14: Tax charged by composition dealer or post-cancellation invoice | G14: Any | H14: High | I14: Full ITC | J14: Reverse | K14: Pending
A15: B-11 | B15: B. ITC Eligibility (s.16) | C15: Document validity | D15: s.16(2)(a), Rule 36 | E15: Invoices | F15: Mandatory particulars present (Rule 46): GSTIN, HSN, POS, tax break-up; e-invoice IRN where supplier mandated | G15: Any | H15: Med | I15: ITC on defective docs | J15: Obtain corrected invoice | K15: Pending
... A142: L-46 | B142: L. Industry-Specific | C142: Predominantly exempt – Rule 42 reversal | D142: s.17(2), Rule 42/43 | E142: ITC ledger, turnover | F142: Common ITC reversal on high exempt ratio; registration threshold | G142: Short reversal | H142: High | I142: ITC reversal | J142: Reverse | K142: Pending

Sheet Sec 73-74 Classifier
A1: Case # | B1: Rule ID | C1: Check (auto) | D1: FY | E1: Tax Amount (₹) | F1: Fake invoice / ITC w/o supply (Y/N) | G1: Suppression / non-disclosure (Y/N) | H1: Wilful misstatement (Y/N) | I1: Nature (auto) | J1: Section (auto) | K1: AR Due Date (auto) | L1: SCN Deadline (auto) | M1: Order Deadline (auto) | N1: Limitation Status (auto) | O1: Payment Stage | P1: Penalty % (auto) | Q1: Penalty ₹ (auto) | R1: Interest From | S1: Payment / Calc Date | T1: Interest ₹ (auto) | U1: Total Exposure ₹ (auto) | V1: s.128A (auto) | W1: Remarks
A2: 1 | B2: B-01 | C2: =IF(B2="","",IFERROR(INDEX('Rule Matrix'!$C$2:$C$142,MATCH(B2,'Rule Matrix'!$A$2:$A$142,0)),"Rule ID not found")) -> ITC claimed vs GSTR-2B | D2: 2022-23 | E2: 125000 | F2: N | G2: N | H2: N | I2: =IF(D2="","",IF(OR(F2="Y",G2="Y",H2="Y"),"Fraud","Non-fraud")) -> Non-fraud | J2: =IF(D2="","",IF(VALUE(LEFT(D2,4))<=2023,IF(I2="Fraud","74","73"),"74A")) -> 73 | K2: =IF(D2="","",INDEX('Limitation Inputs'!$B$2:$B$10,MATCH(D2,'Limitation Inputs'!$A$2:$A$10,0))) -> 45291 | L2: =IF(D2="","",IF(J2="74A",EDATE(K2,42),IF(J2="73",EDATE(M2,-3),EDATE(M2,-6)))) -> 46295 | M2: =IF(D2="","",IF(J2="73",IF(INDEX('Limitation Inputs'!$C$2:$C$10,MATCH(D2,'Limitation Inputs'!$A$2:$A$10,0))>0,INDEX('Limitation Inputs'!$C$2:$C$10,MATCH(D2,'Limitation Inputs'!$A$2:$A$10,0)),EDATE(K2,36)),IF(J2="74",EDATE(K2,60),EDATE(L2,12)))) -> 46387 | N2: =IF(D2="","",IF(AND(J2="74A",N(E2)<1000),"Below ₹1,000 – no SCN",IF('Limitation Inputs'!$B$13>M2,"Order time-barred",IF('Limitation Inputs'!$B$13>L2,"SCN time-barred","Open")))&IF(AND(J2="73",VALUE(LEFT(D2,4))<=2019)," | 168A ext. sub judice","")) -> Open | O2: Before SCN | P2: =IF(OR(D2="",O2=""),"",IF(I2="Non-fraud",IF(OR(O2="Before SCN",O2="Within window of SCN"),0,0.1),IF(O2="Before SCN",0.15,IF(O2="Within window of SCN",0.25,IF(O2="Within window of order",0.5,1))))) -> 0 | Q2: =IF(P2="","",IF(AND(I2="Non-fraud",P2>0),MAX(E2*P2,10000),E2*P2)) -> 0 | R2: 45036 | S2: 45945 | T2: =IF(OR(R2="",S2="",E2=""),"",ROUND(E2*'Limitation Inputs'!$B$12*(S2-R2)/365,0)) -> 56034 | U2: =IF(D2="","",N(E2)+N(Q2)+N(T2)) -> 181034 | V2: =IF(D2="","",IF(AND(J2="73",VALUE(LEFT(D2,4))<=2019),"Eligible if tax paid by 31-Mar-2025","No")) -> No | W2: Sample row
A3: 2 | C3: =IF(B3="","",IFERROR(INDEX('Rule Matrix'!$C$2:$C$142,MATCH(B3,'Rule Matrix'!$A$2:$A$142,0)),"Rule ID not found")) | I3: =IF(D3="","",IF(OR(F3="Y",G3="Y",H3="Y"),"Fraud","Non-fraud")) | J3: =IF(D3="","",IF(VALUE(LEFT(D3,4))<=2023,IF(I3="Fraud","74","73"),"74A")) | K3: =IF(D3="","",INDEX('Limitation Inputs'!$B$2:$B$10,MATCH(D3,'Limitation Inputs'!$A$2:$A$10,0))) | L3: =IF(D3="","",IF(J3="74A",EDATE(K3,42),IF(J3="73",EDATE(M3,-3),EDATE(M3,-6)))) | M3: =IF(D3="","",IF(J3="73",IF(INDEX('Limitation Inputs'!$C$2:$C$10,MATCH(D3,'Limitation Inputs'!$A$2:$A$10,0))>0,INDEX('Limitation Inputs'!$C$2:$C$10,MATCH(D3,'Limitation Inputs'!$A$2:$A$10,0)),EDATE(K3,36)),IF(J3="74",EDATE(K3,60),EDATE(L3,12)))) | N3: =IF(D3="","",IF(AND(J3="74A",N(E3)<1000),"Below ₹1,000 – no SCN",IF('Limitation Inputs'!$B$13>M3,"Order time-barred",IF('Limitation Inputs'!$B$13>L3,"SCN time-barred","Open")))&IF(AND(J3="73",VALUE(LEFT(D3,4))<=2019)," | 168A ext. sub judice","")) | P3: =IF(OR(D3="",O3=""),"",IF(I3="Non-fraud",IF(OR(O3="Before SCN",O3="Within window of SCN"),0,0.1),IF(O3="Before SCN",0.15,IF(O3="Within window of SCN",0.25,IF(O3="Within window of order",0.5,1))))) | Q3: =IF(P3="","",IF(AND(I3="Non-fraud",P3>0),MAX(E3*P3,10000),E3*P3)) | T3: =IF(OR(R3="",S3="",E3=""),"",ROUND(E3*'Limitation Inputs'!$B$12*(S3-R3)/365,0)) | U3: =IF(D3="","",N(E3)+N(Q3)+N(T3)) | V3: =IF(D3="","",IF(AND(J3="73",VALUE(LEFT(D3,4))<=2019),"Eligible if tax paid by 31-Mar-2025","No"))
A4: 3 | C4: =IF(B4="","",IFERROR(INDEX('Rule Matrix'!$C$2:$C$142,MATCH(B4,'Rule Matrix'!$A$2:$A$142,0)),"Rule ID not found")) | I4: =IF(D4="","",IF(OR(F4="Y",G4="Y",H4="Y"),"Fraud","Non-fraud")) | J4: =IF(D4="","",IF(VALUE(LEFT(D4,4))<=2023,IF(I4="Fraud","74","73"),"74A")) | K4: =IF(D4="","",INDEX('Limitation Inputs'!$B$2:$B$10,MATCH(D4,'Limitation Inputs'!$A$2:$A$10,0))) | L4: =IF(D4="","",IF(J4="74A",EDATE(K4,42),IF(J4="73",EDATE(M4,-3),EDATE(M4,-6)))) | M4: =IF(D4="","",IF(J4="73",IF(INDEX('Limitation Inputs'!$C$2:$C$10,MATCH(D4,'Limitation Inputs'!$A$2:$A$10,0))>0,INDEX('Limitation Inputs'!$C$2:$C$10,MATCH(D4,'Limitation Inputs'!$A$2:$A$10,0)),EDATE(K4,36)),IF(J4="74",EDATE(K4,60),EDATE(L4,12)))) | N4: =IF(D4="","",IF(AND(J4="74A",N(E4)<1000),"Below ₹1,000 – no SCN",IF('Limitation Inputs'!$B$13>M4,"Order time-barred",IF('Limitation Inputs'!$B$13>L4,"SCN time-barred","Open")))&IF(AND(J4="73",VALUE(LEFT(D4,4))<=2019)," | 168A ext. sub judice","")) | P4: =IF(OR(D4="",O4=""),"",IF(I4="Non-fraud",IF(OR(O4="Before SCN",O4="Within window of SCN"),0,0.1),IF(O4="Before SCN",0.15,IF(O4="Within window of SCN",0.25,IF(O4="Within window of order",0.5,1))))) | Q4: =IF(P4="","",IF(AND(I4="Non-fraud",P4>0),MAX(E4*P4,10000),E4*P4)) | T4: =IF(OR(R4="",S4="",E4=""),"",ROUND(E4*'Limitation Inputs'!$B$12*(S4-R4)/365,0)) | U4: =IF(D4="","",N(E4)+N(Q4)+N(T4)) | V4: =IF(D4="","",IF(AND(J4="73",VALUE(LEFT(D4,4))<=2019),"Eligible if tax paid by 31-Mar-2025","No"))
A5: 4 | C5: =IF(B5="","",IFERROR(INDEX('Rule Matrix'!$C$2:$C$142,MATCH(B5,'Rule Matrix'!$A$2:$A$142,0)),"Rule ID not found")) | I5: =IF(D5="","",IF(OR(F5="Y",G5="Y",H5="Y"),"Fraud","Non-fraud")) | J5: =IF(D5="","",IF(VALUE(LEFT(D5,4))<=2023,IF(I5="Fraud","74","73"),"74A")) | K5: =IF(D5="","",INDEX('Limitation Inputs'!$B$2:$B$10,MATCH(D5,'Limitation Inputs'!$A$2:$A$10,0))) | L5: =IF(D5="","",IF(J5="74A",EDATE(K5,42),IF(J5="73",EDATE(M5,-3),EDATE(M5,-6)))) | M5: =IF(D5="","",IF(J5="73",IF(INDEX('Limitation Inputs'!$C$2:$C$10,MATCH(D5,'Limitation Inputs'!$A$2:$A$10,0))>0,INDEX('Limitation Inputs'!$C$2:$C$10,MATCH(D5,'Limitation Inputs'!$A$2:$A$10,0)),EDATE(K5,36)),IF(J5="74",EDATE(K5,60),EDATE(L5,12)))) | N5: =IF(D5="","",IF(AND(J5="74A",N(E5)<1000),"Below ₹1,000 – no SCN",IF('Limitation Inputs'!$B$13>M5,"Order time-barred",IF('Limitation Inputs'!$B$13>L5,"SCN time-barred","Open")))&IF(AND(J5="73",VALUE(LEFT(D5,4))<=2019)," | 168A ext. sub judice","")) | P5: =IF(OR(D5="",O5=""),"",IF(I5="Non-fraud",IF(OR(O5="Before SCN",O5="Within window of SCN"),0,0.1),IF(O5="Before SCN",0.15,IF(O5="Within window of SCN",0.25,IF(O5="Within window of order",0.5,1))))) | Q5: =IF(P5="","",IF(AND(I5="Non-fraud",P5>0),MAX(E5*P5,10000),E5*P5)) | T5: =IF(OR(R5="",S5="",E5=""),"",ROUND(E5*'Limitation Inputs'!$B$12*(S5-R5)/365,0)) | U5: =IF(D5="","",N(E5)+N(Q5)+N(T5)) | V5: =IF(D5="","",IF(AND(J5="73",VALUE(LEFT(D5,4))<=2019),"Eligible if tax paid by 31-Mar-2025","No"))
A6: 5 | C6: =IF(B6="","",IFERROR(INDEX('Rule Matrix'!$C$2:$C$142,MATCH(B6,'Rule Matrix'!$A$2:$A$142,0)),"Rule ID not found")) | I6: =IF(D6="","",IF(OR(F6="Y",G6="Y",H6="Y"),"Fraud","Non-fraud")) | J6: =IF(D6="","",IF(VALUE(LEFT(D6,4))<=2023,IF(I6="Fraud","74","73"),"74A")) | K6: =IF(D6="","",INDEX('Limitation Inputs'!$B$2:$B$10,MATCH(D6,'Limitation Inputs'!$A$2:$A$10,0))) | L6: =IF(D6="","",IF(J6="74A",EDATE(K6,42),IF(J6="73",EDATE(M6,-3),EDATE(M6,-6)))) | M6: =IF(D6="","",IF(J6="73",IF(INDEX('Limitation Inputs'!$C$2:$C$10,MATCH(D6,'Limitation Inputs'!$A$2:$A$10,0))>0,INDEX('Limitation Inputs'!$C$2:$C$10,MATCH(D6,'Limitation Inputs'!$A$2:$A$10,0)),EDATE(K6,36)),IF(J6="74",EDATE(K6,60),EDATE(L6,12)))) | N6: =IF(D6="","",IF(AND(J6="74A",N(E6)<1000),"Below ₹1,000 – no SCN",IF('Limitation Inputs'!$B$13>M6,"Order time-barred",IF('Limitation Inputs'!$B$13>L6,"SCN time-barred","Open")))&IF(AND(J6="73",VALUE(LEFT(D6,4))<=2019)," | 168A ext. sub judice","")) | P6: =IF(OR(D6="",O6=""),"",IF(I6="Non-fraud",IF(OR(O6="Before SCN",O6="Within window of SCN"),0,0.1),IF(O6="Before SCN",0.15,IF(O6="Within window of SCN",0.25,IF(O6="Within window of order",0.5,1))))) | Q6: =IF(P6="","",IF(AND(I6="Non-fraud",P6>0),MAX(E6*P6,10000),E6*P6)) | T6: =IF(OR(R6="",S6="",E6=""),"",ROUND(E6*'Limitation Inputs'!$B$12*(S6-R6)/365,0)) | U6: =IF(D6="","",N(E6)+N(Q6)+N(T6)) | V6: =IF(D6="","",IF(AND(J6="73",VALUE(LEFT(D6,4))<=2019),"Eligible if tax paid by 31-Mar-2025","No"))
A7: 6 | C7: =IF(B7="","",IFERROR(INDEX('Rule Matrix'!$C$2:$C$142,MATCH(B7,'Rule Matrix'!$A$2:$A$142,0)),"Rule ID not found")) | I7: =IF(D7="","",IF(OR(F7="Y",G7="Y",H7="Y"),"Fraud","Non-fraud")) | J7: =IF(D7="","",IF(VALUE(LEFT(D7,4))<=2023,IF(I7="Fraud","74","73"),"74A")) | K7: =IF(D7="","",INDEX('Limitation Inputs'!$B$2:$B$10,MATCH(D7,'Limitation Inputs'!$A$2:$A$10,0))) | L7: =IF(D7="","",IF(J7="74A",EDATE(K7,42),IF(J7="73",EDATE(M7,-3),EDATE(M7,-6)))) | M7: =IF(D7="","",IF(J7="73",IF(INDEX('Limitation Inputs'!$C$2:$C$10,MATCH(D7,'Limitation Inputs'!$A$2:$A$10,0))>0,INDEX('Limitation Inputs'!$C$2:$C$10,MATCH(D7,'Limitation Inputs'!$A$2:$A$10,0)),EDATE(K7,36)),IF(J7="74",EDATE(K7,60),EDATE(L7,12)))) | N7: =IF(D7="","",IF(AND(J7="74A",N(E7)<1000),"Below ₹1,000 – no SCN",IF('Limitation Inputs'!$B$13>M7,"Order time-barred",IF('Limitation Inputs'!$B$13>L7,"SCN time-barred","Open")))&IF(AND(J7="73",VALUE(LEFT(D7,4))<=2019)," | 168A ext. sub judice","")) | P7: =IF(OR(D7="",O7=""),"",IF(I7="Non-fraud",IF(OR(O7="Before SCN",O7="Within window of SCN"),0,0.1),IF(O7="Before SCN",0.15,IF(O7="Within window of SCN",0.25,IF(O7="Within window of order",0.5,1))))) | Q7: =IF(P7="","",IF(AND(I7="Non-fraud",P7>0),MAX(E7*P7,10000),E7*P7)) | T7: =IF(OR(R7="",S7="",E7=""),"",ROUND(E7*'Limitation Inputs'!$B$12*(S7-R7)/365,0)) | U7: =IF(D7="","",N(E7)+N(Q7)+N(T7)) | V7: =IF(D7="","",IF(AND(J7="73",VALUE(LEFT(D7,4))<=2019),"Eligible if tax paid by 31-Mar-2025","No"))
A8: 7 | C8: =IF(B8="","",IFERROR(INDEX('Rule Matrix'!$C$2:$C$142,MATCH(B8,'Rule Matrix'!$A$2:$A$142,0)),"Rule ID not found")) | I8: =IF(D8="","",IF(OR(F8="Y",G8="Y",H8="Y"),"Fraud","Non-fraud")) | J8: =IF(D8="","",IF(VALUE(LEFT(D8,4))<=2023,IF(I8="Fraud","74","73"),"74A")) | K8: =IF(D8="","",INDEX('Limitation Inputs'!$B$2:$B$10,MATCH(D8,'Limitation Inputs'!$A$2:$A$10,0))) | L8: =IF(D8="","",IF(J8="74A",EDATE(K8,42),IF(J8="73",EDATE(M8,-3),EDATE(M8,-6)))) | M8: =IF(D8="","",IF(J8="73",IF(INDEX('Limitation Inputs'!$C$2:$C$10,MATCH(D8,'Limitation Inputs'!$A$2:$A$10,0))>0,INDEX('Limitation Inputs'!$C$2:$C$10,MATCH(D8,'Limitation Inputs'!$A$2:$A$10,0)),EDATE(K8,36)),IF(J8="74",EDATE(K8,60),EDATE(L8,12)))) | N8: =IF(D8="","",IF(AND(J8="74A",N(E8)<1000),"Below ₹1,000 – no SCN",IF('Limitation Inputs'!$B$13>M8,"Order time-barred",IF('Limitation Inputs'!$B$13>L8,"SCN time-barred","Open")))&IF(AND(J8="73",VALUE(LEFT(D8,4))<=2019)," | 168A ext. sub judice","")) | P8: =IF(OR(D8="",O8=""),"",IF(I8="Non-fraud",IF(OR(O8="Before SCN",O8="Within window of SCN"),0,0.1),IF(O8="Before SCN",0.15,IF(O8="Within window of SCN",0.25,IF(O8="Within window of order",0.5,1))))) | Q8: =IF(P8="","",IF(AND(I8="Non-fraud",P8>0),MAX(E8*P8,10000),E8*P8)) | T8: =IF(OR(R8="",S8="",E8=""),"",ROUND(E8*'Limitation Inputs'!$B$12*(S8-R8)/365,0)) | U8: =IF(D8="","",N(E8)+N(Q8)+N(T8)) | V8: =IF(D8="","",IF(AND(J8="73",VALUE(LEFT(D8,4))<=2019),"Eligible if tax paid by 31-Mar-2025","No"))
A9: 8 | C9: =IF(B9="","",IFERROR(INDEX('Rule Matrix'!$C$2:$C$142,MATCH(B9,'Rule Matrix'!$A$2:$A$142,0)),"Rule ID not found")) | I9: =IF(D9="","",IF(OR(F9="Y",G9="Y",H9="Y"),"Fraud","Non-fraud")) | J9: =IF(D9="","",IF(VALUE(LEFT(D9,4))<=2023,IF(I9="Fraud","74","73"),"74A")) | K9: =IF(D9="","",INDEX('Limitation Inputs'!$B$2:$B$10,MATCH(D9,'Limitation Inputs'!$A$2:$A$10,0))) | L9: =IF(D9="","",IF(J9="74A",EDATE(K9,42),IF(J9="73",EDATE(M9,-3),EDATE(M9,-6)))) | M9: =IF(D9="","",IF(J9="73",IF(INDEX('Limitation Inputs'!$C$2:$C$10,MATCH(D9,'Limitation Inputs'!$A$2:$A$10,0))>0,INDEX('Limitation Inputs'!$C$2:$C$10,MATCH(D9,'Limitation Inputs'!$A$2:$A$10,0)),EDATE(K9,36)),IF(J9="74",EDATE(K9,60),EDATE(L9,12)))) | N9: =IF(D9="","",IF(AND(J9="74A",N(E9)<1000),"Below ₹1,000 – no SCN",IF('Limitation Inputs'!$B$13>M9,"Order time-barred",IF('Limitation Inputs'!$B$13>L9,"SCN time-barred","Open")))&IF(AND(J9="73",VALUE(LEFT(D9,4))<=2019)," | 168A ext. sub judice","")) | P9: =IF(OR(D9="",O9=""),"",IF(I9="Non-fraud",IF(OR(O9="Before SCN",O9="Within window of SCN"),0,0.1),IF(O9="Before SCN",0.15,IF(O9="Within window of SCN",0.25,IF(O9="Within window of order",0.5,1))))) | Q9: =IF(P9="","",IF(AND(I9="Non-fraud",P9>0),MAX(E9*P9,10000),E9*P9)) | T9: =IF(OR(R9="",S9="",E9=""),"",ROUND(E9*'Limitation Inputs'!$B$12*(S9-R9)/365,0)) | U9: =IF(D9="","",N(E9)+N(Q9)+N(T9)) | V9: =IF(D9="","",IF(AND(J9="73",VALUE(LEFT(D9,4))<=2019),"Eligible if tax paid by 31-Mar-2025","No"))
A10: 9 | C10: =IF(B10="","",IFERROR(INDEX('Rule Matrix'!$C$2:$C$142,MATCH(B10,'Rule Matrix'!$A$2:$A$142,0)),"Rule ID not found")) | I10: =IF(D10="","",IF(OR(F10="Y",G10="Y",H10="Y"),"Fraud","Non-fraud")) | J10: =IF(D10="","",IF(VALUE(LEFT(D10,4))<=2023,IF(I10="Fraud","74","73"),"74A")) | K10: =IF(D10="","",INDEX('Limitation Inputs'!$B$2:$B$10,MATCH(D10,'Limitation Inputs'!$A$2:$A$10,0))) | L10: =IF(D10="","",IF(J10="74A",EDATE(K10,42),IF(J10="73",EDATE(M10,-3),EDATE(M10,-6)))) | M10: =IF(D10="","",IF(J10="73",IF(INDEX('Limitation Inputs'!$C$2:$C$10,MATCH(D10,'Limitation Inputs'!$A$2:$A$10,0))>0,INDEX('Limitation Inputs'!$C$2:$C$10,MATCH(D10,'Limitation Inputs'!$A$2:$A$10,0)),EDATE(K10,36)),IF(J10="74",EDATE(K10,60),EDATE(L10,12)))) | N10: =IF(D10="","",IF(AND(J10="74A",N(E10)<1000),"Below ₹1,000 – no SCN",IF('Limitation Inputs'!$B$13>M10,"Order time-barred",IF('Limitation Inputs'!$B$13>L10,"SCN time-barred","Open")))&IF(AND(J10="73",VALUE(LEFT(D10,4))<=2019)," | 168A ext. sub judice","")) | P10: =IF(OR(D10="",O10=""),"",IF(I10="Non-fraud",IF(OR(O10="Before SCN",O10="Within window of SCN"),0,0.1),IF(O10="Before SCN",0.15,IF(O10="Within window of SCN",0.25,IF(O10="Within window of order",0.5,1))))) | Q10: =IF(P10="","",IF(AND(I10="Non-fraud",P10>0),MAX(E10*P10,10000),E10*P10)) | T10: =IF(OR(R10="",S10="",E10=""),"",ROUND(E10*'Limitation Inputs'!$B$12*(S10-R10)/365,0)) | U10: =IF(D10="","",N(E10)+N(Q10)+N(T10)) | V10: =IF(D10="","",IF(AND(J10="73",VALUE(LEFT(D10,4))<=2019),"Eligible if tax paid by 31-Mar-2025","No"))
A11: 10 | C11: =IF(B11="","",IFERROR(INDEX('Rule Matrix'!$C$2:$C$142,MATCH(B11,'Rule Matrix'!$A$2:$A$142,0)),"Rule ID not found")) | I11: =IF(D11="","",IF(OR(F11="Y",G11="Y",H11="Y"),"Fraud","Non-fraud")) | J11: =IF(D11="","",IF(VALUE(LEFT(D11,4))<=2023,IF(I11="Fraud","74","73"),"74A")) | K11: =IF(D11="","",INDEX('Limitation Inputs'!$B$2:$B$10,MATCH(D11,'Limitation Inputs'!$A$2:$A$10,0))) | L11: =IF(D11="","",IF(J11="74A",EDATE(K11,42),IF(J11="73",EDATE(M11,-3),EDATE(M11,-6)))) | M11: =IF(D11="","",IF(J11="73",IF(INDEX('Limitation Inputs'!$C$2:$C$10,MATCH(D11,'Limitation Inputs'!$A$2:$A$10,0))>0,INDEX('Limitation Inputs'!$C$2:$C$10,MATCH(D11,'Limitation Inputs'!$A$2:$A$10,0)),EDATE(K11,36)),IF(J11="74",EDATE(K11,60),EDATE(L11,12)))) | N11: =IF(D11="","",IF(AND(J11="74A",N(E11)<1000),"Below ₹1,000 – no SCN",IF('Limitation Inputs'!$B$13>M11,"Order time-barred",IF('Limitation Inputs'!$B$13>L11,"SCN time-barred","Open")))&IF(AND(J11="73",VALUE(LEFT(D11,4))<=2019)," | 168A ext. sub judice","")) | P11: =IF(OR(D11="",O11=""),"",IF(I11="Non-fraud",IF(OR(O11="Before SCN",O11="Within window of SCN"),0,0.1),IF(O11="Before SCN",0.15,IF(O11="Within window of SCN",0.25,IF(O11="Within window of order",0.5,1))))) | Q11: =IF(P11="","",IF(AND(I11="Non-fraud",P11>0),MAX(E11*P11,10000),E11*P11)) | T11: =IF(OR(R11="",S11="",E11=""),"",ROUND(E11*'Limitation Inputs'!$B$12*(S11-R11)/365,0)) | U11: =IF(D11="","",N(E11)+N(Q11)+N(T11)) | V11: =IF(D11="","",IF(AND(J11="73",VALUE(LEFT(D11,4))<=2019),"Eligible if tax paid by 31-Mar-2025","No"))
A12: 11 | C12: =IF(B12="","",IFERROR(INDEX('Rule Matrix'!$C$2:$C$142,MATCH(B12,'Rule Matrix'!$A$2:$A$142,0)),"Rule ID not found")) | I12: =IF(D12="","",IF(OR(F12="Y",G12="Y",H12="Y"),"Fraud","Non-fraud")) | J12: =IF(D12="","",IF(VALUE(LEFT(D12,4))<=2023,IF(I12="Fraud","74","73"),"74A")) | K12: =IF(D12="","",INDEX('Limitation Inputs'!$B$2:$B$10,MATCH(D12,'Limitation Inputs'!$A$2:$A$10,0))) | L12: =IF(D12="","",IF(J12="74A",EDATE(K12,42),IF(J12="73",EDATE(M12,-3),EDATE(M12,-6)))) | M12: =IF(D12="","",IF(J12="73",IF(INDEX('Limitation Inputs'!$C$2:$C$10,MATCH(D12,'Limitation Inputs'!$A$2:$A$10,0))>0,INDEX('Limitation Inputs'!$C$2:$C$10,MATCH(D12,'Limitation Inputs'!$A$2:$A$10,0)),EDATE(K12,36)),IF(J12="74",EDATE(K12,60),EDATE(L12,12)))) | N12: =IF(D12="","",IF(AND(J12="74A",N(E12)<1000),"Below ₹1,000 – no SCN",IF('Limitation Inputs'!$B$13>M12,"Order time-barred",IF('Limitation Inputs'!$B$13>L12,"SCN time-barred","Open")))&IF(AND(J12="73",VALUE(LEFT(D12,4))<=2019)," | 168A ext. sub judice","")) | P12: =IF(OR(D12="",O12=""),"",IF(I12="Non-fraud",IF(OR(O12="Before SCN",O12="Within window of SCN"),0,0.1),IF(O12="Before SCN",0.15,IF(O12="Within window of SCN",0.25,IF(O12="Within window of order",0.5,1))))) | Q12: =IF(P12="","",IF(AND(I12="Non-fraud",P12>0),MAX(E12*P12,10000),E12*P12)) | T12: =IF(OR(R12="",S12="",E12=""),"",ROUND(E12*'Limitation Inputs'!$B$12*(S12-R12)/365,0)) | U12: =IF(D12="","",N(E12)+N(Q12)+N(T12)) | V12: =IF(D12="","",IF(AND(J12="73",VALUE(LEFT(D12,4))<=2019),"Eligible if tax paid by 31-Mar-2025","No"))
A13: 12 | C13: =IF(B13="","",IFERROR(INDEX('Rule Matrix'!$C$2:$C$142,MATCH(B13,'Rule Matrix'!$A$2:$A$142,0)),"Rule ID not found")) | I13: =IF(D13="","",IF(OR(F13="Y",G13="Y",H13="Y"),"Fraud","Non-fraud")) | J13: =IF(D13="","",IF(VALUE(LEFT(D13,4))<=2023,IF(I13="Fraud","74","73"),"74A")) | K13: =IF(D13="","",INDEX('Limitation Inputs'!$B$2:$B$10,MATCH(D13,'Limitation Inputs'!$A$2:$A$10,0))) | L13: =IF(D13="","",IF(J13="74A",EDATE(K13,42),IF(J13="73",EDATE(M13,-3),EDATE(M13,-6)))) | M13: =IF(D13="","",IF(J13="73",IF(INDEX('Limitation Inputs'!$C$2:$C$10,MATCH(D13,'Limitation Inputs'!$A$2:$A$10,0))>0,INDEX('Limitation Inputs'!$C$2:$C$10,MATCH(D13,'Limitation Inputs'!$A$2:$A$10,0)),EDATE(K13,36)),IF(J13="74",EDATE(K13,60),EDATE(L13,12)))) | N13: =IF(D13="","",IF(AND(J13="74A",N(E13)<1000),"Below ₹1,000 – no SCN",IF('Limitation Inputs'!$B$13>M13,"Order time-barred",IF('Limitation Inputs'!$B$13>L13,"SCN time-barred","Open")))&IF(AND(J13="73",VALUE(LEFT(D13,4))<=2019)," | 168A ext. sub judice","")) | P13: =IF(OR(D13="",O13=""),"",IF(I13="Non-fraud",IF(OR(O13="Before SCN",O13="Within window of SCN"),0,0.1),IF(O13="Before SCN",0.15,IF(O13="Within window of SCN",0.25,IF(O13="Within window of order",0.5,1))))) | Q13: =IF(P13="","",IF(AND(I13="Non-fraud",P13>0),MAX(E13*P13,10000),E13*P13)) | T13: =IF(OR(R13="",S13="",E13=""),"",ROUND(E13*'Limitation Inputs'!$B$12*(S13-R13)/365,0)) | U13: =IF(D13="","",N(E13)+N(Q13)+N(T13)) | V13: =IF(D13="","",IF(AND(J13="73",VALUE(LEFT(D13,4))<=2019),"Eligible if tax paid by 31-Mar-2025","No"))
A14: 13 | C14: =IF(B14="","",IFERROR(INDEX('Rule Matrix'!$C$2:$C$142,MATCH(B14,'Rule Matrix'!$A$2:$A$142,0)),"Rule ID not found")) | I14: =IF(D14="","",IF(OR(F14="Y",G14="Y",H14="Y"),"Fraud","Non-fraud")) | J14: =IF(D14="","",IF(VALUE(LEFT(D14,4))<=2023,IF(I14="Fraud","74","73"),"74A")) | K14: =IF(D14="","",INDEX('Limitation Inputs'!$B$2:$B$10,MATCH(D14,'Limitation Inputs'!$A$2:$A$10,0))) | L14: =IF(D14="","",IF(J14="74A",EDATE(K14,42),IF(J14="73",EDATE(M14,-3),EDATE(M14,-6)))) | M14: =IF(D14="","",IF(J14="73",IF(INDEX('Limitation Inputs'!$C$2:$C$10,MATCH(D14,'Limitation Inputs'!$A$2:$A$10,0))>0,INDEX('Limitation Inputs'!$C$2:$C$10,MATCH(D14,'Limitation Inputs'!$A$2:$A$10,0)),EDATE(K14,36)),IF(J14="74",EDATE(K14,60),EDATE(L14,12)))) | N14: =IF(D14="","",IF(AND(J14="74A",N(E14)<1000),"Below ₹1,000 – no SCN",IF('Limitation Inputs'!$B$13>M14,"Order time-barred",IF('Limitation Inputs'!$B$13>L14,"SCN time-barred","Open")))&IF(AND(J14="73",VALUE(LEFT(D14,4))<=2019)," | 168A ext. sub judice","")) | P14: =IF(OR(D14="",O14=""),"",IF(I14="Non-fraud",IF(OR(O14="Before SCN",O14="Within window of SCN"),0,0.1),IF(O14="Before SCN",0.15,IF(O14="Within window of SCN",0.25,IF(O14="Within window of order",0.5,1))))) | Q14: =IF(P14="","",IF(AND(I14="Non-fraud",P14>0),MAX(E14*P14,10000),E14*P14)) | T14: =IF(OR(R14="",S14="",E14=""),"",ROUND(E14*'Limitation Inputs'!$B$12*(S14-R14)/365,0)) | U14: =IF(D14="","",N(E14)+N(Q14)+N(T14)) | V14: =IF(D14="","",IF(AND(J14="73",VALUE(LEFT(D14,4))<=2019),"Eligible if tax paid by 31-Mar-2025","No"))
... A26: 25 | C26: =IF(B26="","",IFERROR(INDEX('Rule Matrix'!$C$2:$C$142,MATCH(B26,'Rule Matrix'!$A$2:$A$142,0)),"Rule ID not found")) | I26: =IF(D26="","",IF(OR(F26="Y",G26="Y",H26="Y"),"Fraud","Non-fraud")) | J26: =IF(D26="","",IF(VALUE(LEFT(D26,4))<=2023,IF(I26="Fraud","74","73"),"74A")) | K26: =IF(D26="","",INDEX('Limitation Inputs'!$B$2:$B$10,MATCH(D26,'Limitation Inputs'!$A$2:$A$10,0))) | L26: =IF(D26="","",IF(J26="74A",EDATE(K26,42),IF(J26="73",EDATE(M26,-3),EDATE(M26,-6)))) | M26: =IF(D26="","",IF(J26="73",IF(INDEX('Limitation Inputs'!$C$2:$C$10,MATCH(D26,'Limitation Inputs'!$A$2:$A$10,0))>0,INDEX('Limitation Inputs'!$C$2:$C$10,MATCH(D26,'Limitation Inputs'!$A$2:$A$10,0)),EDATE(K26,36)),IF(J26="74",EDATE(K26,60),EDATE(L26,12)))) | N26: =IF(D26="","",IF(AND(J26="74A",N(E26)<1000),"Below ₹1,000 – no SCN",IF('Limitation Inputs'!$B$13>M26,"Order time-barred",IF('Limitation Inputs'!$B$13>L26,"SCN time-barred","Open")))&IF(AND(J26="73",VALUE(LEFT(D26,4))<=2019)," | 168A ext. sub judice","")) | P26: =IF(OR(D26="",O26=""),"",IF(I26="Non-fraud",IF(OR(O26="Before SCN",O26="Within window of SCN"),0,0.1),IF(O26="Before SCN",0.15,IF(O26="Within window of SCN",0.25,IF(O26="Within window of order",0.5,1))))) | Q26: =IF(P26="","",IF(AND(I26="Non-fraud",P26>0),MAX(E26*P26,10000),E26*P26)) | T26: =IF(OR(R26="",S26="",E26=""),"",ROUND(E26*'Limitation Inputs'!$B$12*(S26-R26)/365,0)) | U26: =IF(D26="","",N(E26)+N(Q26)+N(T26)) | V26: =IF(D26="","",IF(AND(J26="73",VALUE(LEFT(D26,4))<=2019),"Eligible if tax paid by 31-Mar-2025","No"))
A28: Notes:
A29: Section: FY ≤ 2023-24 → s.73 / s.74; FY ≥ 2024-25 → s.74A (single section, fraud & non-fraud limbs).
A30: Windows: 30 days for s.73/74; 60 days for s.74A.
A31: Limitation: 73 – order 3 yrs from AR due date, SCN 3 months prior; 74 – order 5 yrs, SCN 6 months prior; 74A – SCN 42 months, order 12 months from SCN (extendable 6 months; deadline shown excludes extension).
A32: Penalty: Non-fraud – nil if paid before/within window of SCN, else higher of 10% or ₹10,000. Fraud – 15% / 25% / 50% / 100%.
A33: Interest: simple 18% on tax from due date to payment (s.50); for wrong ITC only from utilisation (Rule 88B) – adjust 'Interest From' date.
A34: Erroneous refunds: limitation from refund order date – compute manually. Fraud classification is indicative; final view depends on evidence.

Sheet Applicability
A1: Rule ID | B1: Module | C1: Check | D1: Client Flag Required | E1: Real Estate Developer | F1: Works Contractor | G1: Manufacturer | H1: Trader / Retailer | I1: Service Provider | J1: Exporter | K1: Bank / NBFC / Co-op Bank | L1: Hotel / Restaurant | M1: GTA / Logistics | N1: E-commerce Seller | O1: Education / Charitable / Healthcare
A2: A-01 | B2: A. Data Integrity | C2: GSTIN master validation | E2: Y | F2: Y | G2: Y | H2: Y | I2: Y | J2: Y | K2: Y | L2: Y | M2: Y | N2: Y | O2: Y
A3: A-02 | B3: A. Data Integrity | C3: Period & return filing completeness | E3: Y | F3: Y | G3: Y | H3: Y | I3: Y | J3: Y | K3: Y | L3: Y | M3: Y | N3: Y | O3: Y
A4: A-03 | B4: A. Data Integrity | C4: Books vs return data completeness | E4: Y | F4: Y | G4: Y | H4: Y | I4: Y | J4: Y | K4: Y | L4: Y | M4: Y | N4: Y | O4: Y
A5: B-01 | B5: B. ITC Eligibility (s.16) | C5: ITC claimed vs GSTR-2B | E5: Y | F5: Y | G5: Y | H5: Y | I5: Y | J5: Y | K5: Y | L5: Y | M5: Y | N5: Y | O5: Y
A6: B-02 | B6: B. ITC Eligibility (s.16) | C6: ITC in books but not in 2B | E6: Y | F6: Y | G6: Y | H6: Y | I6: Y | J6: Y | K6: Y | L6: Y | M6: Y | N6: Y | O6: Y
A7: B-03 | B7: B. ITC Eligibility (s.16) | C7: Receipt of goods/services | E7: Y | F7: Y | G7: Y | H7: Y | I7: Y | J7: Y | K7: Y | L7: Y | M7: Y | N7: Y | O7: Y
A8: B-04 | B8: B. ITC Eligibility (s.16) | C8: Supplier tax payment (Rule 37A) | E8: Y | F8: Y | G8: Y | H8: Y | I8: Y | J8: Y | K8: Y | L8: Y | M8: Y | N8: Y | O8: Y
A9: B-05 | B9: B. ITC Eligibility (s.16) | C9: Payment within 180 days | E9: Y | F9: Y | G9: Y | H9: Y | I9: Y | J9: Y | K9: Y | L9: Y | M9: Y | N9: Y | O9: Y
A10: B-06 | B10: B. ITC Eligibility (s.16) | C10: Depreciation on tax component | E10: Y | F10: Y | G10: Y | H10: Y | I10: Y | J10: Y | K10: Y | L10: Y | M10: Y | N10: Y | O10: Y
A11: B-07 | B11: B. ITC Eligibility (s.16) | C11: Time limit for ITC | E11: Y | F11: Y | G11: Y | H11: Y | I11: Y | J11: Y | K11: Y | L11: Y | M11: Y | N11: Y | O11: Y
A12: B-08 | B12: B. ITC Eligibility (s.16) | C12: Duplicate ITC | E12: Y | F12: Y | G12: Y | H12: Y | I12: Y | J12: Y | K12: Y | L12: Y | M12: Y | N12: Y | O12: Y
A13: B-09 | B13: B. ITC Eligibility (s.16) | C13: Import IGST | D13: Imports | E13: Y | F13: Y | G13: Y | H13: Y | I13: Y | J13: Y | K13: Y | L13: Y | M13: Y | N13: Y | O13: Y
A14: B-10 | B14: B. ITC Eligibility (s.16) | C14: ITC on invoices from cancelled/composition vendors | E14: Y | F14: Y | G14: Y | H14: Y | I14: Y | J14: Y | K14: Y | L14: Y | M14: Y | N14: Y | O14: Y
A15: B-11 | B15: B. ITC Eligibility (s.16) | C15: Document validity | E15: Y | F15: Y | G15: Y | H15: Y | I15: Y | J15: Y | K15: Y | L15: Y | M15: Y | N15: Y | O15: Y
A16: C-01 | B16: C. RCM | C16: RCM liability identification | E16: Y | F16: Y | G16: Y | H16: Y | I16: Y | J16: Y | K16: Y | L16: Y | M16: Y | N16: Y | O16: Y
A17: C-02 | B17: C. RCM | C17: RCM ITC after payment | E17: Y | F17: Y | G17: Y | H17: Y | I17: Y | J17: Y | K17: Y | L17: Y | M17: Y | N17: Y | O17: Y
A18: C-03 | B18: C. RCM | C18: RCM self-invoice | E18: Y | F18: Y | G18: Y | H18: Y | I18: Y | J18: Y | K18: Y | L18: Y | M18: Y | N18: Y | O18: Y
A19: C-04 | B19: C. RCM | C19: Import of services | D19: Imports | E19: Y | F19: Y | G19: Y | H19: Y | I19: Y | J19: Y | K19: Y | L19: Y | M19: Y | N19: Y | O19: Y
A20: C-05 | B20: C. RCM | C20: Metal scrap from unregistered & TDS on scrap | E20: N | F20: N | G20: Y | H20: Y | I20: N | J20: N | K20: N | L20: N | M20: N | N20: N | O20: N
A21: D-01 | B21: D. Place of Supply | C21: Tax head vs state codes | E21: Y | F21: Y | G21: Y | H21: Y | I21: Y | J21: Y | K21: Y | L21: Y | M21: Y | N21: Y | O21: Y
A22: D-02 | B22: D. Place of Supply | C22: Hotel/immovable property services | E22: Y | F22: Y | G22: Y | H22: Y | I22: Y | J22: Y | K22: Y | L22: Y | M22: Y | N22: Y | O22: Y
A23: D-03 | B23: D. Place of Supply | C23: Restaurant/catering, training, events | E23: Y | F23: Y | G23: Y | H23: Y | I23: Y | J23: Y | K23: Y | L23: Y | M23: Y | N23: Y | O23: Y
A24: D-04 | B24: D. Place of Supply | C24: Goods transport / passenger transport | E24: Y | F24: Y | G24: Y | H24: Y | I24: Y | J24: Y | K24: Y | L24: Y | M24: Y | N24: Y | O24: Y
A25: D-05 | B25: D. Place of Supply | C25: Bill-to-ship-to goods | E25: Y | F25: Y | G25: Y | H25: Y | I25: Y | J25: Y | K25: Y | L25: Y | M25: Y | N25: Y | O25: Y
A26: D-06 | B26: D. Place of Supply | C26: B2C recipient address | E26: Y | F26: Y | G26: Y | H26: Y | I26: Y | J26: Y | K26: Y | L26: Y | M26: Y | N26: Y | O26: Y
A27: D-07 | B27: D. Place of Supply | C27: Export of services conditions | D27: Exports | E27: Y | F27: Y | G27: Y | H27: Y | I27: Y | J27: Y | K27: Y | L27: Y | M27: Y | N27: Y | O27: Y
A28: D-08 | B28: D. Place of Supply | C28: SEZ supplies | D28: SEZ Supplies | E28: Y | F28: Y | G28: Y | H28: Y | I28: Y | J28: Y | K28: Y | L28: Y | M28: Y | N28: Y | O28: Y
A29: E-01 | B29: E. Blocked Credits s.17(5) | C29: Motor vehicles ≤13 seats | E29: Y | F29: Y | G29: Y | H29: Y | I29: Y | J29: Y | K29: Y | L29: Y | M29: Y | N29: Y | O29: Y
A30: E-02 | B30: E. Blocked Credits s.17(5) | C30: Vessels & aircraft | E30: Y | F30: Y | G30: Y | H30: Y | I30: Y | J30: Y | K30: Y | L30: Y | M30: Y | N30: Y | O30: Y
A31: E-03 | B31: E. Blocked Credits s.17(5) | C31: Food, beverages, outdoor catering | E31: Y | F31: Y | G31: Y | H31: Y | I31: Y | J31: Y | K31: Y | L31: Y | M31: Y | N31: Y | O31: Y
A32: E-04 | B32: E. Blocked Credits s.17(5) | C32: Beauty, health, cosmetic surgery | E32: Y | F32: Y | G32: Y | H32: Y | I32: Y | J32: Y | K32: Y | L32: Y | M32: Y | N32: Y | O32: Y
A33: E-05 | B33: E. Blocked Credits s.17(5) | C33: Life & health insurance | E33: Y | F33: Y | G33: Y | H33: Y | I33: Y | J33: Y | K33: Y | L33: Y | M33: Y | N33: Y | O33: Y
A34: E-06 | B34: E. Blocked Credits s.17(5) | C34: Club / fitness membership | E34: Y | F34: Y | G34: Y | H34: Y | I34: Y | J34: Y | K34: Y | L34: Y | M34: Y | N34: Y | O34: Y
A35: E-07 | B35: E. Blocked Credits s.17(5) | C35: Rent-a-cab | E35: Y | F35: Y | G35: Y | H35: Y | I35: Y | J35: Y | K35: Y | L35: Y | M35: Y | N35: Y | O35: Y
A36: E-08 | B36: E. Blocked Credits s.17(5) | C36: Employee travel benefits (LTC/vacation) | E36: Y | F36: Y | G36: Y | H36: Y | I36: Y | J36: Y | K36: Y | L36: Y | M36: Y | N36: Y | O36: Y
A37: E-09 | B37: E. Blocked Credits s.17(5) | C37: Works contract – immovable property | E37: Y | F37: Y | G37: Y | H37: Y | I37: Y | J37: Y | K37: Y | L37: Y | M37: Y | N37: Y | O37: Y
A38: E-10 | B38: E. Blocked Credits s.17(5) | C38: Construction on own account | E38: Y | F38: Y | G38: Y | H38: Y | I38: Y | J38: Y | K38: Y | L38: Y | M38: Y | N38: Y | O38: Y
A39: E-11 | B39: E. Blocked Credits s.17(5) | C39: Composition tax / NRTP | E39: Y | F39: Y | G39: Y | H39: Y | I39: Y | J39: Y | K39: Y | L39: Y | M39: Y | N39: Y | O39: Y
A40: E-12 | B40: E. Blocked Credits s.17(5) | C40: CSR expenditure | E40: Y | F40: Y | G40: Y | H40: Y | I40: Y | J40: Y | K40: Y | L40: Y | M40: Y | N40: Y | O40: Y
... A49: F-06 | B49: F. Reversals & Apportionment | C49: Rule 86B cash payment | E49: Y | F49: Y | G49: Y | H49: Y | I49: Y | J49: Y | K49: Y | L49: Y | M49: Y | N49: Y | O49: Y
A50: F-07 | B50: F. Reversals & Apportionment | C50: ISD distribution | D50: Multi-GSTIN | E50: Y | F50: Y | G50: Y | H50: Y | I50: Y | J50: Y | K50: Y | L50: Y | M50: Y | N50: Y | O50: Y
A51: G-01 | B51: G. Outward Supplies | C51: Turnover reconciliation | E51: Y | F51: Y | G51: Y | H51: Y | I51: Y | J51: Y | K51: Y | L51: Y | M51: Y | N51: Y | O51: Y
A52: G-02 | B52: G. Outward Supplies | C52: GSTR-1 vs 3B liability | E52: Y | F52: Y | G52: Y | H52: Y | I52: Y | J52: Y | K52: Y | L52: Y | M52: Y | N52: Y | O52: Y
A53: G-03 | B53: G. Outward Supplies | C53: e-invoice vs GSTR-1 | D53: E-invoice | E53: Y | F53: Y | G53: Y | H53: Y | I53: Y | J53: Y | K53: Y | L53: Y | M53: Y | N53: Y | O53: Y
A54: G-04 | B54: G. Outward Supplies | C54: e-invoice applicability & 30-day limit | D54: E-invoice | E54: Y | F54: Y | G54: Y | H54: Y | I54: Y | J54: Y | K54: Y | L54: Y | M54: Y | N54: Y | O54: Y
A55: G-05 | B55: G. Outward Supplies | C55: E-way bill vs sales | E55: Y | F55: Y | G55: Y | H55: Y | I55: Y | J55: Y | K55: Y | L55: Y | M55: Y | N55: Y | O55: Y
A56: G-06 | B56: G. Outward Supplies | C56: Other income scan | E56: Y | F56: Y | G56: Y | H56: Y | I56: Y | J56: Y | K56: Y | L56: Y | M56: Y | N56: Y | O56: Y
A57: G-07 | B57: G. Outward Supplies | C57: Schedule I deemed supplies | E57: Y | F57: Y | G57: Y | H57: Y | I57: Y | J57: Y | K57: Y | L57: Y | M57: Y | N57: Y | O57: Y
A58: G-08 | B58: G. Outward Supplies | C58: Related party valuation | E58: Y | F58: Y | G58: Y | H58: Y | I58: Y | J58: Y | K58: Y | L58: Y | M58: Y | N58: Y | O58: Y
A59: G-09 | B59: G. Outward Supplies | C59: Advances received | E59: Y | F59: Y | G59: Y | H59: Y | I59: Y | J59: Y | K59: Y | L59: Y | M59: Y | N59: Y | O59: Y
A60: G-10 | B60: G. Outward Supplies | C60: Rate & HSN validation | E60: Y | F60: Y | G60: Y | H60: Y | I60: Y | J60: Y | K60: Y | L60: Y | M60: Y | N60: Y | O60: Y
A61: G-11 | B61: G. Outward Supplies | C61: Exempt/nil/non-GST classification | E61: Y | F61: Y | G61: Y | H61: Y | I61: Y | J61: Y | K61: Y | L61: Y | M61: Y | N61: Y | O61: Y
A62: G-12 | B62: G. Outward Supplies | C62: Invoice series gaps | E62: Y | F62: Y | G62: Y | H62: Y | I62: Y | J62: Y | K62: Y | L62: Y | M62: Y | N62: Y | O62: Y
A63: G-13 | B63: G. Outward Supplies | C63: Exports – LUT & realisation | D63: Exports | E63: Y | F63: Y | G63: Y | H63: Y | I63: Y | J63: Y | K63: Y | L63: Y | M63: Y | N63: Y | O63: Y
A64: G-14 | B64: G. Outward Supplies | C64: TDS/TCS credits vs turnover | E64: Y | F64: Y | G64: Y | H64: Y | I64: Y | J64: Y | K64: Y | L64: Y | M64: Y | N64: Y | O64: Y
A65: G-15 | B65: G. Outward Supplies | C65: Amendment time limit | E65: Y | F65: Y | G65: Y | H65: Y | I65: Y | J65: Y | K65: Y | L65: Y | M65: Y | N65: Y | O65: Y
A66: H-01 | B66: H. Credit & Debit Notes | C66: CN time limit | E66: Y | F66: Y | G66: Y | H66: Y | I66: Y | J66: Y | K66: Y | L66: Y | M66: Y | N66: Y | O66: Y
A67: H-02 | B67: H. Credit & Debit Notes | C67: CN linkage to invoice | E67: Y | F67: Y | G67: Y | H67: Y | I67: Y | J67: Y | K67: Y | L67: Y | M67: Y | N67: Y | O67: Y
A68: H-03 | B68: H. Credit & Debit Notes | C68: Recipient ITC reversal for tax reduction | E68: Y | F68: Y | G68: Y | H68: Y | I68: Y | J68: Y | K68: Y | L68: Y | M68: Y | N68: Y | O68: Y
A69: H-04 | B69: H. Credit & Debit Notes | C69: Post-sale discounts | E69: Y | F69: Y | G69: Y | H69: Y | I69: Y | J69: Y | K69: Y | L69: Y | M69: Y | N69: Y | O69: Y
A70: H-05 | B70: H. Credit & Debit Notes | C70: Books CN vs GST CN | E70: Y | F70: Y | G70: Y | H70: Y | I70: Y | J70: Y | K70: Y | L70: Y | M70: Y | N70: Y | O70: Y
A71: H-06 | B71: H. Credit & Debit Notes | C71: Purchase-side CNs | E71: Y | F71: Y | G71: Y | H71: Y | I71: Y | J71: Y | K71: Y | L71: Y | M71: Y | N71: Y | O71: Y
A72: H-07 | B72: H. Credit & Debit Notes | C72: Debit notes – ITC time limit | E72: Y | F72: Y | G72: Y | H72: Y | I72: Y | J72: Y | K72: Y | L72: Y | M72: Y | N72: Y | O72: Y
A73: H-08 | B73: H. Credit & Debit Notes | C73: Unusual CN pattern | E73: Y | F73: Y | G73: Y | H73: Y | I73: Y | J73: Y | K73: Y | L73: Y | M73: Y | N73: Y | O73: Y
A74: I-01 | B74: I. Annual Report Linkages | C74: Capex additions vs capital goods ITC | E74: Y | F74: Y | G74: Y | H74: Y | I74: Y | J74: Y | K74: Y | L74: Y | M74: Y | N74: Y | O74: Y
A75: I-02 | B75: I. Annual Report Linkages | C75: Expense heads vs 3CD cl.44 | E75: Y | F75: Y | G75: Y | H75: Y | I75: Y | J75: Y | K75: Y | L75: Y | M75: Y | N75: Y | O75: Y
... A121: L-25 | B121: L. Industry-Specific | C121: Cross-charge between distinct persons | E121: N | F121: N | G121: Y | H121: N | I121: Y | J121: N | K121: Y | L121: N | M121: N | N121: N | O121: N
A122: L-26 | B122: L. Industry-Specific | C122: Import of services from related party | D122: Imports | E122: N | F122: N | G122: Y | H122: N | I122: Y | J122: N | K122: N | L122: N | M122: N | N122: N | O122: N
A123: L-27 | B123: L. Industry-Specific | C123: Refund of accumulated ITC (LUT) | E123: N | F123: N | G123: N | H123: N | I123: N | J123: Y | K123: N | L123: N | M123: N | N123: N | O123: N
A124: L-28 | B124: L. Industry-Specific | C124: Export proceeds realisation | E124: N | F124: N | G124: N | H124: N | I124: N | J124: Y | K124: N | L124: N | M124: N | N124: N | O124: N
A125: L-29 | B125: L. Industry-Specific | C125: Merchant exporter concessional rate | E125: N | F125: N | G125: N | H125: N | I125: N | J125: Y | K125: N | L125: N | M125: N | N125: N | O125: N
A126: L-30 | B126: L. Industry-Specific | C126: Shipping bill vs GSTR-1 (Table 6A) | E126: N | F126: N | G126: N | H126: N | I126: N | J126: Y | K126: N | L126: N | M126: N | N126: N | O126: N
A127: L-31 | B127: L. Industry-Specific | C127: Exempt interest vs taxable fees | E127: N | F127: N | G127: N | H127: N | I127: N | J127: N | K127: Y | L127: N | M127: N | N127: N | O127: N
A128: L-32 | B128: L. Industry-Specific | C128: Bank-specific RCM | E128: N | F128: N | G128: N | H128: N | I128: N | J128: N | K128: Y | L128: N | M128: N | N128: N | O128: N
A129: L-33 | B129: L. Industry-Specific | C129: Repossessed assets & NPA security sale | E129: N | F129: N | G129: N | H129: N | I129: N | J129: N | K129: Y | L129: N | M129: N | N129: N | O129: N
A130: L-34 | B130: L. Industry-Specific | C130: Restaurant/accommodation rate option | E130: N | F130: N | G130: N | H130: N | I130: N | J130: N | K130: N | L130: Y | M130: N | N130: N | O130: N
A131: L-35 | B131: L. Industry-Specific | C131: Liquor (non-GST) sales & common ITC | E131: N | F131: N | G131: N | H131: N | I131: N | J131: N | K131: N | L131: Y | M131: N | N131: N | O131: N
A132: L-36 | B132: L. Industry-Specific | C132: ECO food delivery – s.9(5) | E132: N | F132: N | G132: N | H132: N | I132: N | J132: N | K132: N | L132: Y | M132: N | N132: N | O132: N
A133: L-37 | B133: L. Industry-Specific | C133: Banquets, events, outdoor catering | E133: N | F133: N | G133: N | H133: N | I133: N | J133: N | K133: N | L133: Y | M133: N | N133: N | O133: N
A134: L-38 | B134: L. Industry-Specific | C134: GTA forward charge option | E134: N | F134: N | G134: N | H134: N | I134: N | J134: N | K134: N | L134: N | M134: Y | N134: N | O134: N
... A142: L-46 | B142: L. Industry-Specific | C142: Predominantly exempt – Rule 42 reversal | E142: N | F142: N | G142: N | H142: N | I142: N | J142: N | K142: N | L142: N | M142: N | N142: N | O142: Y

Sheet Data Sources
A1: Source | B1: Key Fields | C1: Used in Modules
A2: GSTR-1 / 1A | B2: B2B/B2C/CDNR/Exports/HSN/Doc series | C2: A,D,G,H
A3: GSTR-3B | B3: 3.1 liability, 4 ITC avail/reversal, payment | C3: B,C,F,G,J
A4: GSTR-2A / 2B / IMS | B4: Vendor GSTIN, inv no, date, tax, CN, accept/reject | C4: B,H
A5: GSTR-9 / 9C | B5: Annual turnover, ITC, reconciliation | C5: G
A6: GSTR-6 / 7 / 8 | B6: ISD distribution, TDS, TCS | C6: F,G
A7: e-Invoice (IRN) & e-Way Bill | B7: IRN, doc value, EWB no, consignee | C7: B,G
A8: ICEGATE BoE | B8: BoE no, IGST, port | C8: B
A9: GSTIN master (API) | B9: Status, reg/cancel date, type | C9: A,B
A10: Purchase / Sales registers | B10: Invoice-level with GL head mapping | C10: All
A11: Trial balance & GL | B11: Expense/income heads, other income | C11: C,E,G
A12: Fixed asset register & CWIP | B12: Additions, disposals, GST capitalised | C12: B,E,F,I
... A17: Electronic ledgers & DRC-03 | B17: Cash/credit balances, payments | C17: J

Sheet Limitation Inputs
A1: FY | B1: Annual Return Due Date | C1: s.73 Order Deadline (COVID override) | D1: Source / Note
A2: 2017-18 | B2: 43866 | C2: 45291 | D2: GSTR-9 due date extended; Notfn 9/2023
A3: 2018-19 | B3: 44196 | C3: 45412 | D3: Notfn 56/2023
A4: 2019-20 | B4: 44286 | C4: 45535 | D4: Notfn 56/2023
A5: 2020-21 | B5: 44620 | D5: Extended due date
A6: 2021-22 | B6: 44926 | D6: Statutory
A7: 2022-23 | B7: 45291 | D7: Statutory
A8: 2023-24 | B8: 45657 | D8: Statutory
A9: 2024-25 | B9: 46022 | D9: Statutory – verify any extension
A10: 2025-26 | B10: 46387 | D10: Statutory – verify any extension
A12: Interest rate (s.50) | B12: 0.18
A13: Assessment as-of date | B13: =TODAY() -> 46286
A14: Blue = editable input. State-specific extensions (if any) to be overwritten.
